Workbook

Sheet Instruments
B1: Market Instruments · All input cells (blue) — do not modify
B3: OIS MONEY MARKET (Simple Interest, Act/360)
B4: Instrument | C4: Tenor | D4: Rate | E4: Description
B5: 3M SOFR | C5: 0.25 | D5: 0.0415
B6: 6M SOFR | C6: 0.5 | D6: 0.04
B7: OIS SWAPS (Annual Fixed vs Daily Compounded SOFR)
B8: Instrument | C8: Tenor | D8: Par Rate | E8: Description
B9: 1Y OIS | C9: 1 | D9: 0.038
B10: 2Y OIS | C10: 2 | D10: 0.037
B11: 3Y OIS | C11: 3 | D11: 0.0365
B12: 5Y OIS | C12: 5 | D12: 0.036
B13: 7Y OIS | C13: 7 | D13: 0.0358
B14: 10Y OIS | C14: 10 | D14: 0.0355
B17: SOFR FUTURES (Implies 3M SOFR forward rate per quarterly period)
B18: Contract | C18: T_start | D18: T_end | E18: Implied 3M Fwd | F18: Description
B19: Sep25 | C19: 0 | D19: 0.25 | E19: 0.044 | F19: 3M SOFR for Sep25
B20: Dec25 | C20: 0.25 | D20: 0.5 | E20: 0.0425 | F20: 3M SOFR for Dec25
B21: Mar26 | C21: 0.5 | D21: 0.75 | E21: 0.0408 | F21: 3M SOFR for Mar26
B22: Jun26 | C22: 0.75 | D22: 1 | E22: 0.0392 | F22: 3M SOFR for Jun26
B23: Sep26 | C23: 1 | D23: 1.25 | E23: 0.0382 | F23: 3M SOFR for Sep26
B24: Dec26 | C24: 1.25 | D24: 1.5 | E24: 0.0376 | F24: 3M SOFR for Dec26
B25: Mar27 | C25: 1.5 | D25: 1.75 | E25: 0.0372 | F25: 3M SOFR for Mar27
B26: Jun27 | C26: 1.75 | D26: 2 | E26: 0.037 | F26: 3M SOFR for Jun27
B27: 3M SOFR IRS (Quarterly Float vs Annual Fixed, used for 2Y+ projection curve)
B28: Instrument | C28: Tenor | D28: Par Rate | E28: Description
B29: 2Y SOFR IRS | C29: 2 | D29: 0.0371 | E29: 3M SOFR IRS 2Y par rate — used to bootstrap projection fwds beyond 2Y
B30: 3Y SOFR IRS | C30: 3 | D30: 0.0367 | E30: 3M SOFR IRS 3Y par rate — used to bootstrap projection fwds beyond 2Y
B31: 5Y SOFR IRS | C31: 5 | D31: 0.0364 | E31: 3M SOFR IRS 5Y par rate — used to bootstrap projection fwds beyond 2Y
B32: 7Y SOFR IRS | C32: 7 | D32: 0.0362 | E32: 3M SOFR IRS 7Y par rate — used to bootstrap projection fwds beyond 2Y
B33: 10Y SOFR IRS | C33: 10 | D33: 0.0359 | E33: 3M SOFR IRS 10Y par rate — used to bootstrap projection fwds beyond 2Y

Sheet OIS_Curve
B1: OIS Curve · Bootstrap → Discount Factors → Zero Rates → Quarterly Grid
B3: SECTION 1 — SEQUENTIAL OIS BOOTSTRAP (liquid & interpolated tenors)
B4: Tenor | C4: Type | D4: Instr Rate | E4: Discount Factor | F4: Zero Rate (cont) | G4: Formula / Note
B5: 0.25 | C5: MM | D5: =Instruments!$D$5 -> 0.0415 | E5: =1/(1+D5*B5) -> 0.98973154 | F5: =-LN(E5)/B5 -> 0.041286196 | G5: P = 1/(1+r·T) [simple interest, T=0.25]
B6: 0.5 | C6: MM | D6: =Instruments!$D$6 -> 0.04 | E6: =1/(1+D6*B6) -> 0.98039216 | F6: =-LN(E6)/B6 -> 0.039605255 | G6: P = 1/(1+r·T) [simple interest, T=0.50]
B7: 1 | C7: OIS Swap | D7: =Instruments!$D$9 -> 0.038 | E7: =1/(1+D7) -> 0.96339114 | F7: =-LN(E7)/B7 -> 0.037295785 | G7: P = 1/(1+S) [1Y swap: single payment, P(1)=1/(1+S)]
B8: 2 | C8: OIS Swap | D8: =Instruments!$D$10 -> 0.037 | E8: =(1-D8*E7)/(1+D8) -> 0.92994651 | F8: =-LN(E8)/B8 -> 0.036314107 | G8: P = (1-S·P1)/(1+S) [2Y bootstrap]
B9: 3 | C9: OIS Swap | D9: =Instruments!$D$11 -> 0.0365 | E9: =(1-D9*(E7+E8))/(1+D9) -> 0.89811208 | F9: =-LN(E9)/B9 -> 0.035820134 | G9: P = (1-S·(P1+P2))/(1+S) [3Y bootstrap]
B10: 4 | C10: Interp | D10: — | E10: =EXP(-F10*B10) -> 0.86619929 | F10: =F9+(Instruments!$D$12-F9)*(B10-B9)/(5-B9) -> 0.035910067 | G10: INTERP: z4 = z3 + (S5Y-z3)·(4-3)/(5-3) → P4 = EXP(-z4·4) [uses S5Y as proxy for z5]
B11: 5 | C11: OIS Swap | D11: =Instruments!$D$12 -> 0.036 | E11: =(1-D11*(E7+E8+E9+E10))/(1+D11) -> 0.83815119 | F11: =-LN(E11)/B11 -> 0.035311355 | G11: P = (1-S·(P1+P2+P3+P4))/(1+S) [5Y bootstrap using interpolated P4]
B12: 6 | C12: Interp | D12: — | E12: =EXP(-F12*B12) -> 0.80788621 | F12: =F11+(Instruments!$D$13-F11)*(B12-B11)/(7-B11) -> 0.035555677 | G12: INTERP: z6 = z5 + (S7Y-z5)·(6-5)/(7-5) → P6 = EXP(-z6·6)
B13: 7 | C13: OIS Swap | D13: =Instruments!$D$13 -> 0.0358 | E13: =(1-D13*(E7+E8+E9+E10+E11+E12))/(1+D13) -> 0.78212785 | F13: =-LN(E13)/B13 -> 0.035105295 | G13: P = (1-S·(P1+...+P6))/(1+S) [7Y bootstrap]
B14: 8 | C14: Interp | D14: — | E14: =EXP(-F14*B14) -> 0.75435296 | F14: =F13+(Instruments!$D$14-F13)*(B14-B13)/(10-B13) -> 0.035236863 | G14: INTERP: z8 = z7 + (S10Y-z7)·(8-7)/(10-7) → P8 = EXP(-z8·8)
B15: 9 | C15: Interp | D15: — | E15: =EXP(-F15*B15) -> 0.72737299 | F15: =F13+(Instruments!$D$14-F13)*(B15-B13)/(10-B13) -> 0.035368432 | G15: INTERP: z9 = z7 + (S10Y-z7)·(9-7)/(10-7) → P9 = EXP(-z9·9)
B16: 10 | C16: OIS Swap | D16: =Instruments!$D$14 -> 0.0355 | E16: =(1-D16*(E7+E8+E9+E10+E11+E12+E13+E14+E15))/(1+D16) -> 0.7062794 | F16: =-LN(E16)/B16 -> 0.034774436 | G16: P = (1-S·(P1+...+P9))/(1+S) [10Y bootstrap]
B17: SECTION 2 — QUARTERLY OUTPUT GRID (piecewise linear interp on zero rates)
B18: Tenor | C18: Zero Rate (interp) | D18: Discount Factor | E18: Inst. Fwd Rate | F18: 3M OIS Fwd | G18: Formula Key
B19: 0.25 | C19: =INDEX($F$5:$F$16,MIN(MATCH(B19,$B$5:$B$16,1),11))+(INDEX($F$5:$F$16,MIN(MATCH(B19,$B$5:$B$16,1),11)+1)-INDEX($F$5:$F$16,MIN(MATCH(B19,$B$5:$B$16,1),11)))/(INDEX($B$5:$B$16,MIN(MATCH(B19,$B$5:$B$16,1),11)+1)-INDEX($B$5:$B$16,MIN(MATCH(B19,$B$5:$B$16,1),11)))*(B19-INDEX($B$5:$B$16,MIN(MATCH(B19,$B$5:$B$16,1),11))) -> 0.041286196 | D19: =EXP(-C19*B19) -> 0.98973154 | E19: =-LN(D19)/B19 -> 0.041286196 | F19: =(D19/D20-1)/0.25 -> 0.038104664 | G19: Z=MATCH+INDEX linear interp | DF=EXP(-Z·T) | IF=central diff | 3Mfwd=(DF/DF+1-1)/0.25
B20: 0.5 | C20: =INDEX($F$5:$F$16,MIN(MATCH(B20,$B$5:$B$16,1),11))+(INDEX($F$5:$F$16,MIN(MATCH(B20,$B$5:$B$16,1),11)+1)-INDEX($F$5:$F$16,MIN(MATCH(B20,$B$5:$B$16,1),11)))/(INDEX($B$5:$B$16,MIN(MATCH(B20,$B$5:$B$16,1),11)+1)-INDEX($B$5:$B$16,MIN(MATCH(B20,$B$5:$B$16,1),11)))*(B20-INDEX($B$5:$B$16,MIN(MATCH(B20,$B$5:$B$16,1),11))) -> 0.039605255 | D20: =EXP(-C20*B20) -> 0.98039216 | E20: =(LN(D19)-LN(D21))/(B21-B19) -> 0.037032681 | F20: =(D20/D21-1)/0.25 -> 0.036304815 | G20: Z=MATCH+INDEX linear interp | DF=EXP(-Z·T) | IF=central diff | 3Mfwd=(DF/DF+1-1)/0.25
B21: 0.75 | C21: =INDEX($F$5:$F$16,MIN(MATCH(B21,$B$5:$B$16,1),11))+(INDEX($F$5:$F$16,MIN(MATCH(B21,$B$5:$B$16,1),11)+1)-INDEX($F$5:$F$16,MIN(MATCH(B21,$B$5:$B$16,1),11)))/(INDEX($B$5:$B$16,MIN(MATCH(B21,$B$5:$B$16,1),11)+1)-INDEX($B$5:$B$16,MIN(MATCH(B21,$B$5:$B$16,1),11)))*(B21-INDEX($B$5:$B$16,MIN(MATCH(B21,$B$5:$B$16,1),11))) -> 0.03845052 | D21: =EXP(-C21*B21) -> 0.97157395 | E21: =(LN(D20)-LN(D22))/(B22-B20) -> 0.034986315 | F21: =(D21/D22-1)/0.25 -> 0.033975056 | G21: Z=MATCH+INDEX linear interp | DF=EXP(-Z·T) | IF=central diff | 3Mfwd=(DF/DF+1-1)/0.25
B22: 1 | C22: =INDEX($F$5:$F$16,MIN(MATCH(B22,$B$5:$B$16,1),11))+(INDEX($F$5:$F$16,MIN(MATCH(B22,$B$5:$B$16,1),11)+1)-INDEX($F$5:$F$16,MIN(MATCH(B22,$B$5:$B$16,1),11)))/(INDEX($B$5:$B$16,MIN(MATCH(B22,$B$5:$B$16,1),11)+1)-INDEX($B$5:$B$16,MIN(MATCH(B22,$B$5:$B$16,1),11)))*(B22-INDEX($B$5:$B$16,MIN(MATCH(B22,$B$5:$B$16,1),11))) -> 0.037295785 | D22: =EXP(-C22*B22) -> 0.96339114 | E22: =(LN(D21)-LN(D23))/(B23-B21) -> 0.034950134 | F22: =(D22/D23-1)/0.25 -> 0.036231796
B23: 1.25 | C23: =INDEX($F$5:$F$16,MIN(MATCH(B23,$B$5:$B$16,1),11))+(INDEX($F$5:$F$16,MIN(MATCH(B23,$B$5:$B$16,1),11)+1)-INDEX($F$5:$F$16,MIN(MATCH(B23,$B$5:$B$16,1),11)))/(INDEX($B$5:$B$16,MIN(MATCH(B23,$B$5:$B$16,1),11)+1)-INDEX($B$5:$B$16,MIN(MATCH(B23,$B$5:$B$16,1),11)))*(B23-INDEX($B$5:$B$16,MIN(MATCH(B23,$B$5:$B$16,1),11))) -> 0.037050365 | D23: =EXP(-C23*B23) -> 0.95474312 | E23: =(LN(D22)-LN(D24))/(B24-B22) -> 0.035823268 | F23: =(D23/D24-1)/0.25 -> 0.035736541
B24: 1.5 | C24: =INDEX($F$5:$F$16,MIN(MATCH(B24,$B$5:$B$16,1),11))+(INDEX($F$5:$F$16,MIN(MATCH(B24,$B$5:$B$16,1),11)+1)-INDEX($F$5:$F$16,MIN(MATCH(B24,$B$5:$B$16,1),11)))/(INDEX($B$5:$B$16,MIN(MATCH(B24,$B$5:$B$16,1),11)+1)-INDEX($B$5:$B$16,MIN(MATCH(B24,$B$5:$B$16,1),11)))*(B24-INDEX($B$5:$B$16,MIN(MATCH(B24,$B$5:$B$16,1),11))) -> 0.036804946 | D24: =EXP(-C24*B24) -> 0.94628885 | E24: =(LN(D23)-LN(D25))/(B25-B23) -> 0.035332429 | F24: =(D24/D25-1)/0.25 -> 0.035241348
B25: 1.75 | C25: =INDEX($F$5:$F$16,MIN(MATCH(B25,$B$5:$B$16,1),11))+(INDEX($F$5:$F$16,MIN(MATCH(B25,$B$5:$B$16,1),11)+1)-INDEX($F$5:$F$16,MIN(MATCH(B25,$B$5:$B$16,1),11)))/(INDEX($B$5:$B$16,MIN(MATCH(B25,$B$5:$B$16,1),11)+1)-INDEX($B$5:$B$16,MIN(MATCH(B25,$B$5:$B$16,1),11)))*(B25-INDEX($B$5:$B$16,MIN(MATCH(B25,$B$5:$B$16,1),11))) -> 0.036559526 | D25: =EXP(-C25*B25) -> 0.93802454 | E25: =(LN(D24)-LN(D26))/(B26-B24) -> 0.03484159 | F25: =(D25/D26-1)/0.25 -> 0.034746215
B26: 2 | C26: =INDEX($F$5:$F$16,MIN(MATCH(B26,$B$5:$B$16,1),11))+(INDEX($F$5:$F$16,MIN(MATCH(B26,$B$5:$B$16,1),11)+1)-INDEX($F$5:$F$16,MIN(MATCH(B26,$B$5:$B$16,1),11)))/(INDEX($B$5:$B$16,MIN(MATCH(B26,$B$5:$B$16,1),11)+1)-INDEX($B$5:$B$16,MIN(MATCH(B26,$B$5:$B$16,1),11)))*(B26-INDEX($B$5:$B$16,MIN(MATCH(B26,$B$5:$B$16,1),11))) -> 0.036314107 | D26: =EXP(-C26*B26) -> 0.92994651 | E26: =(LN(D25)-LN(D27))/(B27-B25) -> 0.034899419 | F26: =(D26/D27-1)/0.25 -> 0.035358027
B27: 2.25 | C27: =INDEX($F$5:$F$16,MIN(MATCH(B27,$B$5:$B$16,1),11))+(INDEX($F$5:$F$16,MIN(MATCH(B27,$B$5:$B$16,1),11)+1)-INDEX($F$5:$F$16,MIN(MATCH(B27,$B$5:$B$16,1),11)))/(INDEX($B$5:$B$16,MIN(MATCH(B27,$B$5:$B$16,1),11)+1)-INDEX($B$5:$B$16,MIN(MATCH(B27,$B$5:$B$16,1),11)))*(B27-INDEX($B$5:$B$16,MIN(MATCH(B27,$B$5:$B$16,1),11))) -> 0.036190614 | D27: =EXP(-C27*B27) -> 0.92179827 | E27: =(LN(D26)-LN(D28))/(B28-B26) -> 0.035079175 | F27: =(D27/D28-1)/0.25 -> 0.035108865
B28: 2.5 | C28: =INDEX($F$5:$F$16,MIN(MATCH(B28,$B$5:$B$16,1),11))+(INDEX($F$5:$F$16,MIN(MATCH(B28,$B$5:$B$16,1),11)+1)-INDEX($F$5:$F$16,MIN(MATCH(B28,$B$5:$B$16,1),11)))/(INDEX($B$5:$B$16,MIN(MATCH(B28,$B$5:$B$16,1),11)+1)-INDEX($B$5:$B$16,MIN(MATCH(B28,$B$5:$B$16,1),11)))*(B28-INDEX($B$5:$B$16,MIN(MATCH(B28,$B$5:$B$16,1),11))) -> 0.03606712 | D28: =EXP(-C28*B28) -> 0.91377784 | E28: =(LN(D27)-LN(D29))/(B29-B27) -> 0.034832189 | F28: =(D28/D29-1)/0.25 -> 0.034859719
B29: 2.75 | C29: =INDEX($F$5:$F$16,MIN(MATCH(B29,$B$5:$B$16,1),11))+(INDEX($F$5:$F$16,MIN(MATCH(B29,$B$5:$B$16,1),11)+1)-INDEX($F$5:$F$16,MIN(MATCH(B29,$B$5:$B$16,1),11)))/(INDEX($B$5:$B$16,MIN(MATCH(B29,$B$5:$B$16,1),11)+1)-INDEX($B$5:$B$16,MIN(MATCH(B29,$B$5:$B$16,1),11)))*(B29-INDEX($B$5:$B$16,MIN(MATCH(B29,$B$5:$B$16,1),11))) -> 0.035943627 | D29: =EXP(-C29*B29) -> 0.90588313 | E29: =(LN(D28)-LN(D30))/(B30-B28) -> 0.034585202 | F29: =(D29/D30-1)/0.25 -> 0.034610588
B30: 3 | C30: =INDEX($F$5:$F$16,MIN(MATCH(B30,$B$5:$B$16,1),11))+(INDEX($F$5:$F$16,MIN(MATCH(B30,$B$5:$B$16,1),11)+1)-INDEX($F$5:$F$16,MIN(MATCH(B30,$B$5:$B$16,1),11)))/(INDEX($B$5:$B$16,MIN(MATCH(B30,$B$5:$B$16,1),11)+1)-INDEX($B$5:$B$16,MIN(MATCH(B30,$B$5:$B$16,1),11)))*(B30-INDEX($B$5:$B$16,MIN(MATCH(B30,$B$5:$B$16,1),11))) -> 0.035820134 | D30: =EXP(-C30*B30) -> 0.89811208 | E30: =(LN(D29)-LN(D31))/(B31-B29) -> 0.035287063 | F30: =(D30/D31-1)/0.25 -> 0.036275921
B31: 3.25 | C31: =INDEX($F$5:$F$16,MIN(MATCH(B31,$B$5:$B$16,1),11))+(INDEX($F$5:$F$16,MIN(MATCH(B31,$B$5:$B$16,1),11)+1)-INDEX($F$5:$F$16,MIN(MATCH(B31,$B$5:$B$16,1),11)))/(INDEX($B$5:$B$16,MIN(MATCH(B31,$B$5:$B$16,1),11)+1)-INDEX($B$5:$B$16,MIN(MATCH(B31,$B$5:$B$16,1),11)))*(B31-INDEX($B$5:$B$16,MIN(MATCH(B31,$B$5:$B$16,1),11))) -> 0.035842617 | D31: =EXP(-C31*B31) -> 0.89004033 | E31: =(LN(D30)-LN(D32))/(B32-B30) -> 0.036134899 | F31: =(D31/D32-1)/0.25 -> 0.036321296
B32: 3.5 | C32: =INDEX($F$5:$F$16,MIN(MATCH(B32,$B$5:$B$16,1),11))+(INDEX($F$5:$F$16,MIN(MATCH(B32,$B$5:$B$16,1),11)+1)-INDEX($F$5:$F$16,MIN(MATCH(B32,$B$5:$B$16,1),11)))/(INDEX($B$5:$B$16,MIN(MATCH(B32,$B$5:$B$16,1),11)+1)-INDEX($B$5:$B$16,MIN(MATCH(B32,$B$5:$B$16,1),11)))*(B32-INDEX($B$5:$B$16,MIN(MATCH(B32,$B$5:$B$16,1),11))) -> 0.035865101 | D32: =EXP(-C32*B32) -> 0.8820312 | E32: =(LN(D31)-LN(D33))/(B33-B31) -> 0.036179866 | F32: =(D32/D33-1)/0.25 -> 0.036366671
B33: 3.75 | C33: =INDEX($F$5:$F$16,MIN(MATCH(B33,$B$5:$B$16,1),11))+(INDEX($F$5:$F$16,MIN(MATCH(B33,$B$5:$B$16,1),11)+1)-INDEX($F$5:$F$16,MIN(MATCH(B33,$B$5:$B$16,1),11)))/(INDEX($B$5:$B$16,MIN(MATCH(B33,$B$5:$B$16,1),11)+1)-INDEX($B$5:$B$16,MIN(MATCH(B33,$B$5:$B$16,1),11)))*(B33-INDEX($B$5:$B$16,MIN(MATCH(B33,$B$5:$B$16,1),11))) -> 0.035887584 | D33: =EXP(-C33*B33) -> 0.87408431 | E33: =(LN(D32)-LN(D34))/(B34-B32) -> 0.036224832 | F33: =(D33/D34-1)/0.25 -> 0.036412046
... B57: 9.75 | C57: =INDEX($F$5:$F$16,MIN(MATCH(B57,$B$5:$B$16,1),11))+(INDEX($F$5:$F$16,MIN(MATCH(B57,$B$5:$B$16,1),11)+1)-INDEX($F$5:$F$16,MIN(MATCH(B57,$B$5:$B$16,1),11)))/(INDEX($B$5:$B$16,MIN(MATCH(B57,$B$5:$B$16,1),11)+1)-INDEX($B$5:$B$16,MIN(MATCH(B57,$B$5:$B$16,1),11)))*(B57-INDEX($B$5:$B$16,MIN(MATCH(B57,$B$5:$B$16,1),11))) -> 0.034922935 | D57: =EXP(-C57*B57) -> 0.71141551 | E57: =(LN(D56)-LN(D58))/(B58-B56) -> 0.029131483 | F57: =(D57/D58-1)/0.25 -> 0.02908824
B58: 10 | C58: =INDEX($F$5:$F$16,MIN(MATCH(B58,$B$5:$B$16,1),11))+(INDEX($F$5:$F$16,MIN(MATCH(B58,$B$5:$B$16,1),11)+1)-INDEX($F$5:$F$16,MIN(MATCH(B58,$B$5:$B$16,1),11)))/(INDEX($B$5:$B$16,MIN(MATCH(B58,$B$5:$B$16,1),11)+1)-INDEX($B$5:$B$16,MIN(MATCH(B58,$B$5:$B$16,1),11)))*(B58-INDEX($B$5:$B$16,MIN(MATCH(B58,$B$5:$B$16,1),11))) -> 0.034774436 | D58: =EXP(-C58*B58) -> 0.7062794 | E58: =(LN(D57)-LN(D58))/(B58-B57) -> 0.028982984 | F58: —

Sheet Proj_Curve
B1: Projection Curve · SOFR Futures (0-2Y) + IRS Bootstrap (2-10Y)
B3: SECTION 1 — SOFR FUTURES (Implied 3M Forward Rate per Quarterly Period)
B4: Contract | C4: T_start | D4: T_end | E4: Implied 3M Fwd | F4: Note
B5: Sep25 | C5: 0 | D5: 0.25 | E5: =Instruments!$E$19 -> 0.044 | F5: 3M SOFR forward for Sep25 — directly observed from futures market | H5: =1/(1+E5*0.25) -> 0.98911968
B6: Dec25 | C6: 0.25 | D6: 0.5 | E6: =Instruments!$E$20 -> 0.0425 | F6: 3M SOFR forward for Dec25 — directly observed from futures market
B7: Mar26 | C7: 0.5 | D7: 0.75 | E7: =Instruments!$E$21 -> 0.0408 | F7: 3M SOFR forward for Mar26 — directly observed from futures market
B8: Jun26 | C8: 0.75 | D8: 1 | E8: =Instruments!$E$22 -> 0.0392 | F8: 3M SOFR forward for Jun26 — directly observed from futures market
B9: Sep26 | C9: 1 | D9: 1.25 | E9: =Instruments!$E$23 -> 0.0382 | F9: 3M SOFR forward for Sep26 — directly observed from futures market
B10: Dec26 | C10: 1.25 | D10: 1.5 | E10: =Instruments!$E$24 -> 0.0376 | F10: 3M SOFR forward for Dec26 — directly observed from futures market
B11: Mar27 | C11: 1.5 | D11: 1.75 | E11: =Instruments!$E$25 -> 0.0372 | F11: 3M SOFR forward for Mar27 — directly observed from futures market
B12: Jun27 | C12: 1.75 | D12: 2 | E12: =Instruments!$E$26 -> 0.037 | F12: 3M SOFR forward for Jun27 — directly observed from futures market
B14: SECTION 2 — IRS BOOTSTRAP (Flat Forward per Band, bootstrapped from 3M SOFR IRS)
B15: IRS Mat | C15: Par Rate | D15: Band | E15: Flat Fwd (bootstrapped) | F15: Bootstrap Formula
B16: 3 | C16: =Instruments!$D$30 -> 0.0367 | D16: 2Y-3Y | E16: 0.030563284 | F16: Flat Fwd = (K·Ann(3Y) - PV_Float(0-2Y)) / Ann(2Y-3Y) where Ann=δ·ΣP_OIS(Ti), PV_Float=δ·ΣF_i·P_OIS(Ti)
B17: 5 | C17: =Instruments!$D$31 -> 0.0364 | D17: 3Y-5Y | E17: 0.035908895 | F17: Flat Fwd = (K·Ann(5Y) - PV_Float(0-3Y)) / Ann(3Y-5Y) where Ann=δ·ΣP_OIS(Ti), PV_Float=δ·ΣF_i·P_OIS(Ti)
B18: 7 | C18: =Instruments!$D$32 -> 0.0362 | D18: 5Y-7Y | E18: 0.035634867 | F18: Flat Fwd = (K·Ann(7Y) - PV_Float(0-5Y)) / Ann(5Y-7Y) where Ann=δ·ΣP_OIS(Ti), PV_Float=δ·ΣF_i·P_OIS(Ti)
B19: 10 | C19: =Instruments!$D$33 -> 0.0359 | D19: 7Y-10Y | E19: 0.035066571 | F19: Flat Fwd = (K·Ann(10Y) - PV_Float(0-7Y)) / Ann(7Y-10Y) where Ann=δ·ΣP_OIS(Ti), PV_Float=δ·ΣF_i·P_OIS(Ti)
B21: SECTION 3 — QUARTERLY PROJECTION GRID (40 periods: T_start 0 to 9.75)
B22: T_start | C22: T_end | D22: 3M Forward Rate | E22: Proj DF at T_end | F22: Note
B23: 0 | C23: 0.25 | D23: =E5 -> 0.044 | E23: =1/(1+D23*0.25) -> 0.98911968 | F23: Proj DF(T_end)=Proj DF(T_start)/(1+Fwd·δ) where Proj DF(0)=1
B24: 0.25 | C24: 0.5 | D24: =E6 -> 0.0425 | E24: =E23/(1+D24*0.25) -> 0.97872078 | F24: Proj DF(T_end)=Proj DF(T_start)/(1+Fwd·δ) where Proj DF(0)=1
B25: 0.5 | C25: 0.75 | D25: =E7 -> 0.0408 | E25: =E24/(1+D25*0.25) -> 0.96883862
B26: 0.75 | C26: 1 | D26: =E8 -> 0.0392 | E26: =E25/(1+D26*0.25) -> 0.95943615
B27: 1 | C27: 1.25 | D27: =E9 -> 0.0382 | E27: =E26/(1+D27*0.25) -> 0.95036021
B28: 1.25 | C28: 1.5 | D28: =E10 -> 0.0376 | E28: =E27/(1+D28*0.25) -> 0.94151001
B29: 1.5 | C29: 1.75 | D29: =E11 -> 0.0372 | E29: =E28/(1+D29*0.25) -> 0.93283465
B30: 1.75 | C30: 2 | D30: =E12 -> 0.037 | E30: =E29/(1+D30*0.25) -> 0.92428501
B31: 2 | C31: 2.25 | D31: =E16 -> 0.030563284 | E31: =E30/(1+D31*0.25) -> 0.91727627
B32: 2.25 | C32: 2.5 | D32: =E16 -> 0.030563284 | E32: =E31/(1+D32*0.25) -> 0.91032067
B33: 2.5 | C33: 2.75 | D33: =E16 -> 0.030563284 | E33: =E32/(1+D33*0.25) -> 0.90341782
B34: 2.75 | C34: 3 | D34: =E16 -> 0.030563284 | E34: =E33/(1+D34*0.25) -> 0.89656731
B35: 3 | C35: 3.25 | D35: =E17 -> 0.035908895 | E35: =E34/(1+D35*0.25) -> 0.88859024
B36: 3.25 | C36: 3.5 | D36: =E17 -> 0.035908895 | E36: =E35/(1+D36*0.25) -> 0.88068414
B37: 3.5 | C37: 3.75 | D37: =E17 -> 0.035908895 | E37: =E36/(1+D37*0.25) -> 0.87284838
B38: 3.75 | C38: 4 | D38: =E17 -> 0.035908895 | E38: =E37/(1+D38*0.25) -> 0.86508234
B39: 4 | C39: 4.25 | D39: =E17 -> 0.035908895 | E39: =E38/(1+D39*0.25) -> 0.8573854
B40: 4.25 | C40: 4.5 | D40: =E17 -> 0.035908895 | E40: =E39/(1+D40*0.25) -> 0.84975695
B41: 4.5 | C41: 4.75 | D41: =E17 -> 0.035908895 | E41: =E40/(1+D41*0.25) -> 0.84219636
B42: 4.75 | C42: 5 | D42: =E17 -> 0.035908895 | E42: =E41/(1+D42*0.25) -> 0.83470304
B43: 5 | C43: 5.25 | D43: =E18 -> 0.035634867 | E43: =E42/(1+D43*0.25) -> 0.82733257
B44: 5.25 | C44: 5.5 | D44: =E18 -> 0.035634867 | E44: =E43/(1+D44*0.25) -> 0.82002718
B45: 5.5 | C45: 5.75 | D45: =E18 -> 0.035634867 | E45: =E44/(1+D45*0.25) -> 0.8127863
B46: 5.75 | C46: 6 | D46: =E18 -> 0.035634867 | E46: =E45/(1+D46*0.25) -> 0.80560935
B47: 6 | C47: 6.25 | D47: =E18 -> 0.035634867 | E47: =E46/(1+D47*0.25) -> 0.79849578
B48: 6.25 | C48: 6.5 | D48: =E18 -> 0.035634867 | E48: =E47/(1+D48*0.25) -> 0.79144502
B49: 6.5 | C49: 6.75 | D49: =E18 -> 0.035634867 | E49: =E48/(1+D49*0.25) -> 0.78445652
B50: 6.75 | C50: 7 | D50: =E18 -> 0.035634867 | E50: =E49/(1+D50*0.25) -> 0.77752973
B51: 7 | C51: 7.25 | D51: =E19 -> 0.035066571 | E51: =E50/(1+D51*0.25) -> 0.77077264
B52: 7.25 | C52: 7.5 | D52: =E19 -> 0.035066571 | E52: =E51/(1+D52*0.25) -> 0.76407427
B53: 7.5 | C53: 7.75 | D53: =E19 -> 0.035066571 | E53: =E52/(1+D53*0.25) -> 0.75743412
B54: 7.75 | C54: 8 | D54: =E19 -> 0.035066571 | E54: =E53/(1+D54*0.25) -> 0.75085167
B55: 8 | C55: 8.25 | D55: =E19 -> 0.035066571 | E55: =E54/(1+D55*0.25) -> 0.74432643
B56: 8.25 | C56: 8.5 | D56: =E19 -> 0.035066571 | E56: =E55/(1+D56*0.25) -> 0.73785789
B57: 8.5 | C57: 8.75 | D57: =E19 -> 0.035066571 | E57: =E56/(1+D57*0.25) -> 0.73144557
B58: 8.75 | C58: 9 | D58: =E19 -> 0.035066571 | E58: =E57/(1+D58*0.25) -> 0.72508897
B59: 9 | C59: 9.25 | D59: =E19 -> 0.035066571 | E59: =E58/(1+D59*0.25) -> 0.71878762
B60: 9.25 | C60: 9.5 | D60: =E19 -> 0.035066571 | E60: =E59/(1+D60*0.25) -> 0.71254103
B61: 9.5 | C61: 9.75 | D61: =E19 -> 0.035066571 | E61: =E60/(1+D61*0.25) -> 0.70634872
B62: 9.75 | C62: 10 | D62: =E19 -> 0.035066571 | E62: =E61/(1+D62*0.25) -> 0.70021023

Sheet Par_Rates
B1: ATM Par Swap Rates · Cap Strike K per Maturity (Dual-Curve Formula)
B2: Par Rate = PV(Float) / Annuity | PV(Float) = δ·Σ F_i·P_OIS(T_i) | Annuity = δ·Σ P_OIS(T_i)
B4: Cap Maturity | C4: Annuity | D4: PV(Floating) | E4: Par Rate K | F4: Market Cap (bps)
B5: 2Y | C5: =0.25*SUM(OIS_Curve!$D$19:$D$26) -> 1.9185229 | D5: =0.25*SUMPRODUCT(Proj_Curve!$D$23:$D$30,OIS_Curve!$D$19:$D$26) -> 0.075993546 | E5: =D5/C5 -> 0.039610444 | F5: 21.897316
B6: 3Y | C6: =0.25*SUM(OIS_Curve!$D$19:$D$30) -> 2.8284158 | D6: =0.25*SUMPRODUCT(Proj_Curve!$D$23:$D$34,OIS_Curve!$D$19:$D$30) -> 0.10380286 | E6: =D6/C6 -> 0.0367 | F6: 69.912719
B7: 5Y | C7: =0.25*SUM(OIS_Curve!$D$19:$D$38) -> 4.555022 | D7: =0.25*SUMPRODUCT(Proj_Curve!$D$23:$D$42,OIS_Curve!$D$19:$D$38) -> 0.16580338 | E7: =D7/C7 -> 0.036400127 | F7: 143.36482
B8: 7Y | C8: =0.25*SUM(OIS_Curve!$D$19:$D$46) -> 6.1658681 | D8: =0.25*SUMPRODUCT(Proj_Curve!$D$23:$D$50,OIS_Curve!$D$19:$D$46) -> 0.22320567 | E8: =D8/C8 -> 0.036200201 | F8: 219.15872
B9: 10Y | C9: =0.25*SUM(OIS_Curve!$D$19:$D$58) -> 8.3820774 | D9: =0.25*SUMPRODUCT(Proj_Curve!$D$23:$D$62,OIS_Curve!$D$19:$D$58) -> 0.30092053 | E9: =D9/C9 -> 0.035900471 | F9: 333.79573

Sheet HW_Caplets
B1: HW Caplet Pricing · Organised by Cap Maturity · Formula-driven
B2: Caplet = (1+Kδ)·[K̃·P(0,S)·Φ(-h+σ_p) - P(0,S+δ)·Φ(-h)] | σ_p=(σ/a)·(1-e^{-aδ})·√[(1-e^{-2aS})/(2a)] | h=(1/σ_p)·ln[P(0,S+δ)/(P(0,S)·K̃)]+σ_p/2 | K̃=1/(1+Kδ)
B3: 2Y Cap · K = 3.961% · 7 caplets (T_start = 0.25 to 1.75)
B4: T_start | C4: T_end | D4: P(0,S) | E4: P(0,S+δ) | F4: K | G4: K̃ | H4: σ_p | I4: h | J4: Φ(-h+σ_p) | K4: Φ(-h) | L4: Caplet (dec) | M4: Caplet (bps)
B5: 0.25 | C5: 0.5 | D5: =VLOOKUP(B5,OIS_Curve!$B$19:$D$58,3,FALSE()) -> 0.98973154 | E5: =VLOOKUP(C5,OIS_Curve!$B$19:$D$58,3,FALSE()) -> 0.98039216 | F5: =Par_Rates!$E$5 -> 0.039610444 | G5: =1/(1+F5*0.25) -> 0.99019449 | H5: =IF(B5=0,0,(Parameters!$C$5/Parameters!$C$4)*(1-EXP(-Parameters!$C$4*0.25))*SQRT((1-EXP(-2*Parameters!$C$4*B5))/(2*Parameters!$C$4))) -> 0.00097241305 | I5: =IF(H5=0,0,(1/H5)*LN(E5/(D5*G5))+H5/2) -> 0.38388635 | J5: =NORMSDIST(-I5+H5) -> 0.35089179 | K5: =NORMSDIST(-I5) -> 0.35053134 | L5: =IF(H5=0,0,(1+F5*0.25)*(G5*D5*J5-E5*K5)) -> 0.00022737711 | M5: =L5*10000 -> 2.2737711
B6: 0.5 | C6: 0.75 | D6: =VLOOKUP(B6,OIS_Curve!$B$19:$D$58,3,FALSE()) -> 0.98039216 | E6: =VLOOKUP(C6,OIS_Curve!$B$19:$D$58,3,FALSE()) -> 0.97157395 | F6: =Par_Rates!$E$5 -> 0.039610444 | G6: =1/(1+F6*0.25) -> 0.99019449 | H6: =IF(B6=0,0,(Parameters!$C$5/Parameters!$C$4)*(1-EXP(-Parameters!$C$4*0.25))*SQRT((1-EXP(-2*Parameters!$C$4*B6))/(2*Parameters!$C$4))) -> 0.0013481001 | I6: =IF(H6=0,0,(1/H6)*LN(E6/(D6*G6))+H6/2) -> 0.60792795 | J6: =NORMSDIST(-I6+H6) -> 0.27206489 | K6: =NORMSDIST(-I6) -> 0.27161763 | L6: =IF(H6=0,0,(1+F6*0.25)*(G6*D6*J6-E6*K6)) -> 0.00022040156 | M6: =L6*10000 -> 2.2040156
B7: 0.75 | C7: 1 | D7: =VLOOKUP(B7,OIS_Curve!$B$19:$D$58,3,FALSE()) -> 0.97157395 | E7: =VLOOKUP(C7,OIS_Curve!$B$19:$D$58,3,FALSE()) -> 0.96339114 | F7: =Par_Rates!$E$5 -> 0.039610444 | G7: =1/(1+F7*0.25) -> 0.99019449 | H7: =IF(B7=0,0,(Parameters!$C$5/Parameters!$C$4)*(1-EXP(-Parameters!$C$4*0.25))*SQRT((1-EXP(-2*Parameters!$C$4*B7))/(2*Parameters!$C$4))) -> 0.0016189875 | I7: =IF(H7=0,0,(1/H7)*LN(E7/(D7*G7))+H7/2) -> 0.86308085 | J7: =NORMSDIST(-I7+H7) -> 0.19449186 | K7: =NORMSDIST(-I7) -> 0.19404651 | L7: =IF(H7=0,0,(1+F7*0.25)*(G7*D7*J7-E7*K7)) -> 0.00016931734 | M7: =L7*10000 -> 1.6931734
B8: 1 | C8: 1.25 | D8: =VLOOKUP(B8,OIS_Curve!$B$19:$D$58,3,FALSE()) -> 0.96339114 | E8: =VLOOKUP(C8,OIS_Curve!$B$19:$D$58,3,FALSE()) -> 0.95474312 | F8: =Par_Rates!$E$5 -> 0.039610444 | G8: =1/(1+F8*0.25) -> 0.99019449 | H8: =IF(B8=0,0,(Parameters!$C$5/Parameters!$C$4)*(1-EXP(-Parameters!$C$4*0.25))*SQRT((1-EXP(-2*Parameters!$C$4*B8))/(2*Parameters!$C$4))) -> 0.0018336131 | I8: =IF(H8=0,0,(1/H8)*LN(E8/(D8*G8))+H8/2) -> 0.45724519 | J8: =NORMSDIST(-I8+H8) -> 0.32440658 | K8: =NORMSDIST(-I8) -> 0.32374741 | L8: =IF(H8=0,0,(1+F8*0.25)*(G8*D8*J8-E8*K8)) -> 0.00037396084 | M8: =L8*10000 -> 3.7396084
B9: 1.25 | C9: 1.5 | D9: =VLOOKUP(B9,OIS_Curve!$B$19:$D$58,3,FALSE()) -> 0.95474312 | E9: =VLOOKUP(C9,OIS_Curve!$B$19:$D$58,3,FALSE()) -> 0.94628885 | F9: =Par_Rates!$E$5 -> 0.039610444 | G9: =1/(1+F9*0.25) -> 0.99019449 | H9: =IF(B9=0,0,(Parameters!$C$5/Parameters!$C$4)*(1-EXP(-Parameters!$C$4*0.25))*SQRT((1-EXP(-2*Parameters!$C$4*B9))/(2*Parameters!$C$4))) -> 0.0020112979 | I9: =IF(H9=0,0,(1/H9)*LN(E9/(D9*G9))+H9/2) -> 0.47803068 | J9: =NORMSDIST(-I9+H9) -> 0.31703029 | K9: =NORMSDIST(-I9) -> 0.31631418 | L9: =IF(H9=0,0,(1+F9*0.25)*(G9*D9*J9-E9*K9)) -> 0.00039380335 | M9: =L9*10000 -> 3.9380335
B10: 1.5 | C10: 1.75 | D10: =VLOOKUP(B10,OIS_Curve!$B$19:$D$58,3,FALSE()) -> 0.94628885 | E10: =VLOOKUP(C10,OIS_Curve!$B$19:$D$58,3,FALSE()) -> 0.93802454 | F10: =Par_Rates!$E$5 -> 0.039610444 | G10: =1/(1+F10*0.25) -> 0.99019449 | H10: =IF(B10=0,0,(Parameters!$C$5/Parameters!$C$4)*(1-EXP(-Parameters!$C$4*0.25))*SQRT((1-EXP(-2*Parameters!$C$4*B10))/(2*Parameters!$C$4))) -> 0.0021622167 | I10: =IF(H10=0,0,(1/H10)*LN(E10/(D10*G10))+H10/2) -> 0.50156248 | J10: =NORMSDIST(-I10+H10) -> 0.30874872 | K10: =NORMSDIST(-I10) -> 0.30798766 | L10: =IF(H10=0,0,(1+F10*0.25)*(G10*D10*J10-E10*K10)) -> 0.00040462284 | M10: =L10*10000 -> 4.0462284
B11: 1.75 | C11: 2 | D11: =VLOOKUP(B11,OIS_Curve!$B$19:$D$58,3,FALSE()) -> 0.93802454 | E11: =VLOOKUP(C11,OIS_Curve!$B$19:$D$58,3,FALSE()) -> 0.92994651 | F11: =Par_Rates!$E$5 -> 0.039610444 | G11: =1/(1+F11*0.25) -> 0.99019449 | H11: =IF(B11=0,0,(Parameters!$C$5/Parameters!$C$4)*(1-EXP(-Parameters!$C$4*0.25))*SQRT((1-EXP(-2*Parameters!$C$4*B11))/(2*Parameters!$C$4))) -> 0.0022925715 | I11: =IF(H11=0,0,(1/H11)*LN(E11/(D11*G11))+H11/2) -> 0.52669539 | J11: =NORMSDIST(-I11+H11) -> 0.2999992 | K11: =NORMSDIST(-I11) -> 0.29920257 | L11: =IF(H11=0,0,(1+F11*0.25)*(G11*D11*J11-E11*K11)) -> 0.00040889935 | M11: =L11*10000 -> 4.0889935
B12: Cap 2Y Total (Model) | L12: =SUM(L5:L11) -> 0.0021983824 | M12: =SUM(M5:M11) -> 21.983824
B14: 3Y Cap · K = 3.670% · 11 caplets (T_start = 0.25 to 2.75)
B15: T_start | C15: T_end | D15: P(0,S) | E15: P(0,S+δ) | F15: K | G15: K̃ | H15: σ_p | I15: h | J15: Φ(-h+σ_p) | K15: Φ(-h) | L15: Caplet (dec) | M15: Caplet (bps)
B16: 0.25 | C16: 0.5 | D16: =VLOOKUP(B16,OIS_Curve!$B$19:$D$58,3,FALSE()) -> 0.98973154 | E16: =VLOOKUP(C16,OIS_Curve!$B$19:$D$58,3,FALSE()) -> 0.98039216 | F16: =Par_Rates!$E$6 -> 0.0367 | G16: =1/(1+F16*0.25) -> 0.99090842 | H16: =IF(B16=0,0,(Parameters!$C$5/Parameters!$C$4)*(1-EXP(-Parameters!$C$4*0.25))*SQRT((1-EXP(-2*Parameters!$C$4*B16))/(2*Parameters!$C$4))) -> 0.00097241305 | I16: =IF(H16=0,0,(1/H16)*LN(E16/(D16*G16))+H16/2) -> -0.35729678 | J16: =NORMSDIST(-I16+H16) -> 0.63992906 | K16: =NORMSDIST(-I16) -> 0.63956518 | L16: =IF(H16=0,0,(1+F16*0.25)*(G16*D16*J16-E16*K16)) -> 0.00058033818 | M16: =L16*10000 -> 5.8033818
B17: 0.5 | C17: 0.75 | D17: =VLOOKUP(B17,OIS_Curve!$B$19:$D$58,3,FALSE()) -> 0.98039216 | E17: =VLOOKUP(C17,OIS_Curve!$B$19:$D$58,3,FALSE()) -> 0.97157395 | F17: =Par_Rates!$E$6 -> 0.0367 | G17: =1/(1+F17*0.25) -> 0.99090842 | H17: =IF(B17=0,0,(Parameters!$C$5/Parameters!$C$4)*(1-EXP(-Parameters!$C$4*0.25))*SQRT((1-EXP(-2*Parameters!$C$4*B17))/(2*Parameters!$C$4))) -> 0.0013481001 | I17: =IF(H17=0,0,(1/H17)*LN(E17/(D17*G17))+H17/2) -> 0.073296939 | J17: =NORMSDIST(-I17+H17) -> 0.47132131 | K17: =NORMSDIST(-I17) -> 0.47078491 | L17: =IF(H17=0,0,(1+F17*0.25)*(G17*D17*J17-E17*K17)) -> 0.00048069045 | M17: =L17*10000 -> 4.8069045
B18: 0.75 | C18: 1 | D18: =VLOOKUP(B18,OIS_Curve!$B$19:$D$58,3,FALSE()) -> 0.97157395 | E18: =VLOOKUP(C18,OIS_Curve!$B$19:$D$58,3,FALSE()) -> 0.96339114 | F18: =Par_Rates!$E$6 -> 0.0367 | G18: =1/(1+F18*0.25) -> 0.99090842 | H18: =IF(B18=0,0,(Parameters!$C$5/Parameters!$C$4)*(1-EXP(-Parameters!$C$4*0.25))*SQRT((1-EXP(-2*Parameters!$C$4*B18))/(2*Parameters!$C$4))) -> 0.0016189875 | I18: =IF(H18=0,0,(1/H18)*LN(E18/(D18*G18))+H18/2) -> 0.41790376 | J18: =NORMSDIST(-I18+H18) -> 0.33860082 | K18: =NORMSDIST(-I18) -> 0.33800874 | L18: =IF(H18=0,0,(1+F18*0.25)*(G18*D18*J18-E18*K18)) -> 0.0003534109 | M18: =L18*10000 -> 3.534109
B19: 1 | C19: 1.25 | D19: =VLOOKUP(B19,OIS_Curve!$B$19:$D$58,3,FALSE()) -> 0.96339114 | E19: =VLOOKUP(C19,OIS_Curve!$B$19:$D$58,3,FALSE()) -> 0.95474312 | F19: =Par_Rates!$E$6 -> 0.0367 | G19: =1/(1+F19*0.25) -> 0.99090842 | H19: =IF(B19=0,0,(Parameters!$C$5/Parameters!$C$4)*(1-EXP(-Parameters!$C$4*0.25))*SQRT((1-EXP(-2*Parameters!$C$4*B19))/(2*Parameters!$C$4))) -> 0.0018336131 | I19: =IF(H19=0,0,(1/H19)*LN(E19/(D19*G19))+H19/2) -> 0.06417636 | J19: =NORMSDIST(-I19+H19) -> 0.47514494 | K19: =NORMSDIST(-I19) -> 0.4744149 | L19: =IF(H19=0,0,(1+F19*0.25)*(G19*D19*J19-E19*K19)) -> 0.00065029983 | M19: =L19*10000 -> 6.5029983
B20: 1.25 | C20: 1.5 | D20: =VLOOKUP(B20,OIS_Curve!$B$19:$D$58,3,FALSE()) -> 0.95474312 | E20: =VLOOKUP(C20,OIS_Curve!$B$19:$D$58,3,FALSE()) -> 0.94628885 | F20: =Par_Rates!$E$6 -> 0.0367 | G20: =1/(1+F20*0.25) -> 0.99090842 | H20: =IF(B20=0,0,(Parameters!$C$5/Parameters!$C$4)*(1-EXP(-Parameters!$C$4*0.25))*SQRT((1-EXP(-2*Parameters!$C$4*B20))/(2*Parameters!$C$4))) -> 0.0020112979 | I20: =IF(H20=0,0,(1/H20)*LN(E20/(D20*G20))+H20/2) -> 0.11968687 | J20: =NORMSDIST(-I20+H20) -> 0.45316236 | K20: =NORMSDIST(-I20) -> 0.4523656 | L20: =IF(H20=0,0,(1+F20*0.25)*(G20*D20*J20-E20*K20)) -> 0.00065759508 | M20: =L20*10000 -> 6.5759508
B21: 1.5 | C21: 1.75 | D21: =VLOOKUP(B21,OIS_Curve!$B$19:$D$58,3,FALSE()) -> 0.94628885 | E21: =VLOOKUP(C21,OIS_Curve!$B$19:$D$58,3,FALSE()) -> 0.93802454 | F21: =Par_Rates!$E$6 -> 0.0367 | G21: =1/(1+F21*0.25) -> 0.99090842 | H21: =IF(B21=0,0,(Parameters!$C$5/Parameters!$C$4)*(1-EXP(-Parameters!$C$4*0.25))*SQRT((1-EXP(-2*Parameters!$C$4*B21))/(2*Parameters!$C$4))) -> 0.0021622167 | I21: =IF(H21=0,0,(1/H21)*LN(E21/(D21*G21))+H21/2) -> 0.16823042 | J21: =NORMSDIST(-I21+H21) -> 0.43405164 | K21: =NORMSDIST(-I21) -> 0.43320101 | L21: =IF(H21=0,0,(1+F21*0.25)*(G21*D21*J21-E21*K21)) -> 0.00065676274 | M21: =L21*10000 -> 6.5676274
B22: 1.75 | C22: 2 | D22: =VLOOKUP(B22,OIS_Curve!$B$19:$D$58,3,FALSE()) -> 0.93802454 | E22: =VLOOKUP(C22,OIS_Curve!$B$19:$D$58,3,FALSE()) -> 0.92994651 | F22: =Par_Rates!$E$6 -> 0.0367 | G22: =1/(1+F22*0.25) -> 0.99090842 | H22: =IF(B22=0,0,(Parameters!$C$5/Parameters!$C$4)*(1-EXP(-Parameters!$C$4*0.25))*SQRT((1-EXP(-2*Parameters!$C$4*B22))/(2*Parameters!$C$4))) -> 0.0022925715 | I22: =IF(H22=0,0,(1/H22)*LN(E22/(D22*G22))+H22/2) -> 0.21231648 | J22: =NORMSDIST(-I22+H22) -> 0.41682451 | K22: =NORMSDIST(-I22) -> 0.41593007 | L22: =IF(H22=0,0,(1+F22*0.25)*(G22*D22*J22-E22*K22)) -> 0.00065007615 | M22: =L22*10000 -> 6.5007615
B23: 2 | C23: 2.25 | D23: =VLOOKUP(B23,OIS_Curve!$B$19:$D$58,3,FALSE()) -> 0.92994651 | E23: =VLOOKUP(C23,OIS_Curve!$B$19:$D$58,3,FALSE()) -> 0.92179827 | F23: =Par_Rates!$E$6 -> 0.0367 | G23: =1/(1+F23*0.25) -> 0.99090842 | H23: =IF(B23=0,0,(Parameters!$C$5/Parameters!$C$4)*(1-EXP(-Parameters!$C$4*0.25))*SQRT((1-EXP(-2*Parameters!$C$4*B23))/(2*Parameters!$C$4))) -> 0.0024065047 | I23: =IF(H23=0,0,(1/H23)*LN(E23/(D23*G23))+H23/2) -> 0.13936975 | J23: =NORMSDIST(-I23+H23) -> 0.44552992 | K23: =NORMSDIST(-I23) -> 0.44457899 | L23: =IF(H23=0,0,(1+F23*0.25)*(G23*D23*J23-E23*K23)) -> 0.00074683052 | M23: =L23*10000 -> 7.4683052
B24: 2.25 | C24: 2.5 | D24: =VLOOKUP(B24,OIS_Curve!$B$19:$D$58,3,FALSE()) -> 0.92179827 | E24: =VLOOKUP(C24,OIS_Curve!$B$19:$D$58,3,FALSE()) -> 0.91377784 | F24: =Par_Rates!$E$6 -> 0.0367 | G24: =1/(1+F24*0.25) -> 0.99090842 | H24: =IF(B24=0,0,(Parameters!$C$5/Parameters!$C$4)*(1-EXP(-Parameters!$C$4*0.25))*SQRT((1-EXP(-2*Parameters!$C$4*B24))/(2*Parameters!$C$4))) -> 0.0025069625 | I24: =IF(H24=0,0,(1/H24)*LN(E24/(D24*G24))+H24/2) -> 0.15851348 | J24: =NORMSDIST(-I24+H24) -> 0.43801394 | K24: =NORMSDIST(-I24) -> 0.4370261 | L24: =IF(H24=0,0,(1+F24*0.25)*(G24*D24*J24-E24*K24)) -> 0.00075173841 | M24: =L24*10000 -> 7.5173841
B25: 2.5 | C25: 2.75 | D25: =VLOOKUP(B25,OIS_Curve!$B$19:$D$58,3,FALSE()) -> 0.91377784 | E25: =VLOOKUP(C25,OIS_Curve!$B$19:$D$58,3,FALSE()) -> 0.90588313 | F25: =Par_Rates!$E$6 -> 0.0367 | G25: =1/(1+F25*0.25) -> 0.99090842 | H25: =IF(B25=0,0,(Parameters!$C$5/Parameters!$C$4)*(1-EXP(-Parameters!$C$4*0.25))*SQRT((1-EXP(-2*Parameters!$C$4*B25))/(2*Parameters!$C$4))) -> 0.0025961381 | I25: =IF(H25=0,0,(1/H25)*LN(E25/(D25*G25))+H25/2) -> 0.17694031 | J25: =NORMSDIST(-I25+H25) -> 0.43079749 | K25: =NORMSDIST(-I25) -> 0.42977764 | L25: =IF(H25=0,0,(1+F25*0.25)*(G25*D25*J25-E25*K25)) -> 0.00075280309 | M25: =L25*10000 -> 7.5280309
B26: 2.75 | C26: 3 | D26: =VLOOKUP(B26,OIS_Curve!$B$19:$D$58,3,FALSE()) -> 0.90588313 | E26: =VLOOKUP(C26,OIS_Curve!$B$19:$D$58,3,FALSE()) -> 0.89811208 | F26: =Par_Rates!$E$6 -> 0.0367 | G26: =1/(1+F26*0.25) -> 0.99090842 | H26: =IF(B26=0,0,(Parameters!$C$5/Parameters!$C$4)*(1-EXP(-Parameters!$C$4*0.25))*SQRT((1-EXP(-2*Parameters!$C$4*B26))/(2*Parameters!$C$4))) -> 0.002675722 | I26: =IF(H26=0,0,(1/H26)*LN(E26/(D26*G26))+H26/2) -> 0.19483259 | J26: =NORMSDIST(-I26+H26) -> 0.42380967 | K26: =NORMSDIST(-I26) -> 0.42276201 | L26: =IF(H26=0,0,(1+F26*0.25)*(G26*D26*J26-E26*K26)) -> 0.00075072765 | M26: =L26*10000 -> 7.5072765
B27: Cap 3Y Total (Model) | L27: =SUM(L16:L26) -> 0.007031273 | M27: =SUM(M16:M26) -> 70.31273
B29: 5Y Cap · K = 3.640% · 19 caplets (T_start = 0.25 to 4.75)
B30: T_start | C30: T_end | D30: P(0,S) | E30: P(0,S+δ) | F30: K | G30: K̃ | H30: σ_p | I30: h | J30: Φ(-h+σ_p) | K30: Φ(-h) | L30: Caplet (dec) | M30: Caplet (bps)
B31: 0.25 | C31: 0.5 | D31: =VLOOKUP(B31,OIS_Curve!$B$19:$D$58,3,FALSE()) -> 0.98973154 | E31: =VLOOKUP(C31,OIS_Curve!$B$19:$D$58,3,FALSE()) -> 0.98039216 | F31: =Par_Rates!$E$7 -> 0.036400127 | G31: =1/(1+F31*0.25) -> 0.99098203 | H31: =IF(B31=0,0,(Parameters!$C$5/Parameters!$C$4)*(1-EXP(-Parameters!$C$4*0.25))*SQRT((1-EXP(-2*Parameters!$C$4*B31))/(2*Parameters!$C$4))) -> 0.00097241305 | I31: =IF(H31=0,0,(1/H31)*LN(E31/(D31*G31))+H31/2) -> -0.43369367 | J31: =NORMSDIST(-I31+H31) -> 0.66809759 | K31: =NORMSDIST(-I31) -> 0.66774455 | L31: =IF(H31=0,0,(1+F31*0.25)*(G31*D31*J31-E31*K31)) -> 0.00062838583 | M31: =L31*10000 -> 6.2838583
B32: 0.5 | C32: 0.75 | D32: =VLOOKUP(B32,OIS_Curve!$B$19:$D$58,3,FALSE()) -> 0.98039216 | E32: =VLOOKUP(C32,OIS_Curve!$B$19:$D$58,3,FALSE()) -> 0.97157395 | F32: =Par_Rates!$E$7 -> 0.036400127 | G32: =1/(1+F32*0.25) -> 0.99098203 | H32: =IF(B32=0,0,(Parameters!$C$5/Parameters!$C$4)*(1-EXP(-Parameters!$C$4*0.25))*SQRT((1-EXP(-2*Parameters!$C$4*B32))/(2*Parameters!$C$4))) -> 0.0013481001 | I32: =IF(H32=0,0,(1/H32)*LN(E32/(D32*G32))+H32/2) -> 0.018190254 | J32: =NORMSDIST(-I32+H32) -> 0.49328127 | K32: =NORMSDIST(-I32) -> 0.49274354 | L32: =IF(H32=0,0,(1+F32*0.25)*(G32*D32*J32-E32*K32)) -> 0.00051578041 | M32: =L32*10000 -> 5.1578041
B33: 0.75 | C33: 1 | D33: =VLOOKUP(B33,OIS_Curve!$B$19:$D$58,3,FALSE()) -> 0.97157395 | E33: =VLOOKUP(C33,OIS_Curve!$B$19:$D$58,3,FALSE()) -> 0.96339114 | F33: =Par_Rates!$E$7 -> 0.036400127 | G33: =1/(1+F33*0.25) -> 0.99098203 | H33: =IF(B33=0,0,(Parameters!$C$5/Parameters!$C$4)*(1-EXP(-Parameters!$C$4*0.25))*SQRT((1-EXP(-2*Parameters!$C$4*B33))/(2*Parameters!$C$4))) -> 0.0016189875 | I33: =IF(H33=0,0,(1/H33)*LN(E33/(D33*G33))+H33/2) -> 0.37201747 | J33: =NORMSDIST(-I33+H33) -> 0.3555428 | K33: =NORMSDIST(-I33) -> 0.35493992 | L33: =IF(H33=0,0,(1+F33*0.25)*(G33*D33*J33-E33*K33)) -> 0.00037843268 | M33: =L33*10000 -> 3.7843268
B34: 1 | C34: 1.25 | D34: =VLOOKUP(B34,OIS_Curve!$B$19:$D$58,3,FALSE()) -> 0.96339114 | E34: =VLOOKUP(C34,OIS_Curve!$B$19:$D$58,3,FALSE()) -> 0.95474312 | F34: =Par_Rates!$E$7 -> 0.036400127 | G34: =1/(1+F34*0.25) -> 0.99098203 | H34: =IF(B34=0,0,(Parameters!$C$5/Parameters!$C$4)*(1-EXP(-Parameters!$C$4*0.25))*SQRT((1-EXP(-2*Parameters!$C$4*B34))/(2*Parameters!$C$4))) -> 0.0018336131 | I34: =IF(H34=0,0,(1/H34)*LN(E34/(D34*G34))+H34/2) -> 0.02366109 | J34: =NORMSDIST(-I34+H34) -> 0.49129279 | K34: =NORMSDIST(-I34) -> 0.49056147 | L34: =IF(H34=0,0,(1+F34*0.25)*(G34*D34*J34-E34*K34)) -> 0.0006848339 | M34: =L34*10000 -> 6.848339
B35: 1.25 | C35: 1.5 | D35: =VLOOKUP(B35,OIS_Curve!$B$19:$D$58,3,FALSE()) -> 0.95474312 | E35: =VLOOKUP(C35,OIS_Curve!$B$19:$D$58,3,FALSE()) -> 0.94628885 | F35: =Par_Rates!$E$7 -> 0.036400127 | G35: =1/(1+F35*0.25) -> 0.99098203 | H35: =IF(B35=0,0,(Parameters!$C$5/Parameters!$C$4)*(1-EXP(-Parameters!$C$4*0.25))*SQRT((1-EXP(-2*Parameters!$C$4*B35))/(2*Parameters!$C$4))) -> 0.0020112979 | I35: =IF(H35=0,0,(1/H35)*LN(E35/(D35*G35))+H35/2) -> 0.082750853 | J35: =NORMSDIST(-I35+H35) -> 0.46782454 | K35: =NORMSDIST(-I35) -> 0.46702482 | L35: =IF(H35=0,0,(1+F35*0.25)*(G35*D35*J35-E35*K35)) -> 0.00069020622 | M35: =L35*10000 -> 6.9020622
B36: 1.5 | C36: 1.75 | D36: =VLOOKUP(B36,OIS_Curve!$B$19:$D$58,3,FALSE()) -> 0.94628885 | E36: =VLOOKUP(C36,OIS_Curve!$B$19:$D$58,3,FALSE()) -> 0.93802454 | F36: =Par_Rates!$E$7 -> 0.036400127 | G36: =1/(1+F36*0.25) -> 0.99098203 | H36: =IF(B36=0,0,(Parameters!$C$5/Parameters!$C$4)*(1-EXP(-Parameters!$C$4*0.25))*SQRT((1-EXP(-2*Parameters!$C$4*B36))/(2*Parameters!$C$4))) -> 0.0021622167 | I36: =IF(H36=0,0,(1/H36)*LN(E36/(D36*G36))+H36/2) -> 0.13387247 | J36: =NORMSDIST(-I36+H36) -> 0.44760674 | K36: =NORMSDIST(-I36) -> 0.44675171 | L36: =IF(H36=0,0,(1+F36*0.25)*(G36*D36*J36-E36*K36)) -> 0.00068770232 | M36: =L36*10000 -> 6.8770232
B37: 1.75 | C37: 2 | D37: =VLOOKUP(B37,OIS_Curve!$B$19:$D$58,3,FALSE()) -> 0.93802454 | E37: =VLOOKUP(C37,OIS_Curve!$B$19:$D$58,3,FALSE()) -> 0.92994651 | F37: =Par_Rates!$E$7 -> 0.036400127 | G37: =1/(1+F37*0.25) -> 0.99098203 | H37: =IF(B37=0,0,(Parameters!$C$5/Parameters!$C$4)*(1-EXP(-Parameters!$C$4*0.25))*SQRT((1-EXP(-2*Parameters!$C$4*B37))/(2*Parameters!$C$4))) -> 0.0022925715 | I37: =IF(H37=0,0,(1/H37)*LN(E37/(D37*G37))+H37/2) -> 0.17991211 | J37: =NORMSDIST(-I37+H37) -> 0.42951089 | K37: =NORMSDIST(-I37) -> 0.42861078 | L37: =IF(H37=0,0,(1+F37*0.25)*(G37*D37*J37-E37*K37)) -> 0.00067951484 | M37: =L37*10000 -> 6.7951484
B38: 2 | C38: 2.25 | D38: =VLOOKUP(B38,OIS_Curve!$B$19:$D$58,3,FALSE()) -> 0.92994651 | E38: =VLOOKUP(C38,OIS_Curve!$B$19:$D$58,3,FALSE()) -> 0.92179827 | F38: =Par_Rates!$E$7 -> 0.036400127 | G38: =1/(1+F38*0.25) -> 0.99098203 | H38: =IF(B38=0,0,(Parameters!$C$5/Parameters!$C$4)*(1-EXP(-Parameters!$C$4*0.25))*SQRT((1-EXP(-2*Parameters!$C$4*B38))/(2*Parameters!$C$4))) -> 0.0024065047 | I38: =IF(H38=0,0,(1/H38)*LN(E38/(D38*G38))+H38/2) -> 0.10849953 | J38: =NORMSDIST(-I38+H38) -> 0.45775427 | K38: =NORMSDIST(-I38) -> 0.45679973 | L38: =IF(H38=0,0,(1+F38*0.25)*(G38*D38*J38-E38*K38)) -> 0.00077797537 | M38: =L38*10000 -> 7.7797537
B39: 2.25 | C39: 2.5 | D39: =VLOOKUP(B39,OIS_Curve!$B$19:$D$58,3,FALSE()) -> 0.92179827 | E39: =VLOOKUP(C39,OIS_Curve!$B$19:$D$58,3,FALSE()) -> 0.91377784 | F39: =Par_Rates!$E$7 -> 0.036400127 | G39: =1/(1+F39*0.25) -> 0.99098203 | H39: =IF(B39=0,0,(Parameters!$C$5/Parameters!$C$4)*(1-EXP(-Parameters!$C$4*0.25))*SQRT((1-EXP(-2*Parameters!$C$4*B39))/(2*Parameters!$C$4))) -> 0.0025069625 | I39: =IF(H39=0,0,(1/H39)*LN(E39/(D39*G39))+H39/2) -> 0.12888028 | J39: =NORMSDIST(-I39+H39) -> 0.44971821 | K39: =NORMSDIST(-I39) -> 0.44872619 | L39: =IF(H39=0,0,(1+F39*0.25)*(G39*D39*J39-E39*K39)) -> 0.00078207701 | M39: =L39*10000 -> 7.8207701
B40: 2.5 | C40: 2.75 | D40: =VLOOKUP(B40,OIS_Curve!$B$19:$D$58,3,FALSE()) -> 0.91377784 | E40: =VLOOKUP(C40,OIS_Curve!$B$19:$D$58,3,FALSE()) -> 0.90588313 | F40: =Par_Rates!$E$7 -> 0.036400127 | G40: =1/(1+F40*0.25) -> 0.99098203 | H40: =IF(B40=0,0,(Parameters!$C$5/Parameters!$C$4)*(1-EXP(-Parameters!$C$4*0.25))*SQRT((1-EXP(-2*Parameters!$C$4*B40))/(2*Parameters!$C$4))) -> 0.0025961381 | I40: =IF(H40=0,0,(1/H40)*LN(E40/(D40*G40))+H40/2) -> 0.14832498 | J40: =NORMSDIST(-I40+H40) -> 0.44206772 | K40: =NORMSDIST(-I40) -> 0.44104315 | L40: =IF(H40=0,0,(1+F40*0.25)*(G40*D40*J40-E40*K40)) -> 0.00078237254 | M40: =L40*10000 -> 7.8237254
B41: 2.75 | C41: 3 | D41: =VLOOKUP(B41,OIS_Curve!$B$19:$D$58,3,FALSE()) -> 0.90588313 | E41: =VLOOKUP(C41,OIS_Curve!$B$19:$D$58,3,FALSE()) -> 0.89811208 | F41: =Par_Rates!$E$7 -> 0.036400127 | G41: =1/(1+F41*0.25) -> 0.99098203 | H41: =IF(B41=0,0,(Parameters!$C$5/Parameters!$C$4)*(1-EXP(-Parameters!$C$4*0.25))*SQRT((1-EXP(-2*Parameters!$C$4*B41))/(2*Parameters!$C$4))) -> 0.002675722 | I41: =IF(H41=0,0,(1/H41)*LN(E41/(D41*G41))+H41/2) -> 0.16706837 | J41: =NORMSDIST(-I41+H41) -> 0.43471103 | K41: =NORMSDIST(-I41) -> 0.43365813 | L41: =IF(H41=0,0,(1+F41*0.25)*(G41*D41*J41-E41*K41)) -> 0.00077955864 | M41: =L41*10000 -> 7.7955864
B42: 3 | C42: 3.25 | D42: =VLOOKUP(B42,OIS_Curve!$B$19:$D$58,3,FALSE()) -> 0.89811208 | E42: =VLOOKUP(C42,OIS_Curve!$B$19:$D$58,3,FALSE()) -> 0.89004033 | F42: =Par_Rates!$E$7 -> 0.036400127 | G42: =1/(1+F42*0.25) -> 0.99098203 | H42: =IF(B42=0,0,(Parameters!$C$5/Parameters!$C$4)*(1-EXP(-Parameters!$C$4*0.25))*SQRT((1-EXP(-2*Parameters!$C$4*B42))/(2*Parameters!$C$4))) -> 0.0027470527 | I42: =IF(H42=0,0,(1/H42)*LN(E42/(D42*G42))+H42/2) -> 0.012575352 | J42: =NORMSDIST(-I42+H42) -> 0.49607914 | K42: =NORMSDIST(-I42) -> 0.49498329 | L42: =IF(H42=0,0,(1+F42*0.25)*(G42*D42*J42-E42*K42)) -> 0.00097051294 | M42: =L42*10000 -> 9.7051294
... B49: 4.75 | C49: 5 | D49: =VLOOKUP(B49,OIS_Curve!$B$19:$D$58,3,FALSE()) -> 0.84498204 | E49: =VLOOKUP(C49,OIS_Curve!$B$19:$D$58,3,FALSE()) -> 0.83815119 | F49: =Par_Rates!$E$7 -> 0.036400127 | G49: =1/(1+F49*0.25) -> 0.99098203 | H49: =IF(B49=0,0,(Parameters!$C$5/Parameters!$C$4)*(1-EXP(-Parameters!$C$4*0.25))*SQRT((1-EXP(-2*Parameters!$C$4*B49))/(2*Parameters!$C$4))) -> 0.0030868291 | I49: =IF(H49=0,0,(1/H49)*LN(E49/(D49*G49))+H49/2) -> 0.30671355 | J49: =NORMSDIST(-I49+H49) -> 0.38070614 | K49: =NORMSDIST(-I49) -> 0.37953071 | L49: =IF(H49=0,0,(1+F49*0.25)*(G49*D49*J49-E49*K49)) -> 0.00069098309 | M49: =L49*10000 -> 6.9098309
B50: Cap 5Y Total (Model) | L50: =SUM(L31:L49) -> 0.014246292 | M50: =SUM(M31:M49) -> 142.46292
B52: 7Y Cap · K = 3.620% · 27 caplets (T_start = 0.25 to 6.75)
B53: T_start | C53: T_end | D53: P(0,S) | E53: P(0,S+δ) | F53: K | G53: K̃ | H53: σ_p | I53: h | J53: Φ(-h+σ_p) | K53: Φ(-h) | L53: Caplet (dec) | M53: Caplet (bps)
B54: 0.25 | C54: 0.5 | D54: =VLOOKUP(B54,OIS_Curve!$B$19:$D$58,3,FALSE()) -> 0.98973154 | E54: =VLOOKUP(C54,OIS_Curve!$B$19:$D$58,3,FALSE()) -> 0.98039216 | F54: =Par_Rates!$E$8 -> 0.036200201 | G54: =1/(1+F54*0.25) -> 0.99103112 | H54: =IF(B54=0,0,(Parameters!$C$5/Parameters!$C$4)*(1-EXP(-Parameters!$C$4*0.25))*SQRT((1-EXP(-2*Parameters!$C$4*B54))/(2*Parameters!$C$4))) -> 0.00097241305 | I54: =IF(H54=0,0,(1/H54)*LN(E54/(D54*G54))+H54/2) -> -0.48463086 | J54: =NORMSDIST(-I54+H54) -> 0.68637576 | K54: =NORMSDIST(-I54) -> 0.68603089 | L54: =IF(H54=0,0,(1+F54*0.25)*(G54*D54*J54-E54*K54)) -> 0.00066155607 | M54: =L54*10000 -> 6.6155607
B55: 0.5 | C55: 0.75 | D55: =VLOOKUP(B55,OIS_Curve!$B$19:$D$58,3,FALSE()) -> 0.98039216 | E55: =VLOOKUP(C55,OIS_Curve!$B$19:$D$58,3,FALSE()) -> 0.97157395 | F55: =Par_Rates!$E$8 -> 0.036200201 | G55: =1/(1+F55*0.25) -> 0.99103112 | H55: =IF(B55=0,0,(Parameters!$C$5/Parameters!$C$4)*(1-EXP(-Parameters!$C$4*0.25))*SQRT((1-EXP(-2*Parameters!$C$4*B55))/(2*Parameters!$C$4))) -> 0.0013481001 | I55: =IF(H55=0,0,(1/H55)*LN(E55/(D55*G55))+H55/2) -> -0.01855182 | J55: =NORMSDIST(-I55+H55) -> 0.5079384 | K55: =NORMSDIST(-I55) -> 0.50740068 | L55: =IF(H55=0,0,(1+F55*0.25)*(G55*D55*J55-E55*K55)) -> 0.00054006427 | M55: =L55*10000 -> 5.4006427
B56: 0.75 | C56: 1 | D56: =VLOOKUP(B56,OIS_Curve!$B$19:$D$58,3,FALSE()) -> 0.97157395 | E56: =VLOOKUP(C56,OIS_Curve!$B$19:$D$58,3,FALSE()) -> 0.96339114 | F56: =Par_Rates!$E$8 -> 0.036200201 | G56: =1/(1+F56*0.25) -> 0.99103112 | H56: =IF(B56=0,0,(Parameters!$C$5/Parameters!$C$4)*(1-EXP(-Parameters!$C$4*0.25))*SQRT((1-EXP(-2*Parameters!$C$4*B56))/(2*Parameters!$C$4))) -> 0.0016189875 | I56: =IF(H56=0,0,(1/H56)*LN(E56/(D56*G56))+H56/2) -> 0.34142304 | J56: =NORMSDIST(-I56+H56) -> 0.36700205 | K56: =NORMSDIST(-I56) -> 0.36639257 | L56: =IF(H56=0,0,(1+F56*0.25)*(G56*D56*J56-E56*K56)) -> 0.00039579889 | M56: =L56*10000 -> 3.9579889
B57: 1 | C57: 1.25 | D57: =VLOOKUP(B57,OIS_Curve!$B$19:$D$58,3,FALSE()) -> 0.96339114 | E57: =VLOOKUP(C57,OIS_Curve!$B$19:$D$58,3,FALSE()) -> 0.95474312 | F57: =Par_Rates!$E$8 -> 0.036200201 | G57: =1/(1+F57*0.25) -> 0.99103112 | H57: =IF(B57=0,0,(Parameters!$C$5/Parameters!$C$4)*(1-EXP(-Parameters!$C$4*0.25))*SQRT((1-EXP(-2*Parameters!$C$4*B57))/(2*Parameters!$C$4))) -> 0.0018336131 | I57: =IF(H57=0,0,(1/H57)*LN(E57/(D57*G57))+H57/2) -> -0.0033522411 | J57: =NORMSDIST(-I57+H57) -> 0.50206885 | K57: =NORMSDIST(-I57) -> 0.50133735 | L57: =IF(H57=0,0,(1+F57*0.25)*(G57*D57*J57-E57*K57)) -> 0.00070850034 | M57: =L57*10000 -> 7.0850034
B58: 1.25 | C58: 1.5 | D58: =VLOOKUP(B58,OIS_Curve!$B$19:$D$58,3,FALSE()) -> 0.95474312 | E58: =VLOOKUP(C58,OIS_Curve!$B$19:$D$58,3,FALSE()) -> 0.94628885 | F58: =Par_Rates!$E$8 -> 0.036200201 | G58: =1/(1+F58*0.25) -> 0.99103112 | H58: =IF(B58=0,0,(Parameters!$C$5/Parameters!$C$4)*(1-EXP(-Parameters!$C$4*0.25))*SQRT((1-EXP(-2*Parameters!$C$4*B58))/(2*Parameters!$C$4))) -> 0.0020112979 | I58: =IF(H58=0,0,(1/H58)*LN(E58/(D58*G58))+H58/2) -> 0.05812397 | J58: =NORMSDIST(-I58+H58) -> 0.47762602 | K58: =NORMSDIST(-I58) -> 0.47682494 | L58: =IF(H58=0,0,(1+F58*0.25)*(G58*D58*J58-E58*K58)) -> 0.00071252676 | M58: =L58*10000 -> 7.1252676
B59: 1.5 | C59: 1.75 | D59: =VLOOKUP(B59,OIS_Curve!$B$19:$D$58,3,FALSE()) -> 0.94628885 | E59: =VLOOKUP(C59,OIS_Curve!$B$19:$D$58,3,FALSE()) -> 0.93802454 | F59: =Par_Rates!$E$8 -> 0.036200201 | G59: =1/(1+F59*0.25) -> 0.99103112 | H59: =IF(B59=0,0,(Parameters!$C$5/Parameters!$C$4)*(1-EXP(-Parameters!$C$4*0.25))*SQRT((1-EXP(-2*Parameters!$C$4*B59))/(2*Parameters!$C$4))) -> 0.0021622167 | I59: =IF(H59=0,0,(1/H59)*LN(E59/(D59*G59))+H59/2) -> 0.1109645 | J59: =NORMSDIST(-I59+H59) -> 0.45667966 | K59: =NORMSDIST(-I59) -> 0.45582225 | L59: =IF(H59=0,0,(1+F59*0.25)*(G59*D59*J59-E59*K59)) -> 0.0007088603 | M59: =L59*10000 -> 7.088603
B60: 1.75 | C60: 2 | D60: =VLOOKUP(B60,OIS_Curve!$B$19:$D$58,3,FALSE()) -> 0.93802454 | E60: =VLOOKUP(C60,OIS_Curve!$B$19:$D$58,3,FALSE()) -> 0.92994651 | F60: =Par_Rates!$E$8 -> 0.036200201 | G60: =1/(1+F60*0.25) -> 0.99103112 | H60: =IF(B60=0,0,(Parameters!$C$5/Parameters!$C$4)*(1-EXP(-Parameters!$C$4*0.25))*SQRT((1-EXP(-2*Parameters!$C$4*B60))/(2*Parameters!$C$4))) -> 0.0022925715 | I60: =IF(H60=0,0,(1/H60)*LN(E60/(D60*G60))+H60/2) -> 0.15830668 | J60: =NORMSDIST(-I60+H60) -> 0.43801095 | K60: =NORMSDIST(-I60) -> 0.43710757 | L60: =IF(H60=0,0,(1+F60*0.25)*(G60*D60*J60-E60*K60)) -> 0.00069963407 | M60: =L60*10000 -> 6.9963407
B61: 2 | C61: 2.25 | D61: =VLOOKUP(B61,OIS_Curve!$B$19:$D$58,3,FALSE()) -> 0.92994651 | E61: =VLOOKUP(C61,OIS_Curve!$B$19:$D$58,3,FALSE()) -> 0.92179827 | F61: =Par_Rates!$E$8 -> 0.036200201 | G61: =1/(1+F61*0.25) -> 0.99103112 | H61: =IF(B61=0,0,(Parameters!$C$5/Parameters!$C$4)*(1-EXP(-Parameters!$C$4*0.25))*SQRT((1-EXP(-2*Parameters!$C$4*B61))/(2*Parameters!$C$4))) -> 0.0024065047 | I61: =IF(H61=0,0,(1/H61)*LN(E61/(D61*G61))+H61/2) -> 0.087916984 | J61: =NORMSDIST(-I61+H61) -> 0.46592778 | K61: =NORMSDIST(-I61) -> 0.46497133 | L61: =IF(H61=0,0,(1+F61*0.25)*(G61*D61*J61-E61*K61)) -> 0.00079920962 | M61: =L61*10000 -> 7.9920962
B62: 2.25 | C62: 2.5 | D62: =VLOOKUP(B62,OIS_Curve!$B$19:$D$58,3,FALSE()) -> 0.92179827 | E62: =VLOOKUP(C62,OIS_Curve!$B$19:$D$58,3,FALSE()) -> 0.91377784 | F62: =Par_Rates!$E$8 -> 0.036200201 | G62: =1/(1+F62*0.25) -> 0.99103112 | H62: =IF(B62=0,0,(Parameters!$C$5/Parameters!$C$4)*(1-EXP(-Parameters!$C$4*0.25))*SQRT((1-EXP(-2*Parameters!$C$4*B62))/(2*Parameters!$C$4))) -> 0.0025069625 | I62: =IF(H62=0,0,(1/H62)*LN(E62/(D62*G62))+H62/2) -> 0.1091225 | J62: =NORMSDIST(-I62+H62) -> 0.45754699 | K62: =NORMSDIST(-I62) -> 0.45655266 | L62: =IF(H62=0,0,(1+F62*0.25)*(G62*D62*J62-E62*K62)) -> 0.00080274988 | M62: =L62*10000 -> 8.0274988
B63: 2.5 | C63: 2.75 | D63: =VLOOKUP(B63,OIS_Curve!$B$19:$D$58,3,FALSE()) -> 0.91377784 | E63: =VLOOKUP(C63,OIS_Curve!$B$19:$D$58,3,FALSE()) -> 0.90588313 | F63: =Par_Rates!$E$8 -> 0.036200201 | G63: =1/(1+F63*0.25) -> 0.99103112 | H63: =IF(B63=0,0,(Parameters!$C$5/Parameters!$C$4)*(1-EXP(-Parameters!$C$4*0.25))*SQRT((1-EXP(-2*Parameters!$C$4*B63))/(2*Parameters!$C$4))) -> 0.0025961381 | I63: =IF(H63=0,0,(1/H63)*LN(E63/(D63*G63))+H63/2) -> 0.12924588 | J63: =NORMSDIST(-I63+H63) -> 0.44960881 | K63: =NORMSDIST(-I63) -> 0.44858155 | L63: =IF(H63=0,0,(1+F63*0.25)*(G63*D63*J63-E63*K63)) -> 0.00080251241 | M63: =L63*10000 -> 8.0251241
B64: 2.75 | C64: 3 | D64: =VLOOKUP(B64,OIS_Curve!$B$19:$D$58,3,FALSE()) -> 0.90588313 | E64: =VLOOKUP(C64,OIS_Curve!$B$19:$D$58,3,FALSE()) -> 0.89811208 | F64: =Par_Rates!$E$8 -> 0.036200201 | G64: =1/(1+F64*0.25) -> 0.99103112 | H64: =IF(B64=0,0,(Parameters!$C$5/Parameters!$C$4)*(1-EXP(-Parameters!$C$4*0.25))*SQRT((1-EXP(-2*Parameters!$C$4*B64))/(2*Parameters!$C$4))) -> 0.002675722 | I64: =IF(H64=0,0,(1/H64)*LN(E64/(D64*G64))+H64/2) -> 0.14855673 | J64: =NORMSDIST(-I64+H64) -> 0.44200766 | K64: =NORMSDIST(-I64) -> 0.44095171 | L64: =IF(H64=0,0,(1+F64*0.25)*(G64*D64*J64-E64*K64)) -> 0.00079918873 | M64: =L64*10000 -> 7.9918873
B65: 3 | C65: 3.25 | D65: =VLOOKUP(B65,OIS_Curve!$B$19:$D$58,3,FALSE()) -> 0.89811208 | E65: =VLOOKUP(C65,OIS_Curve!$B$19:$D$58,3,FALSE()) -> 0.89004033 | F65: =Par_Rates!$E$8 -> 0.036200201 | G65: =1/(1+F65*0.25) -> 0.99103112 | H65: =IF(B65=0,0,(Parameters!$C$5/Parameters!$C$4)*(1-EXP(-Parameters!$C$4*0.25))*SQRT((1-EXP(-2*Parameters!$C$4*B65))/(2*Parameters!$C$4))) -> 0.0027470527 | I65: =IF(H65=0,0,(1/H65)*LN(E65/(D65*G65))+H65/2) -> -0.0054556071 | J65: =NORMSDIST(-I65+H65) -> 0.50327235 | K65: =NORMSDIST(-I65) -> 0.50217646 | L65: =IF(H65=0,0,(1+F65*0.25)*(G65*D65*J65-E65*K65)) -> 0.00099269254 | M65: =L65*10000 -> 9.9269254
... B80: 6.75 | C80: 7 | D80: =VLOOKUP(B80,OIS_Curve!$B$19:$D$58,3,FALSE()) -> 0.78842282 | E80: =VLOOKUP(C80,OIS_Curve!$B$19:$D$58,3,FALSE()) -> 0.78212785 | F80: =Par_Rates!$E$8 -> 0.036200201 | G80: =1/(1+F80*0.25) -> 0.99103112 | H80: =IF(B80=0,0,(Parameters!$C$5/Parameters!$C$4)*(1-EXP(-Parameters!$C$4*0.25))*SQRT((1-EXP(-2*Parameters!$C$4*B80))/(2*Parameters!$C$4))) -> 0.0032810279 | I80: =IF(H80=0,0,(1/H80)*LN(E80/(D80*G80))+H80/2) -> 0.30430224 | J80: =NORMSDIST(-I80+H80) -> 0.38169916 | K80: =NORMSDIST(-I80) -> 0.38044882 | L80: =IF(H80=0,0,(1+F80*0.25)*(G80*D80*J80-E80*K80)) -> 0.00068778156 | M80: =L80*10000 -> 6.8778156
B81: Cap 7Y Total (Model) | L81: =SUM(L54:L80) -> 0.021983469 | M81: =SUM(M54:M80) -> 219.83469
B83: 10Y Cap · K = 3.590% · 39 caplets (T_start = 0.25 to 9.75)
B84: T_start | C84: T_end | D84: P(0,S) | E84: P(0,S+δ) | F84: K | G84: K̃ | H84: σ_p | I84: h | J84: Φ(-h+σ_p) | K84: Φ(-h) | L84: Caplet (dec) | M84: Caplet (bps)
B85: 0.25 | C85: 0.5 | D85: =VLOOKUP(B85,OIS_Curve!$B$19:$D$58,3,FALSE()) -> 0.98973154 | E85: =VLOOKUP(C85,OIS_Curve!$B$19:$D$58,3,FALSE()) -> 0.98039216 | F85: =Par_Rates!$E$9 -> 0.035900471 | G85: =1/(1+F85*0.25) -> 0.99110472 | H85: =IF(B85=0,0,(Parameters!$C$5/Parameters!$C$4)*(1-EXP(-Parameters!$C$4*0.25))*SQRT((1-EXP(-2*Parameters!$C$4*B85))/(2*Parameters!$C$4))) -> 0.00097241305 | I85: =IF(H85=0,0,(1/H85)*LN(E85/(D85*G85))+H85/2) -> -0.56100095 | J85: =NORMSDIST(-I85+H85) -> 0.71293292 | K85: =NORMSDIST(-I85) -> 0.71260156 | L85: =IF(H85=0,0,(1+F85*0.25)*(G85*D85*J85-E85*K85)) -> 0.00071293663 | M85: =L85*10000 -> 7.1293663
B86: 0.5 | C86: 0.75 | D86: =VLOOKUP(B86,OIS_Curve!$B$19:$D$58,3,FALSE()) -> 0.98039216 | E86: =VLOOKUP(C86,OIS_Curve!$B$19:$D$58,3,FALSE()) -> 0.97157395 | F86: =Par_Rates!$E$9 -> 0.035900471 | G86: =1/(1+F86*0.25) -> 0.99110472 | H86: =IF(B86=0,0,(Parameters!$C$5/Parameters!$C$4)*(1-EXP(-Parameters!$C$4*0.25))*SQRT((1-EXP(-2*Parameters!$C$4*B86))/(2*Parameters!$C$4))) -> 0.0013481001 | I86: =IF(H86=0,0,(1/H86)*LN(E86/(D86*G86))+H86/2) -> -0.073639176 | J86: =NORMSDIST(-I86+H86) -> 0.52988758 | K86: =NORMSDIST(-I86) -> 0.52935125 | L86: =IF(H86=0,0,(1+F86*0.25)*(G86*D86*J86-E86*K86)) -> 0.00057780369 | M86: =L86*10000 -> 5.7780369
B87: 0.75 | C87: 1 | D87: =VLOOKUP(B87,OIS_Curve!$B$19:$D$58,3,FALSE()) -> 0.97157395 | E87: =VLOOKUP(C87,OIS_Curve!$B$19:$D$58,3,FALSE()) -> 0.96339114 | F87: =Par_Rates!$E$9 -> 0.035900471 | G87: =1/(1+F87*0.25) -> 0.99110472 | H87: =IF(B87=0,0,(Parameters!$C$5/Parameters!$C$4)*(1-EXP(-Parameters!$C$4*0.25))*SQRT((1-EXP(-2*Parameters!$C$4*B87))/(2*Parameters!$C$4))) -> 0.0016189875 | I87: =IF(H87=0,0,(1/H87)*LN(E87/(D87*G87))+H87/2) -> 0.29555284 | J87: =NORMSDIST(-I87+H87) -> 0.38440422 | K87: =NORMSDIST(-I87) -> 0.3837858 | L87: =IF(H87=0,0,(1+F87*0.25)*(G87*D87*J87-E87*K87)) -> 0.0004228748 | M87: =L87*10000 -> 4.228748
B88: 1 | C88: 1.25 | D88: =VLOOKUP(B88,OIS_Curve!$B$19:$D$58,3,FALSE()) -> 0.96339114 | E88: =VLOOKUP(C88,OIS_Curve!$B$19:$D$58,3,FALSE()) -> 0.95474312 | F88: =Par_Rates!$E$9 -> 0.035900471 | G88: =1/(1+F88*0.25) -> 0.99110472 | H88: =IF(B88=0,0,(Parameters!$C$5/Parameters!$C$4)*(1-EXP(-Parameters!$C$4*0.25))*SQRT((1-EXP(-2*Parameters!$C$4*B88))/(2*Parameters!$C$4))) -> 0.0018336131 | I88: =IF(H88=0,0,(1/H88)*LN(E88/(D88*G88))+H88/2) -> -0.043853301 | J88: =NORMSDIST(-I88+H88) -> 0.5182201 | K88: =NORMSDIST(-I88) -> 0.51748933 | L88: =IF(H88=0,0,(1+F88*0.25)*(G88*D88*J88-E88*K88)) -> 0.00074494455 | M88: =L88*10000 -> 7.4494455
B89: 1.25 | C89: 1.5 | D89: =VLOOKUP(B89,OIS_Curve!$B$19:$D$58,3,FALSE()) -> 0.95474312 | E89: =VLOOKUP(C89,OIS_Curve!$B$19:$D$58,3,FALSE()) -> 0.94628885 | F89: =Par_Rates!$E$9 -> 0.035900471 | G89: =1/(1+F89*0.25) -> 0.99110472 | H89: =IF(B89=0,0,(Parameters!$C$5/Parameters!$C$4)*(1-EXP(-Parameters!$C$4*0.25))*SQRT((1-EXP(-2*Parameters!$C$4*B89))/(2*Parameters!$C$4))) -> 0.0020112979 | I89: =IF(H89=0,0,(1/H89)*LN(E89/(D89*G89))+H89/2) -> 0.02120091 | J89: =NORMSDIST(-I89+H89) -> 0.49234492 | K89: =NORMSDIST(-I89) -> 0.49154269 | L89: =IF(H89=0,0,(1+F89*0.25)*(G89*D89*J89-E89*K89)) -> 0.00074685906 | M89: =L89*10000 -> 7.4685906
B90: 1.5 | C90: 1.75 | D90: =VLOOKUP(B90,OIS_Curve!$B$19:$D$58,3,FALSE()) -> 0.94628885 | E90: =VLOOKUP(C90,OIS_Curve!$B$19:$D$58,3,FALSE()) -> 0.93802454 | F90: =Par_Rates!$E$9 -> 0.035900471 | G90: =1/(1+F90*0.25) -> 0.99110472 | H90: =IF(B90=0,0,(Parameters!$C$5/Parameters!$C$4)*(1-EXP(-Parameters!$C$4*0.25))*SQRT((1-EXP(-2*Parameters!$C$4*B90))/(2*Parameters!$C$4))) -> 0.0021622167 | I90: =IF(H90=0,0,(1/H90)*LN(E90/(D90*G90))+H90/2) -> 0.0766186 | J90: =NORMSDIST(-I90+H90) -> 0.47032362 | K90: =NORMSDIST(-I90) -> 0.46946348 | L90: =IF(H90=0,0,(1+F90*0.25)*(G90*D90*J90-E90*K90)) -> 0.00074137856 | M90: =L90*10000 -> 7.4137856
B91: 1.75 | C91: 2 | D91: =VLOOKUP(B91,OIS_Curve!$B$19:$D$58,3,FALSE()) -> 0.93802454 | E91: =VLOOKUP(C91,OIS_Curve!$B$19:$D$58,3,FALSE()) -> 0.92994651 | F91: =Par_Rates!$E$9 -> 0.035900471 | G91: =1/(1+F91*0.25) -> 0.99110472 | H91: =IF(B91=0,0,(Parameters!$C$5/Parameters!$C$4)*(1-EXP(-Parameters!$C$4*0.25))*SQRT((1-EXP(-2*Parameters!$C$4*B91))/(2*Parameters!$C$4))) -> 0.0022925715 | I91: =IF(H91=0,0,(1/H91)*LN(E91/(D91*G91))+H91/2) -> 0.12591368 | J91: =NORMSDIST(-I91+H91) -> 0.45080764 | K91: =NORMSDIST(-I91) -> 0.44990013 | L91: =IF(H91=0,0,(1+F91*0.25)*(G91*D91*J91-E91*K91)) -> 0.00073053853 | M91: =L91*10000 -> 7.3053853
B92: 2 | C92: 2.25 | D92: =VLOOKUP(B92,OIS_Curve!$B$19:$D$58,3,FALSE()) -> 0.92994651 | E92: =VLOOKUP(C92,OIS_Curve!$B$19:$D$58,3,FALSE()) -> 0.92179827 | F92: =Par_Rates!$E$9 -> 0.035900471 | G92: =1/(1+F92*0.25) -> 0.99110472 | H92: =IF(B92=0,0,(Parameters!$C$5/Parameters!$C$4)*(1-EXP(-Parameters!$C$4*0.25))*SQRT((1-EXP(-2*Parameters!$C$4*B92))/(2*Parameters!$C$4))) -> 0.0024065047 | I92: =IF(H92=0,0,(1/H92)*LN(E92/(D92*G92))+H92/2) -> 0.057057593 | J92: =NORMSDIST(-I92+H92) -> 0.47820822 | K92: =NORMSDIST(-I92) -> 0.47724966 | L92: =IF(H92=0,0,(1+F92*0.25)*(G92*D92*J92-E92*K92)) -> 0.00083175034 | M92: =L92*10000 -> 8.3175034
B93: 2.25 | C93: 2.5 | D93: =VLOOKUP(B93,OIS_Curve!$B$19:$D$58,3,FALSE()) -> 0.92179827 | E93: =VLOOKUP(C93,OIS_Curve!$B$19:$D$58,3,FALSE()) -> 0.91377784 | F93: =Par_Rates!$E$9 -> 0.035900471 | G93: =1/(1+F93*0.25) -> 0.99110472 | H93: =IF(B93=0,0,(Parameters!$C$5/Parameters!$C$4)*(1-EXP(-Parameters!$C$4*0.25))*SQRT((1-EXP(-2*Parameters!$C$4*B93))/(2*Parameters!$C$4))) -> 0.0025069625 | I93: =IF(H93=0,0,(1/H93)*LN(E93/(D93*G93))+H93/2) -> 0.079499695 | J93: =NORMSDIST(-I93+H93) -> 0.46931466 | K93: =NORMSDIST(-I93) -> 0.46831759 | L93: =IF(H93=0,0,(1+F93*0.25)*(G93*D93*J93-E93*K93)) -> 0.00083441342 | M93: =L93*10000 -> 8.3441342
B94: 2.5 | C94: 2.75 | D94: =VLOOKUP(B94,OIS_Curve!$B$19:$D$58,3,FALSE()) -> 0.91377784 | E94: =VLOOKUP(C94,OIS_Curve!$B$19:$D$58,3,FALSE()) -> 0.90588313 | F94: =Par_Rates!$E$9 -> 0.035900471 | G94: =1/(1+F94*0.25) -> 0.99110472 | H94: =IF(B94=0,0,(Parameters!$C$5/Parameters!$C$4)*(1-EXP(-Parameters!$C$4*0.25))*SQRT((1-EXP(-2*Parameters!$C$4*B94))/(2*Parameters!$C$4))) -> 0.0025961381 | I94: =IF(H94=0,0,(1/H94)*LN(E94/(D94*G94))+H94/2) -> 0.10064059 | J94: =NORMSDIST(-I94+H94) -> 0.4609485 | K94: =NORMSDIST(-I94) -> 0.45991789 | L94: =IF(H94=0,0,(1+F94*0.25)*(G94*D94*J94-E94*K94)) -> 0.00083334674 | M94: =L94*10000 -> 8.3334674
B95: 2.75 | C95: 3 | D95: =VLOOKUP(B95,OIS_Curve!$B$19:$D$58,3,FALSE()) -> 0.90588313 | E95: =VLOOKUP(C95,OIS_Curve!$B$19:$D$58,3,FALSE()) -> 0.89811208 | F95: =Par_Rates!$E$9 -> 0.035900471 | G95: =1/(1+F95*0.25) -> 0.99110472 | H95: =IF(B95=0,0,(Parameters!$C$5/Parameters!$C$4)*(1-EXP(-Parameters!$C$4*0.25))*SQRT((1-EXP(-2*Parameters!$C$4*B95))/(2*Parameters!$C$4))) -> 0.002675722 | I95: =IF(H95=0,0,(1/H95)*LN(E95/(D95*G95))+H95/2) -> 0.12080225 | J95: =NORMSDIST(-I95+H95) -> 0.4529837 | K95: =NORMSDIST(-I95) -> 0.45192383 | L95: =IF(H95=0,0,(1+F95*0.25)*(G95*D95*J95-E95*K95)) -> 0.0008292328 | M95: =L95*10000 -> 8.292328
B96: 3 | C96: 3.25 | D96: =VLOOKUP(B96,OIS_Curve!$B$19:$D$58,3,FALSE()) -> 0.89811208 | E96: =VLOOKUP(C96,OIS_Curve!$B$19:$D$58,3,FALSE()) -> 0.89004033 | F96: =Par_Rates!$E$9 -> 0.035900471 | G96: =1/(1+F96*0.25) -> 0.99110472 | H96: =IF(B96=0,0,(Parameters!$C$5/Parameters!$C$4)*(1-EXP(-Parameters!$C$4*0.25))*SQRT((1-EXP(-2*Parameters!$C$4*B96))/(2*Parameters!$C$4))) -> 0.0027470527 | I96: =IF(H96=0,0,(1/H96)*LN(E96/(D96*G96))+H96/2) -> -0.032489406 | J96: =NORMSDIST(-I96+H96) -> 0.5140544 | K96: =NORMSDIST(-I96) -> 0.51295912 | L96: =IF(H96=0,0,(1+F96*0.25)*(G96*D96*J96-E96*K96)) -> 0.0010265438 | M96: =L96*10000 -> 10.265438
... B123: 9.75 | C123: 10 | D123: =VLOOKUP(B123,OIS_Curve!$B$19:$D$58,3,FALSE()) -> 0.71141551 | E123: =VLOOKUP(C123,OIS_Curve!$B$19:$D$58,3,FALSE()) -> 0.7062794 | F123: =Par_Rates!$E$9 -> 0.035900471 | G123: =1/(1+F123*0.25) -> 0.99110472 | H123: =IF(B123=0,0,(Parameters!$C$5/Parameters!$C$4)*(1-EXP(-Parameters!$C$4*0.25))*SQRT((1-EXP(-2*Parameters!$C$4*B123))/(2*Parameters!$C$4))) -> 0.0034068003 | I123: =IF(H123=0,0,(1/H123)*LN(E123/(D123*G123))+H123/2) -> 0.49757478 | J123: =NORMSDIST(-I123+H123) -> 0.31059377 | K123: =NORMSDIST(-I123) -> 0.30939189 | L123: =IF(H123=0,0,(1+F123*0.25)*(G123*D123*J123-E123*K123)) -> 0.00048289169 | M123: =L123*10000 -> 4.8289169
B124: Cap 10Y Total (Model) | L124: =SUM(L85:L123) -> 0.033364325 | M124: =SUM(M85:M123) -> 333.64325

Sheet TRY_Caplets
B1: PRACTICE: HW Caplet Pricing · Yellow cells = YOUR TURN · Check col shows OK/CHECK
B2: Caplet = (1+Kδ)·[K̃·P(0,S)·Φ(-h+σ_p) - P(0,S+δ)·Φ(-h)] | σ_p=(σ/a)·(1-e^{-aδ})·√[(1-e^{-2aS})/(2a)] | h=(1/σ_p)·ln[P(0,S+δ)/(P(0,S)·K̃)]+σ_p/2 | K̃=1/(1+Kδ)
B3: 2Y Cap · K = 3.961% · 7 caplets (T_start = 0.25 to 1.75) | O3: Check vs Solution
B4: T_start | C4: T_end | D4: P(0,S) | E4: P(0,S+δ) | F4: K | G4: K̃ | H4: σ_p | I4: h | J4: Φ(-h+σ_p) | K4: Φ(-h) | L4: Caplet (dec) | M4: Caplet (bps)
B5: 0.25 | C5: 0.5 | D5: =VLOOKUP(B5,OIS_Curve!$B$19:$D$58,3,FALSE()) -> 0.98973154 | E5: =VLOOKUP(C5,OIS_Curve!$B$19:$D$58,3,FALSE()) -> 0.98039216 | F5: =Par_Rates!$E$5 -> 0.039610444 | G5: =1/(1+F5*0.25) -> 0.99019449 | H5: =(Parameters!$C$5/Parameters!$C$4)*(1-EXP(-Parameters!$C$4*0.25))*SQRT((1-EXP(-2*Parameters!$C$4*B5))/(2*Parameters!$C$4)) -> 0.00097241305 | I5: =(1/H5)*LN(E5/(D5*G5))+H5/2 -> 0.38388635 | J5: =NORMSDIST(-I5+H5) -> 0.35089179 | K5: =NORMSDIST(-I5) -> 0.35053134 | L5: =(1+F5*0.25)*(G5*D5*J5-E5*K5) -> 0.00022737711 | M5: =L5*10000 -> 2.2737711 | O5: =IF(M5="","?",IF(ABS(M5-HW_Caplets!M5)<0.0000001,"OK","CHECK")) -> OK
B6: 0.5 | C6: 0.75 | D6: =VLOOKUP(B6,OIS_Curve!$B$19:$D$58,3,FALSE()) -> 0.98039216 | E6: =VLOOKUP(C6,OIS_Curve!$B$19:$D$58,3,FALSE()) -> 0.97157395 | F6: =Par_Rates!$E$5 -> 0.039610444 | G6: =1/(1+F6*0.25) -> 0.99019449 | H6: =(Parameters!$C$5/Parameters!$C$4)*(1-EXP(-Parameters!$C$4*0.25))*SQRT((1-EXP(-2*Parameters!$C$4*B6))/(2*Parameters!$C$4)) -> 0.0013481001 | I6: =(1/H6)*LN(E6/(D6*G6))+H6/2 -> 0.60792795 | J6: =NORMSDIST(-I6+H6) -> 0.27206489 | K6: =NORMSDIST(-I6) -> 0.27161763 | L6: =(1+F6*0.25)*(G6*D6*J6-E6*K6) -> 0.00022040156 | M6: =L6*10000 -> 2.2040156 | O6: =IF(M6="","?",IF(ABS(M6-HW_Caplets!M6)<0.0000001,"OK","CHECK")) -> OK
B7: 0.75 | C7: 1 | D7: =VLOOKUP(B7,OIS_Curve!$B$19:$D$58,3,FALSE()) -> 0.97157395 | E7: =VLOOKUP(C7,OIS_Curve!$B$19:$D$58,3,FALSE()) -> 0.96339114 | F7: =Par_Rates!$E$5 -> 0.039610444 | G7: =1/(1+F7*0.25) -> 0.99019449 | H7: =(Parameters!$C$5/Parameters!$C$4)*(1-EXP(-Parameters!$C$4*0.25))*SQRT((1-EXP(-2*Parameters!$C$4*B7))/(2*Parameters!$C$4)) -> 0.0016189875 | I7: =(1/H7)*LN(E7/(D7*G7))+H7/2 -> 0.86308085 | J7: =NORMSDIST(-I7+H7) -> 0.19449186 | K7: =NORMSDIST(-I7) -> 0.19404651 | L7: =(1+F7*0.25)*(G7*D7*J7-E7*K7) -> 0.00016931734 | M7: =L7*10000 -> 1.6931734 | O7: =IF(M7="","?",IF(ABS(M7-HW_Caplets!M7)<0.0000001,"OK","CHECK")) -> OK
B8: 1 | C8: 1.25 | D8: =VLOOKUP(B8,OIS_Curve!$B$19:$D$58,3,FALSE()) -> 0.96339114 | E8: =VLOOKUP(C8,OIS_Curve!$B$19:$D$58,3,FALSE()) -> 0.95474312 | F8: =Par_Rates!$E$5 -> 0.039610444 | G8: =1/(1+F8*0.25) -> 0.99019449 | H8: =(Parameters!$C$5/Parameters!$C$4)*(1-EXP(-Parameters!$C$4*0.25))*SQRT((1-EXP(-2*Parameters!$C$4*B8))/(2*Parameters!$C$4)) -> 0.0018336131 | I8: =(1/H8)*LN(E8/(D8*G8))+H8/2 -> 0.45724519 | J8: =NORMSDIST(-I8+H8) -> 0.32440658 | K8: =NORMSDIST(-I8) -> 0.32374741 | L8: =(1+F8*0.25)*(G8*D8*J8-E8*K8) -> 0.00037396084 | M8: =L8*10000 -> 3.7396084 | O8: =IF(M8="","?",IF(ABS(M8-HW_Caplets!M8)<0.0000001,"OK","CHECK")) -> OK
B9: 1.25 | C9: 1.5 | D9: =VLOOKUP(B9,OIS_Curve!$B$19:$D$58,3,FALSE()) -> 0.95474312 | E9: =VLOOKUP(C9,OIS_Curve!$B$19:$D$58,3,FALSE()) -> 0.94628885 | F9: =Par_Rates!$E$5 -> 0.039610444 | G9: =1/(1+F9*0.25) -> 0.99019449 | H9: =(Parameters!$C$5/Parameters!$C$4)*(1-EXP(-Parameters!$C$4*0.25))*SQRT((1-EXP(-2*Parameters!$C$4*B9))/(2*Parameters!$C$4)) -> 0.0020112979 | I9: =(1/H9)*LN(E9/(D9*G9))+H9/2 -> 0.47803068 | J9: =NORMSDIST(-I9+H9) -> 0.31703029 | K9: =NORMSDIST(-I9) -> 0.31631418 | L9: =(1+F9*0.25)*(G9*D9*J9-E9*K9) -> 0.00039380335 | M9: =L9*10000 -> 3.9380335 | O9: =IF(M9="","?",IF(ABS(M9-HW_Caplets!M9)<0.0000001,"OK","CHECK")) -> OK
B10: 1.5 | C10: 1.75 | D10: =VLOOKUP(B10,OIS_Curve!$B$19:$D$58,3,FALSE()) -> 0.94628885 | E10: =VLOOKUP(C10,OIS_Curve!$B$19:$D$58,3,FALSE()) -> 0.93802454 | F10: =Par_Rates!$E$5 -> 0.039610444 | G10: =1/(1+F10*0.25) -> 0.99019449 | H10: =(Parameters!$C$5/Parameters!$C$4)*(1-EXP(-Parameters!$C$4*0.25))*SQRT((1-EXP(-2*Parameters!$C$4*B10))/(2*Parameters!$C$4)) -> 0.0021622167 | I10: =(1/H10)*LN(E10/(D10*G10))+H10/2 -> 0.50156248 | J10: =NORMSDIST(-I10+H10) -> 0.30874872 | K10: =NORMSDIST(-I10) -> 0.30798766 | L10: =(1+F10*0.25)*(G10*D10*J10-E10*K10) -> 0.00040462284 | M10: =L10*10000 -> 4.0462284 | O10: =IF(M10="","?",IF(ABS(M10-HW_Caplets!M10)<0.0000001,"OK","CHECK")) -> OK
B11: 1.75 | C11: 2 | D11: =VLOOKUP(B11,OIS_Curve!$B$19:$D$58,3,FALSE()) -> 0.93802454 | E11: =VLOOKUP(C11,OIS_Curve!$B$19:$D$58,3,FALSE()) -> 0.92994651 | F11: =Par_Rates!$E$5 -> 0.039610444 | G11: =1/(1+F11*0.25) -> 0.99019449 | H11: =(Parameters!$C$5/Parameters!$C$4)*(1-EXP(-Parameters!$C$4*0.25))*SQRT((1-EXP(-2*Parameters!$C$4*B11))/(2*Parameters!$C$4)) -> 0.0022925715 | I11: =(1/H11)*LN(E11/(D11*G11))+H11/2 -> 0.52669539 | J11: =NORMSDIST(-I11+H11) -> 0.2999992 | K11: =NORMSDIST(-I11) -> 0.29920257 | L11: =(1+F11*0.25)*(G11*D11*J11-E11*K11) -> 0.00040889935 | M11: =L11*10000 -> 4.0889935 | O11: =IF(M11="","?",IF(ABS(M11-HW_Caplets!M11)<0.0000001,"OK","CHECK")) -> OK
B12: Cap 2Y Total (Model) | L12: =SUM(L5:L11) -> 0.0021983824 | M12: =SUM(M5:M11) -> 21.983824
B14: 3Y Cap · K = 3.670% · 11 caplets (T_start = 0.25 to 2.75)
B15: T_start | C15: T_end | D15: P(0,S) | E15: P(0,S+δ) | F15: K
B16: 0.25 | C16: 0.5 | D16: =VLOOKUP(B16,OIS_Curve!$B$19:$D$58,3,FALSE()) -> 0.98973154 | E16: =VLOOKUP(C16,OIS_Curve!$B$19:$D$58,3,FALSE()) -> 0.98039216 | F16: =Par_Rates!$E$6 -> 0.0367 | G16: =1/(1+F16*0.25) -> 0.99090842 | H16: =(Parameters!$C$5/Parameters!$C$4)*(1-EXP(-Parameters!$C$4*0.25))*SQRT((1-EXP(-2*Parameters!$C$4*B16))/(2*Parameters!$C$4)) -> 0.00097241305 | I16: =(1/H16)*LN(E16/(D16*G16))+H16/2 -> -0.35729678 | J16: =NORMSDIST(-I16+H16) -> 0.63992906 | K16: =NORMSDIST(-I16) -> 0.63956518 | L16: =(1+F16*0.25)*(G16*D16*J16-E16*K16) -> 0.00058033818 | M16: =L16*10000 -> 5.8033818 | O16: =IF(M16="","?",IF(ABS(M16-HW_Caplets!M16)<0.0000001,"OK","CHECK")) -> OK
B17: 0.5 | C17: 0.75 | D17: =VLOOKUP(B17,OIS_Curve!$B$19:$D$58,3,FALSE()) -> 0.98039216 | E17: =VLOOKUP(C17,OIS_Curve!$B$19:$D$58,3,FALSE()) -> 0.97157395 | F17: =Par_Rates!$E$6 -> 0.0367 | G17: =1/(1+F17*0.25) -> 0.99090842 | H17: =(Parameters!$C$5/Parameters!$C$4)*(1-EXP(-Parameters!$C$4*0.25))*SQRT((1-EXP(-2*Parameters!$C$4*B17))/(2*Parameters!$C$4)) -> 0.0013481001 | I17: =(1/H17)*LN(E17/(D17*G17))+H17/2 -> 0.073296939 | J17: =NORMSDIST(-I17+H17) -> 0.47132131 | K17: =NORMSDIST(-I17) -> 0.47078491 | L17: =(1+F17*0.25)*(G17*D17*J17-E17*K17) -> 0.00048069045 | M17: =L17*10000 -> 4.8069045 | O17: =IF(M17="","?",IF(ABS(M17-HW_Caplets!M17)<0.0000001,"OK","CHECK")) -> OK
B18: 0.75 | C18: 1 | D18: =VLOOKUP(B18,OIS_Curve!$B$19:$D$58,3,FALSE()) -> 0.97157395 | E18: =VLOOKUP(C18,OIS_Curve!$B$19:$D$58,3,FALSE()) -> 0.96339114 | F18: =Par_Rates!$E$6 -> 0.0367 | G18: =1/(1+F18*0.25) -> 0.99090842 | H18: =(Parameters!$C$5/Parameters!$C$4)*(1-EXP(-Parameters!$C$4*0.25))*SQRT((1-EXP(-2*Parameters!$C$4*B18))/(2*Parameters!$C$4)) -> 0.0016189875 | I18: =(1/H18)*LN(E18/(D18*G18))+H18/2 -> 0.41790376 | J18: =NORMSDIST(-I18+H18) -> 0.33860082 | K18: =NORMSDIST(-I18) -> 0.33800874 | L18: =(1+F18*0.25)*(G18*D18*J18-E18*K18) -> 0.0003534109 | M18: =L18*10000 -> 3.534109 | O18: =IF(M18="","?",IF(ABS(M18-HW_Caplets!M18)<0.0000001,"OK","CHECK")) -> OK
B19: 1 | C19: 1.25 | D19: =VLOOKUP(B19,OIS_Curve!$B$19:$D$58,3,FALSE()) -> 0.96339114 | E19: =VLOOKUP(C19,OIS_Curve!$B$19:$D$58,3,FALSE()) -> 0.95474312 | F19: =Par_Rates!$E$6 -> 0.0367 | G19: =1/(1+F19*0.25) -> 0.99090842 | H19: =(Parameters!$C$5/Parameters!$C$4)*(1-EXP(-Parameters!$C$4*0.25))*SQRT((1-EXP(-2*Parameters!$C$4*B19))/(2*Parameters!$C$4)) -> 0.0018336131 | I19: =(1/H19)*LN(E19/(D19*G19))+H19/2 -> 0.06417636 | J19: =NORMSDIST(-I19+H19) -> 0.47514494 | K19: =NORMSDIST(-I19) -> 0.4744149 | L19: =(1+F19*0.25)*(G19*D19*J19-E19*K19) -> 0.00065029983 | M19: =L19*10000 -> 6.5029983 | O19: =IF(M19="","?",IF(ABS(M19-HW_Caplets!M19)<0.0000001,"OK","CHECK")) -> OK
B20: 1.25 | C20: 1.5 | D20: =VLOOKUP(B20,OIS_Curve!$B$19:$D$58,3,FALSE()) -> 0.95474312 | E20: =VLOOKUP(C20,OIS_Curve!$B$19:$D$58,3,FALSE()) -> 0.94628885 | F20: =Par_Rates!$E$6 -> 0.0367 | G20: =1/(1+F20*0.25) -> 0.99090842 | H20: =(Parameters!$C$5/Parameters!$C$4)*(1-EXP(-Parameters!$C$4*0.25))*SQRT((1-EXP(-2*Parameters!$C$4*B20))/(2*Parameters!$C$4)) -> 0.0020112979 | I20: =(1/H20)*LN(E20/(D20*G20))+H20/2 -> 0.11968687 | J20: =NORMSDIST(-I20+H20) -> 0.45316236 | K20: =NORMSDIST(-I20) -> 0.4523656 | L20: =(1+F20*0.25)*(G20*D20*J20-E20*K20) -> 0.00065759508 | M20: =L20*10000 -> 6.5759508 | O20: =IF(M20="","?",IF(ABS(M20-HW_Caplets!M20)<0.0000001,"OK","CHECK")) -> OK
B21: 1.5 | C21: 1.75 | D21: =VLOOKUP(B21,OIS_Curve!$B$19:$D$58,3,FALSE()) -> 0.94628885 | E21: =VLOOKUP(C21,OIS_Curve!$B$19:$D$58,3,FALSE()) -> 0.93802454 | F21: =Par_Rates!$E$6 -> 0.0367 | G21: =1/(1+F21*0.25) -> 0.99090842 | H21: =(Parameters!$C$5/Parameters!$C$4)*(1-EXP(-Parameters!$C$4*0.25))*SQRT((1-EXP(-2*Parameters!$C$4*B21))/(2*Parameters!$C$4)) -> 0.0021622167 | I21: =(1/H21)*LN(E21/(D21*G21))+H21/2 -> 0.16823042 | J21: =NORMSDIST(-I21+H21) -> 0.43405164 | K21: =NORMSDIST(-I21) -> 0.43320101 | L21: =(1+F21*0.25)*(G21*D21*J21-E21*K21) -> 0.00065676274 | M21: =L21*10000 -> 6.5676274 | O21: =IF(M21="","?",IF(ABS(M21-HW_Caplets!M21)<0.0000001,"OK","CHECK")) -> OK
B22: 1.75 | C22: 2 | D22: =VLOOKUP(B22,OIS_Curve!$B$19:$D$58,3,FALSE()) -> 0.93802454 | E22: =VLOOKUP(C22,OIS_Curve!$B$19:$D$58,3,FALSE()) -> 0.92994651 | F22: =Par_Rates!$E$6 -> 0.0367 | G22: =1/(1+F22*0.25) -> 0.99090842 | H22: =(Parameters!$C$5/Parameters!$C$4)*(1-EXP(-Parameters!$C$4*0.25))*SQRT((1-EXP(-2*Parameters!$C$4*B22))/(2*Parameters!$C$4)) -> 0.0022925715 | I22: =(1/H22)*LN(E22/(D22*G22))+H22/2 -> 0.21231648 | J22: =NORMSDIST(-I22+H22) -> 0.41682451 | K22: =NORMSDIST(-I22) -> 0.41593007 | L22: =(1+F22*0.25)*(G22*D22*J22-E22*K22) -> 0.00065007615 | M22: =L22*10000 -> 6.5007615 | O22: =IF(M22="","?",IF(ABS(M22-HW_Caplets!M22)<0.0000001,"OK","CHECK")) -> OK
B23: 2 | C23: 2.25 | D23: =VLOOKUP(B23,OIS_Curve!$B$19:$D$58,3,FALSE()) -> 0.92994651 | E23: =VLOOKUP(C23,OIS_Curve!$B$19:$D$58,3,FALSE()) -> 0.92179827 | F23: =Par_Rates!$E$6 -> 0.0367 | G23: =1/(1+F23*0.25) -> 0.99090842 | H23: =(Parameters!$C$5/Parameters!$C$4)*(1-EXP(-Parameters!$C$4*0.25))*SQRT((1-EXP(-2*Parameters!$C$4*B23))/(2*Parameters!$C$4)) -> 0.0024065047 | I23: =(1/H23)*LN(E23/(D23*G23))+H23/2 -> 0.13936975 | J23: =NORMSDIST(-I23+H23) -> 0.44552992 | K23: =NORMSDIST(-I23) -> 0.44457899 | L23: =(1+F23*0.25)*(G23*D23*J23-E23*K23) -> 0.00074683052 | M23: =L23*10000 -> 7.4683052 | O23: =IF(M23="","?",IF(ABS(M23-HW_Caplets!M23)<0.0000001,"OK","CHECK")) -> OK
B24: 2.25 | C24: 2.5 | D24: =VLOOKUP(B24,OIS_Curve!$B$19:$D$58,3,FALSE()) -> 0.92179827 | E24: =VLOOKUP(C24,OIS_Curve!$B$19:$D$58,3,FALSE()) -> 0.91377784 | F24: =Par_Rates!$E$6 -> 0.0367 | G24: =1/(1+F24*0.25) -> 0.99090842 | H24: =(Parameters!$C$5/Parameters!$C$4)*(1-EXP(-Parameters!$C$4*0.25))*SQRT((1-EXP(-2*Parameters!$C$4*B24))/(2*Parameters!$C$4)) -> 0.0025069625 | I24: =(1/H24)*LN(E24/(D24*G24))+H24/2 -> 0.15851348 | J24: =NORMSDIST(-I24+H24) -> 0.43801394 | K24: =NORMSDIST(-I24) -> 0.4370261 | L24: =(1+F24*0.25)*(G24*D24*J24-E24*K24) -> 0.00075173841 | M24: =L24*10000 -> 7.5173841 | O24: =IF(M24="","?",IF(ABS(M24-HW_Caplets!M24)<0.0000001,"OK","CHECK")) -> OK
B25: 2.5 | C25: 2.75 | D25: =VLOOKUP(B25,OIS_Curve!$B$19:$D$58,3,FALSE()) -> 0.91377784 | E25: =VLOOKUP(C25,OIS_Curve!$B$19:$D$58,3,FALSE()) -> 0.90588313 | F25: =Par_Rates!$E$6 -> 0.0367 | G25: =1/(1+F25*0.25) -> 0.99090842 | H25: =(Parameters!$C$5/Parameters!$C$4)*(1-EXP(-Parameters!$C$4*0.25))*SQRT((1-EXP(-2*Parameters!$C$4*B25))/(2*Parameters!$C$4)) -> 0.0025961381 | I25: =(1/H25)*LN(E25/(D25*G25))+H25/2 -> 0.17694031 | J25: =NORMSDIST(-I25+H25) -> 0.43079749 | K25: =NORMSDIST(-I25) -> 0.42977764 | L25: =(1+F25*0.25)*(G25*D25*J25-E25*K25) -> 0.00075280309 | M25: =L25*10000 -> 7.5280309 | O25: =IF(M25="","?",IF(ABS(M25-HW_Caplets!M25)<0.0000001,"OK","CHECK")) -> OK
B26: 2.75 | C26: 3 | D26: =VLOOKUP(B26,OIS_Curve!$B$19:$D$58,3,FALSE()) -> 0.90588313 | E26: =VLOOKUP(C26,OIS_Curve!$B$19:$D$58,3,FALSE()) -> 0.89811208 | F26: =Par_Rates!$E$6 -> 0.0367 | G26: =1/(1+F26*0.25) -> 0.99090842 | H26: =(Parameters!$C$5/Parameters!$C$4)*(1-EXP(-Parameters!$C$4*0.25))*SQRT((1-EXP(-2*Parameters!$C$4*B26))/(2*Parameters!$C$4)) -> 0.002675722 | I26: =(1/H26)*LN(E26/(D26*G26))+H26/2 -> 0.19483259 | J26: =NORMSDIST(-I26+H26) -> 0.42380967 | K26: =NORMSDIST(-I26) -> 0.42276201 | L26: =(1+F26*0.25)*(G26*D26*J26-E26*K26) -> 0.00075072765 | M26: =L26*10000 -> 7.5072765 | O26: =IF(M26="","?",IF(ABS(M26-HW_Caplets!M26)<0.0000001,"OK","CHECK")) -> OK
B27: Cap 3Y Total (Model) | L27: =SUM(L16:L26) -> 0.007031273 | M27: =SUM(M16:M26) -> 70.31273
B29: 5Y Cap · K = 3.640% · 19 caplets (T_start = 0.25 to 4.75)
B30: T_start | C30: T_end | D30: P(0,S) | E30: P(0,S+δ) | F30: K
B31: 0.25 | C31: 0.5 | D31: =VLOOKUP(B31,OIS_Curve!$B$19:$D$58,3,FALSE()) -> 0.98973154 | E31: =VLOOKUP(C31,OIS_Curve!$B$19:$D$58,3,FALSE()) -> 0.98039216 | F31: =Par_Rates!$E$7 -> 0.036400127 | G31: =1/(1+F31*0.25) -> 0.99098203 | H31: =(Parameters!$C$5/Parameters!$C$4)*(1-EXP(-Parameters!$C$4*0.25))*SQRT((1-EXP(-2*Parameters!$C$4*B31))/(2*Parameters!$C$4)) -> 0.00097241305 | I31: =(1/H31)*LN(E31/(D31*G31))+H31/2 -> -0.43369367 | J31: =NORMSDIST(-I31+H31) -> 0.66809759 | K31: =NORMSDIST(-I31) -> 0.66774455 | L31: =(1+F31*0.25)*(G31*D31*J31-E31*K31) -> 0.00062838583 | M31: =L31*10000 -> 6.2838583 | O31: =IF(M31="","?",IF(ABS(M31-HW_Caplets!M31)<0.0000001,"OK","CHECK")) -> OK
B32: 0.5 | C32: 0.75 | D32: =VLOOKUP(B32,OIS_Curve!$B$19:$D$58,3,FALSE()) -> 0.98039216 | E32: =VLOOKUP(C32,OIS_Curve!$B$19:$D$58,3,FALSE()) -> 0.97157395 | F32: =Par_Rates!$E$7 -> 0.036400127 | G32: =1/(1+F32*0.25) -> 0.99098203 | H32: =(Parameters!$C$5/Parameters!$C$4)*(1-EXP(-Parameters!$C$4*0.25))*SQRT((1-EXP(-2*Parameters!$C$4*B32))/(2*Parameters!$C$4)) -> 0.0013481001 | I32: =(1/H32)*LN(E32/(D32*G32))+H32/2 -> 0.018190254 | J32: =NORMSDIST(-I32+H32) -> 0.49328127 | K32: =NORMSDIST(-I32) -> 0.49274354 | L32: =(1+F32*0.25)*(G32*D32*J32-E32*K32) -> 0.00051578041 | M32: =L32*10000 -> 5.1578041 | O32: =IF(M32="","?",IF(ABS(M32-HW_Caplets!M32)<0.0000001,"OK","CHECK")) -> OK
B33: 0.75 | C33: 1 | D33: =VLOOKUP(B33,OIS_Curve!$B$19:$D$58,3,FALSE()) -> 0.97157395 | E33: =VLOOKUP(C33,OIS_Curve!$B$19:$D$58,3,FALSE()) -> 0.96339114 | F33: =Par_Rates!$E$7 -> 0.036400127 | G33: =1/(1+F33*0.25) -> 0.99098203 | H33: =(Parameters!$C$5/Parameters!$C$4)*(1-EXP(-Parameters!$C$4*0.25))*SQRT((1-EXP(-2*Parameters!$C$4*B33))/(2*Parameters!$C$4)) -> 0.0016189875 | I33: =(1/H33)*LN(E33/(D33*G33))+H33/2 -> 0.37201747 | J33: =NORMSDIST(-I33+H33) -> 0.3555428 | K33: =NORMSDIST(-I33) -> 0.35493992 | L33: =(1+F33*0.25)*(G33*D33*J33-E33*K33) -> 0.00037843268 | M33: =L33*10000 -> 3.7843268 | O33: =IF(M33="","?",IF(ABS(M33-HW_Caplets!M33)<0.0000001,"OK","CHECK")) -> OK
B34: 1 | C34: 1.25 | D34: =VLOOKUP(B34,OIS_Curve!$B$19:$D$58,3,FALSE()) -> 0.96339114 | E34: =VLOOKUP(C34,OIS_Curve!$B$19:$D$58,3,FALSE()) -> 0.95474312 | F34: =Par_Rates!$E$7 -> 0.036400127 | G34: =1/(1+F34*0.25) -> 0.99098203 | H34: =(Parameters!$C$5/Parameters!$C$4)*(1-EXP(-Parameters!$C$4*0.25))*SQRT((1-EXP(-2*Parameters!$C$4*B34))/(2*Parameters!$C$4)) -> 0.0018336131 | I34: =(1/H34)*LN(E34/(D34*G34))+H34/2 -> 0.02366109 | J34: =NORMSDIST(-I34+H34) -> 0.49129279 | K34: =NORMSDIST(-I34) -> 0.49056147 | L34: =(1+F34*0.25)*(G34*D34*J34-E34*K34) -> 0.0006848339 | M34: =L34*10000 -> 6.848339 | O34: =IF(M34="","?",IF(ABS(M34-HW_Caplets!M34)<0.0000001,"OK","CHECK")) -> OK
B35: 1.25 | C35: 1.5 | D35: =VLOOKUP(B35,OIS_Curve!$B$19:$D$58,3,FALSE()) -> 0.95474312 | E35: =VLOOKUP(C35,OIS_Curve!$B$19:$D$58,3,FALSE()) -> 0.94628885 | F35: =Par_Rates!$E$7 -> 0.036400127 | G35: =1/(1+F35*0.25) -> 0.99098203 | H35: =(Parameters!$C$5/Parameters!$C$4)*(1-EXP(-Parameters!$C$4*0.25))*SQRT((1-EXP(-2*Parameters!$C$4*B35))/(2*Parameters!$C$4)) -> 0.0020112979 | I35: =(1/H35)*LN(E35/(D35*G35))+H35/2 -> 0.082750853 | J35: =NORMSDIST(-I35+H35) -> 0.46782454 | K35: =NORMSDIST(-I35) -> 0.46702482 | L35: =(1+F35*0.25)*(G35*D35*J35-E35*K35) -> 0.00069020622 | M35: =L35*10000 -> 6.9020622 | O35: =IF(M35="","?",IF(ABS(M35-HW_Caplets!M35)<0.0000001,"OK","CHECK")) -> OK
B36: 1.5 | C36: 1.75 | D36: =VLOOKUP(B36,OIS_Curve!$B$19:$D$58,3,FALSE()) -> 0.94628885 | E36: =VLOOKUP(C36,OIS_Curve!$B$19:$D$58,3,FALSE()) -> 0.93802454 | F36: =Par_Rates!$E$7 -> 0.036400127 | G36: =1/(1+F36*0.25) -> 0.99098203 | H36: =(Parameters!$C$5/Parameters!$C$4)*(1-EXP(-Parameters!$C$4*0.25))*SQRT((1-EXP(-2*Parameters!$C$4*B36))/(2*Parameters!$C$4)) -> 0.0021622167 | I36: =(1/H36)*LN(E36/(D36*G36))+H36/2 -> 0.13387247 | J36: =NORMSDIST(-I36+H36) -> 0.44760674 | K36: =NORMSDIST(-I36) -> 0.44675171 | L36: =(1+F36*0.25)*(G36*D36*J36-E36*K36) -> 0.00068770232 | M36: =L36*10000 -> 6.8770232 | O36: =IF(M36="","?",IF(ABS(M36-HW_Caplets!M36)<0.0000001,"OK","CHECK")) -> OK
B37: 1.75 | C37: 2 | D37: =VLOOKUP(B37,OIS_Curve!$B$19:$D$58,3,FALSE()) -> 0.93802454 | E37: =VLOOKUP(C37,OIS_Curve!$B$19:$D$58,3,FALSE()) -> 0.92994651 | F37: =Par_Rates!$E$7 -> 0.036400127 | G37: =1/(1+F37*0.25) -> 0.99098203 | H37: =(Parameters!$C$5/Parameters!$C$4)*(1-EXP(-Parameters!$C$4*0.25))*SQRT((1-EXP(-2*Parameters!$C$4*B37))/(2*Parameters!$C$4)) -> 0.0022925715 | I37: =(1/H37)*LN(E37/(D37*G37))+H37/2 -> 0.17991211 | J37: =NORMSDIST(-I37+H37) -> 0.42951089 | K37: =NORMSDIST(-I37) -> 0.42861078 | L37: =(1+F37*0.25)*(G37*D37*J37-E37*K37) -> 0.00067951484 | M37: =L37*10000 -> 6.7951484 | O37: =IF(M37="","?",IF(ABS(M37-HW_Caplets!M37)<0.0000001,"OK","CHECK")) -> OK
B38: 2 | C38: 2.25 | D38: =VLOOKUP(B38,OIS_Curve!$B$19:$D$58,3,FALSE()) -> 0.92994651 | E38: =VLOOKUP(C38,OIS_Curve!$B$19:$D$58,3,FALSE()) -> 0.92179827 | F38: =Par_Rates!$E$7 -> 0.036400127 | G38: =1/(1+F38*0.25) -> 0.99098203 | H38: =(Parameters!$C$5/Parameters!$C$4)*(1-EXP(-Parameters!$C$4*0.25))*SQRT((1-EXP(-2*Parameters!$C$4*B38))/(2*Parameters!$C$4)) -> 0.0024065047 | I38: =(1/H38)*LN(E38/(D38*G38))+H38/2 -> 0.10849953 | J38: =NORMSDIST(-I38+H38) -> 0.45775427 | K38: =NORMSDIST(-I38) -> 0.45679973 | L38: =(1+F38*0.25)*(G38*D38*J38-E38*K38) -> 0.00077797537 | M38: =L38*10000 -> 7.7797537 | O38: =IF(M38="","?",IF(ABS(M38-HW_Caplets!M38)<0.0000001,"OK","CHECK")) -> OK
B39: 2.25 | C39: 2.5 | D39: =VLOOKUP(B39,OIS_Curve!$B$19:$D$58,3,FALSE()) -> 0.92179827 | E39: =VLOOKUP(C39,OIS_Curve!$B$19:$D$58,3,FALSE()) -> 0.91377784 | F39: =Par_Rates!$E$7 -> 0.036400127 | G39: =1/(1+F39*0.25) -> 0.99098203 | H39: =(Parameters!$C$5/Parameters!$C$4)*(1-EXP(-Parameters!$C$4*0.25))*SQRT((1-EXP(-2*Parameters!$C$4*B39))/(2*Parameters!$C$4)) -> 0.0025069625 | I39: =(1/H39)*LN(E39/(D39*G39))+H39/2 -> 0.12888028 | J39: =NORMSDIST(-I39+H39) -> 0.44971821 | K39: =NORMSDIST(-I39) -> 0.44872619 | L39: =(1+F39*0.25)*(G39*D39*J39-E39*K39) -> 0.00078207701 | M39: =L39*10000 -> 7.8207701 | O39: =IF(M39="","?",IF(ABS(M39-HW_Caplets!M39)<0.0000001,"OK","CHECK")) -> OK
B40: 2.5 | C40: 2.75 | D40: =VLOOKUP(B40,OIS_Curve!$B$19:$D$58,3,FALSE()) -> 0.91377784 | E40: =VLOOKUP(C40,OIS_Curve!$B$19:$D$58,3,FALSE()) -> 0.90588313 | F40: =Par_Rates!$E$7 -> 0.036400127 | G40: =1/(1+F40*0.25) -> 0.99098203 | H40: =(Parameters!$C$5/Parameters!$C$4)*(1-EXP(-Parameters!$C$4*0.25))*SQRT((1-EXP(-2*Parameters!$C$4*B40))/(2*Parameters!$C$4)) -> 0.0025961381 | I40: =(1/H40)*LN(E40/(D40*G40))+H40/2 -> 0.14832498 | J40: =NORMSDIST(-I40+H40) -> 0.44206772 | K40: =NORMSDIST(-I40) -> 0.44104315 | L40: =(1+F40*0.25)*(G40*D40*J40-E40*K40) -> 0.00078237254 | M40: =L40*10000 -> 7.8237254 | O40: =IF(M40="","?",IF(ABS(M40-HW_Caplets!M40)<0.0000001,"OK","CHECK")) -> OK
B41: 2.75 | C41: 3 | D41: =VLOOKUP(B41,OIS_Curve!$B$19:$D$58,3,FALSE()) -> 0.90588313 | E41: =VLOOKUP(C41,OIS_Curve!$B$19:$D$58,3,FALSE()) -> 0.89811208 | F41: =Par_Rates!$E$7 -> 0.036400127 | G41: =1/(1+F41*0.25) -> 0.99098203 | H41: =(Parameters!$C$5/Parameters!$C$4)*(1-EXP(-Parameters!$C$4*0.25))*SQRT((1-EXP(-2*Parameters!$C$4*B41))/(2*Parameters!$C$4)) -> 0.002675722 | I41: =(1/H41)*LN(E41/(D41*G41))+H41/2 -> 0.16706837 | J41: =NORMSDIST(-I41+H41) -> 0.43471103 | K41: =NORMSDIST(-I41) -> 0.43365813 | L41: =(1+F41*0.25)*(G41*D41*J41-E41*K41) -> 0.00077955864 | M41: =L41*10000 -> 7.7955864 | O41: =IF(M41="","?",IF(ABS(M41-HW_Caplets!M41)<0.0000001,"OK","CHECK")) -> OK
B42: 3 | C42: 3.25 | D42: =VLOOKUP(B42,OIS_Curve!$B$19:$D$58,3,FALSE()) -> 0.89811208 | E42: =VLOOKUP(C42,OIS_Curve!$B$19:$D$58,3,FALSE()) -> 0.89004033 | F42: =Par_Rates!$E$7 -> 0.036400127 | G42: =1/(1+F42*0.25) -> 0.99098203 | H42: =(Parameters!$C$5/Parameters!$C$4)*(1-EXP(-Parameters!$C$4*0.25))*SQRT((1-EXP(-2*Parameters!$C$4*B42))/(2*Parameters!$C$4)) -> 0.0027470527 | I42: =(1/H42)*LN(E42/(D42*G42))+H42/2 -> 0.012575352 | J42: =NORMSDIST(-I42+H42) -> 0.49607914 | K42: =NORMSDIST(-I42) -> 0.49498329 | L42: =(1+F42*0.25)*(G42*D42*J42-E42*K42) -> 0.00097051294 | M42: =L42*10000 -> 9.7051294 | O42: =IF(M42="","?",IF(ABS(M42-HW_Caplets!M42)<0.0000001,"OK","CHECK")) -> OK
... B49: 4.75 | C49: 5 | D49: =VLOOKUP(B49,OIS_Curve!$B$19:$D$58,3,FALSE()) -> 0.84498204 | E49: =VLOOKUP(C49,OIS_Curve!$B$19:$D$58,3,FALSE()) -> 0.83815119 | F49: =Par_Rates!$E$7 -> 0.036400127 | G49: =1/(1+F49*0.25) -> 0.99098203 | H49: =(Parameters!$C$5/Parameters!$C$4)*(1-EXP(-Parameters!$C$4*0.25))*SQRT((1-EXP(-2*Parameters!$C$4*B49))/(2*Parameters!$C$4)) -> 0.0030868291 | I49: =(1/H49)*LN(E49/(D49*G49))+H49/2 -> 0.30671355 | J49: =NORMSDIST(-I49+H49) -> 0.38070614 | K49: =NORMSDIST(-I49) -> 0.37953071 | L49: =(1+F49*0.25)*(G49*D49*J49-E49*K49) -> 0.00069098309 | M49: =L49*10000 -> 6.9098309 | O49: =IF(M49="","?",IF(ABS(M49-HW_Caplets!M49)<0.0000001,"OK","CHECK")) -> OK
B50: Cap 5Y Total (Model) | L50: =SUM(L31:L49) -> 0.014246292 | M50: =SUM(M31:M49) -> 142.46292
B52: 7Y Cap · K = 3.620% · 27 caplets (T_start = 0.25 to 6.75)
B53: T_start | C53: T_end | D53: P(0,S) | E53: P(0,S+δ) | F53: K
B54: 0.25 | C54: 0.5 | D54: =VLOOKUP(B54,OIS_Curve!$B$19:$D$58,3,FALSE()) -> 0.98973154 | E54: =VLOOKUP(C54,OIS_Curve!$B$19:$D$58,3,FALSE()) -> 0.98039216 | F54: =Par_Rates!$E$8 -> 0.036200201 | G54: =1/(1+F54*0.25) -> 0.99103112 | H54: =(Parameters!$C$5/Parameters!$C$4)*(1-EXP(-Parameters!$C$4*0.25))*SQRT((1-EXP(-2*Parameters!$C$4*B54))/(2*Parameters!$C$4)) -> 0.00097241305 | I54: =(1/H54)*LN(E54/(D54*G54))+H54/2 -> -0.48463086 | J54: =NORMSDIST(-I54+H54) -> 0.68637576 | K54: =NORMSDIST(-I54) -> 0.68603089 | L54: =(1+F54*0.25)*(G54*D54*J54-E54*K54) -> 0.00066155607 | M54: =L54*10000 -> 6.6155607 | O54: =IF(M54="","?",IF(ABS(M54-HW_Caplets!M54)<0.0000001,"OK","CHECK")) -> OK
B55: 0.5 | C55: 0.75 | D55: =VLOOKUP(B55,OIS_Curve!$B$19:$D$58,3,FALSE()) -> 0.98039216 | E55: =VLOOKUP(C55,OIS_Curve!$B$19:$D$58,3,FALSE()) -> 0.97157395 | F55: =Par_Rates!$E$8 -> 0.036200201 | G55: =1/(1+F55*0.25) -> 0.99103112 | H55: =(Parameters!$C$5/Parameters!$C$4)*(1-EXP(-Parameters!$C$4*0.25))*SQRT((1-EXP(-2*Parameters!$C$4*B55))/(2*Parameters!$C$4)) -> 0.0013481001 | I55: =(1/H55)*LN(E55/(D55*G55))+H55/2 -> -0.01855182 | J55: =NORMSDIST(-I55+H55) -> 0.5079384 | K55: =NORMSDIST(-I55) -> 0.50740068 | L55: =(1+F55*0.25)*(G55*D55*J55-E55*K55) -> 0.00054006427 | M55: =L55*10000 -> 5.4006427 | O55: =IF(M55="","?",IF(ABS(M55-HW_Caplets!M55)<0.0000001,"OK","CHECK")) -> OK
B56: 0.75 | C56: 1 | D56: =VLOOKUP(B56,OIS_Curve!$B$19:$D$58,3,FALSE()) -> 0.97157395 | E56: =VLOOKUP(C56,OIS_Curve!$B$19:$D$58,3,FALSE()) -> 0.96339114 | F56: =Par_Rates!$E$8 -> 0.036200201 | G56: =1/(1+F56*0.25) -> 0.99103112 | H56: =(Parameters!$C$5/Parameters!$C$4)*(1-EXP(-Parameters!$C$4*0.25))*SQRT((1-EXP(-2*Parameters!$C$4*B56))/(2*Parameters!$C$4)) -> 0.0016189875 | I56: =(1/H56)*LN(E56/(D56*G56))+H56/2 -> 0.34142304 | J56: =NORMSDIST(-I56+H56) -> 0.36700205 | K56: =NORMSDIST(-I56) -> 0.36639257 | L56: =(1+F56*0.25)*(G56*D56*J56-E56*K56) -> 0.00039579889 | M56: =L56*10000 -> 3.9579889 | O56: =IF(M56="","?",IF(ABS(M56-HW_Caplets!M56)<0.0000001,"OK","CHECK")) -> OK
B57: 1 | C57: 1.25 | D57: =VLOOKUP(B57,OIS_Curve!$B$19:$D$58,3,FALSE()) -> 0.96339114 | E57: =VLOOKUP(C57,OIS_Curve!$B$19:$D$58,3,FALSE()) -> 0.95474312 | F57: =Par_Rates!$E$8 -> 0.036200201 | G57: =1/(1+F57*0.25) -> 0.99103112 | H57: =(Parameters!$C$5/Parameters!$C$4)*(1-EXP(-Parameters!$C$4*0.25))*SQRT((1-EXP(-2*Parameters!$C$4*B57))/(2*Parameters!$C$4)) -> 0.0018336131 | I57: =(1/H57)*LN(E57/(D57*G57))+H57/2 -> -0.0033522411 | J57: =NORMSDIST(-I57+H57) -> 0.50206885 | K57: =NORMSDIST(-I57) -> 0.50133735 | L57: =(1+F57*0.25)*(G57*D57*J57-E57*K57) -> 0.00070850034 | M57: =L57*10000 -> 7.0850034 | O57: =IF(M57="","?",IF(ABS(M57-HW_Caplets!M57)<0.0000001,"OK","CHECK")) -> OK
B58: 1.25 | C58: 1.5 | D58: =VLOOKUP(B58,OIS_Curve!$B$19:$D$58,3,FALSE()) -> 0.95474312 | E58: =VLOOKUP(C58,OIS_Curve!$B$19:$D$58,3,FALSE()) -> 0.94628885 | F58: =Par_Rates!$E$8 -> 0.036200201 | G58: =1/(1+F58*0.25) -> 0.99103112 | H58: =(Parameters!$C$5/Parameters!$C$4)*(1-EXP(-Parameters!$C$4*0.25))*SQRT((1-EXP(-2*Parameters!$C$4*B58))/(2*Parameters!$C$4)) -> 0.0020112979 | I58: =(1/H58)*LN(E58/(D58*G58))+H58/2 -> 0.05812397 | J58: =NORMSDIST(-I58+H58) -> 0.47762602 | K58: =NORMSDIST(-I58) -> 0.47682494 | L58: =(1+F58*0.25)*(G58*D58*J58-E58*K58) -> 0.00071252676 | M58: =L58*10000 -> 7.1252676 | O58: =IF(M58="","?",IF(ABS(M58-HW_Caplets!M58)<0.0000001,"OK","CHECK")) -> OK
B59: 1.5 | C59: 1.75 | D59: =VLOOKUP(B59,OIS_Curve!$B$19:$D$58,3,FALSE()) -> 0.94628885 | E59: =VLOOKUP(C59,OIS_Curve!$B$19:$D$58,3,FALSE()) -> 0.93802454 | F59: =Par_Rates!$E$8 -> 0.036200201 | G59: =1/(1+F59*0.25) -> 0.99103112 | H59: =(Parameters!$C$5/Parameters!$C$4)*(1-EXP(-Parameters!$C$4*0.25))*SQRT((1-EXP(-2*Parameters!$C$4*B59))/(2*Parameters!$C$4)) -> 0.0021622167 | I59: =(1/H59)*LN(E59/(D59*G59))+H59/2 -> 0.1109645 | J59: =NORMSDIST(-I59+H59) -> 0.45667966 | K59: =NORMSDIST(-I59) -> 0.45582225 | L59: =(1+F59*0.25)*(G59*D59*J59-E59*K59) -> 0.0007088603 | M59: =L59*10000 -> 7.088603 | O59: =IF(M59="","?",IF(ABS(M59-HW_Caplets!M59)<0.0000001,"OK","CHECK")) -> OK
B60: 1.75 | C60: 2 | D60: =VLOOKUP(B60,OIS_Curve!$B$19:$D$58,3,FALSE()) -> 0.93802454 | E60: =VLOOKUP(C60,OIS_Curve!$B$19:$D$58,3,FALSE()) -> 0.92994651 | F60: =Par_Rates!$E$8 -> 0.036200201 | G60: =1/(1+F60*0.25) -> 0.99103112 | H60: =(Parameters!$C$5/Parameters!$C$4)*(1-EXP(-Parameters!$C$4*0.25))*SQRT((1-EXP(-2*Parameters!$C$4*B60))/(2*Parameters!$C$4)) -> 0.0022925715 | I60: =(1/H60)*LN(E60/(D60*G60))+H60/2 -> 0.15830668 | J60: =NORMSDIST(-I60+H60) -> 0.43801095 | K60: =NORMSDIST(-I60) -> 0.43710757 | L60: =(1+F60*0.25)*(G60*D60*J60-E60*K60) -> 0.00069963407 | M60: =L60*10000 -> 6.9963407 | O60: =IF(M60="","?",IF(ABS(M60-HW_Caplets!M60)<0.0000001,"OK","CHECK")) -> OK
B61: 2 | C61: 2.25 | D61: =VLOOKUP(B61,OIS_Curve!$B$19:$D$58,3,FALSE()) -> 0.92994651 | E61: =VLOOKUP(C61,OIS_Curve!$B$19:$D$58,3,FALSE()) -> 0.92179827 | F61: =Par_Rates!$E$8 -> 0.036200201 | G61: =1/(1+F61*0.25) -> 0.99103112 | H61: =(Parameters!$C$5/Parameters!$C$4)*(1-EXP(-Parameters!$C$4*0.25))*SQRT((1-EXP(-2*Parameters!$C$4*B61))/(2*Parameters!$C$4)) -> 0.0024065047 | I61: =(1/H61)*LN(E61/(D61*G61))+H61/2 -> 0.087916984 | J61: =NORMSDIST(-I61+H61) -> 0.46592778 | K61: =NORMSDIST(-I61) -> 0.46497133 | L61: =(1+F61*0.25)*(G61*D61*J61-E61*K61) -> 0.00079920962 | M61: =L61*10000 -> 7.9920962 | O61: =IF(M61="","?",IF(ABS(M61-HW_Caplets!M61)<0.0000001,"OK","CHECK")) -> OK
B62: 2.25 | C62: 2.5 | D62: =VLOOKUP(B62,OIS_Curve!$B$19:$D$58,3,FALSE()) -> 0.92179827 | E62: =VLOOKUP(C62,OIS_Curve!$B$19:$D$58,3,FALSE()) -> 0.91377784 | F62: =Par_Rates!$E$8 -> 0.036200201 | G62: =1/(1+F62*0.25) -> 0.99103112 | H62: =(Parameters!$C$5/Parameters!$C$4)*(1-EXP(-Parameters!$C$4*0.25))*SQRT((1-EXP(-2*Parameters!$C$4*B62))/(2*Parameters!$C$4)) -> 0.0025069625 | I62: =(1/H62)*LN(E62/(D62*G62))+H62/2 -> 0.1091225 | J62: =NORMSDIST(-I62+H62) -> 0.45754699 | K62: =NORMSDIST(-I62) -> 0.45655266 | L62: =(1+F62*0.25)*(G62*D62*J62-E62*K62) -> 0.00080274988 | M62: =L62*10000 -> 8.0274988 | O62: =IF(M62="","?",IF(ABS(M62-HW_Caplets!M62)<0.0000001,"OK","CHECK")) -> OK
B63: 2.5 | C63: 2.75 | D63: =VLOOKUP(B63,OIS_Curve!$B$19:$D$58,3,FALSE()) -> 0.91377784 | E63: =VLOOKUP(C63,OIS_Curve!$B$19:$D$58,3,FALSE()) -> 0.90588313 | F63: =Par_Rates!$E$8 -> 0.036200201 | G63: =1/(1+F63*0.25) -> 0.99103112 | H63: =(Parameters!$C$5/Parameters!$C$4)*(1-EXP(-Parameters!$C$4*0.25))*SQRT((1-EXP(-2*Parameters!$C$4*B63))/(2*Parameters!$C$4)) -> 0.0025961381 | I63: =(1/H63)*LN(E63/(D63*G63))+H63/2 -> 0.12924588 | J63: =NORMSDIST(-I63+H63) -> 0.44960881 | K63: =NORMSDIST(-I63) -> 0.44858155 | L63: =(1+F63*0.25)*(G63*D63*J63-E63*K63) -> 0.00080251241 | M63: =L63*10000 -> 8.0251241 | O63: =IF(M63="","?",IF(ABS(M63-HW_Caplets!M63)<0.0000001,"OK","CHECK")) -> OK
B64: 2.75 | C64: 3 | D64: =VLOOKUP(B64,OIS_Curve!$B$19:$D$58,3,FALSE()) -> 0.90588313 | E64: =VLOOKUP(C64,OIS_Curve!$B$19:$D$58,3,FALSE()) -> 0.89811208 | F64: =Par_Rates!$E$8 -> 0.036200201 | G64: =1/(1+F64*0.25) -> 0.99103112 | H64: =(Parameters!$C$5/Parameters!$C$4)*(1-EXP(-Parameters!$C$4*0.25))*SQRT((1-EXP(-2*Parameters!$C$4*B64))/(2*Parameters!$C$4)) -> 0.002675722 | I64: =(1/H64)*LN(E64/(D64*G64))+H64/2 -> 0.14855673 | J64: =NORMSDIST(-I64+H64) -> 0.44200766 | K64: =NORMSDIST(-I64) -> 0.44095171 | L64: =(1+F64*0.25)*(G64*D64*J64-E64*K64) -> 0.00079918873 | M64: =L64*10000 -> 7.9918873 | O64: =IF(M64="","?",IF(ABS(M64-HW_Caplets!M64)<0.0000001,"OK","CHECK")) -> OK
B65: 3 | C65: 3.25 | D65: =VLOOKUP(B65,OIS_Curve!$B$19:$D$58,3,FALSE()) -> 0.89811208 | E65: =VLOOKUP(C65,OIS_Curve!$B$19:$D$58,3,FALSE()) -> 0.89004033 | F65: =Par_Rates!$E$8 -> 0.036200201 | G65: =1/(1+F65*0.25) -> 0.99103112 | H65: =(Parameters!$C$5/Parameters!$C$4)*(1-EXP(-Parameters!$C$4*0.25))*SQRT((1-EXP(-2*Parameters!$C$4*B65))/(2*Parameters!$C$4)) -> 0.0027470527 | I65: =(1/H65)*LN(E65/(D65*G65))+H65/2 -> -0.0054556071 | J65: =NORMSDIST(-I65+H65) -> 0.50327235 | K65: =NORMSDIST(-I65) -> 0.50217646 | L65: =(1+F65*0.25)*(G65*D65*J65-E65*K65) -> 0.00099269254 | M65: =L65*10000 -> 9.9269254 | O65: =IF(M65="","?",IF(ABS(M65-HW_Caplets!M65)<0.0000001,"OK","CHECK")) -> OK
... B80: 6.75 | C80: 7 | D80: =VLOOKUP(B80,OIS_Curve!$B$19:$D$58,3,FALSE()) -> 0.78842282 | E80: =VLOOKUP(C80,OIS_Curve!$B$19:$D$58,3,FALSE()) -> 0.78212785 | F80: =Par_Rates!$E$8 -> 0.036200201 | G80: =1/(1+F80*0.25) -> 0.99103112 | H80: =(Parameters!$C$5/Parameters!$C$4)*(1-EXP(-Parameters!$C$4*0.25))*SQRT((1-EXP(-2*Parameters!$C$4*B80))/(2*Parameters!$C$4)) -> 0.0032810279 | I80: =(1/H80)*LN(E80/(D80*G80))+H80/2 -> 0.30430224 | J80: =NORMSDIST(-I80+H80) -> 0.38169916 | K80: =NORMSDIST(-I80) -> 0.38044882 | L80: =(1+F80*0.25)*(G80*D80*J80-E80*K80) -> 0.00068778156 | M80: =L80*10000 -> 6.8778156 | O80: =IF(M80="","?",IF(ABS(M80-HW_Caplets!M80)<0.0000001,"OK","CHECK")) -> OK
B81: Cap 7Y Total (Model) | L81: =SUM(L54:L80) -> 0.021983469 | M81: =SUM(M54:M80) -> 219.83469
B83: 10Y Cap · K = 3.590% · 39 caplets (T_start = 0.25 to 9.75)
B84: T_start | C84: T_end | D84: P(0,S) | E84: P(0,S+δ) | F84: K
B85: 0.25 | C85: 0.5 | D85: =VLOOKUP(B85,OIS_Curve!$B$19:$D$58,3,FALSE()) -> 0.98973154 | E85: =VLOOKUP(C85,OIS_Curve!$B$19:$D$58,3,FALSE()) -> 0.98039216 | F85: =Par_Rates!$E$9 -> 0.035900471 | G85: =1/(1+F85*0.25) -> 0.99110472 | H85: =(Parameters!$C$5/Parameters!$C$4)*(1-EXP(-Parameters!$C$4*0.25))*SQRT((1-EXP(-2*Parameters!$C$4*B85))/(2*Parameters!$C$4)) -> 0.00097241305 | I85: =(1/H85)*LN(E85/(D85*G85))+H85/2 -> -0.56100095 | J85: =NORMSDIST(-I85+H85) -> 0.71293292 | K85: =NORMSDIST(-I85) -> 0.71260156 | L85: =(1+F85*0.25)*(G85*D85*J85-E85*K85) -> 0.00071293663 | M85: =L85*10000 -> 7.1293663 | O85: =IF(M85="","?",IF(ABS(M85-HW_Caplets!M85)<0.0000001,"OK","CHECK")) -> OK
B86: 0.5 | C86: 0.75 | D86: =VLOOKUP(B86,OIS_Curve!$B$19:$D$58,3,FALSE()) -> 0.98039216 | E86: =VLOOKUP(C86,OIS_Curve!$B$19:$D$58,3,FALSE()) -> 0.97157395 | F86: =Par_Rates!$E$9 -> 0.035900471 | G86: =1/(1+F86*0.25) -> 0.99110472 | H86: =(Parameters!$C$5/Parameters!$C$4)*(1-EXP(-Parameters!$C$4*0.25))*SQRT((1-EXP(-2*Parameters!$C$4*B86))/(2*Parameters!$C$4)) -> 0.0013481001 | I86: =(1/H86)*LN(E86/(D86*G86))+H86/2 -> -0.073639176 | J86: =NORMSDIST(-I86+H86) -> 0.52988758 | K86: =NORMSDIST(-I86) -> 0.52935125 | L86: =(1+F86*0.25)*(G86*D86*J86-E86*K86) -> 0.00057780369 | M86: =L86*10000 -> 5.7780369 | O86: =IF(M86="","?",IF(ABS(M86-HW_Caplets!M86)<0.0000001,"OK","CHECK")) -> OK
B87: 0.75 | C87: 1 | D87: =VLOOKUP(B87,OIS_Curve!$B$19:$D$58,3,FALSE()) -> 0.97157395 | E87: =VLOOKUP(C87,OIS_Curve!$B$19:$D$58,3,FALSE()) -> 0.96339114 | F87: =Par_Rates!$E$9 -> 0.035900471 | G87: =1/(1+F87*0.25) -> 0.99110472 | H87: =(Parameters!$C$5/Parameters!$C$4)*(1-EXP(-Parameters!$C$4*0.25))*SQRT((1-EXP(-2*Parameters!$C$4*B87))/(2*Parameters!$C$4)) -> 0.0016189875 | I87: =(1/H87)*LN(E87/(D87*G87))+H87/2 -> 0.29555284 | J87: =NORMSDIST(-I87+H87) -> 0.38440422 | K87: =NORMSDIST(-I87) -> 0.3837858 | L87: =(1+F87*0.25)*(G87*D87*J87-E87*K87) -> 0.0004228748 | M87: =L87*10000 -> 4.228748 | O87: =IF(M87="","?",IF(ABS(M87-HW_Caplets!M87)<0.0000001,"OK","CHECK")) -> OK
B88: 1 | C88: 1.25 | D88: =VLOOKUP(B88,OIS_Curve!$B$19:$D$58,3,FALSE()) -> 0.96339114 | E88: =VLOOKUP(C88,OIS_Curve!$B$19:$D$58,3,FALSE()) -> 0.95474312 | F88: =Par_Rates!$E$9 -> 0.035900471 | G88: =1/(1+F88*0.25) -> 0.99110472 | H88: =(Parameters!$C$5/Parameters!$C$4)*(1-EXP(-Parameters!$C$4*0.25))*SQRT((1-EXP(-2*Parameters!$C$4*B88))/(2*Parameters!$C$4)) -> 0.0018336131 | I88: =(1/H88)*LN(E88/(D88*G88))+H88/2 -> -0.043853301 | J88: =NORMSDIST(-I88+H88) -> 0.5182201 | K88: =NORMSDIST(-I88) -> 0.51748933 | L88: =(1+F88*0.25)*(G88*D88*J88-E88*K88) -> 0.00074494455 | M88: =L88*10000 -> 7.4494455 | O88: =IF(M88="","?",IF(ABS(M88-HW_Caplets!M88)<0.0000001,"OK","CHECK")) -> OK
B89: 1.25 | C89: 1.5 | D89: =VLOOKUP(B89,OIS_Curve!$B$19:$D$58,3,FALSE()) -> 0.95474312 | E89: =VLOOKUP(C89,OIS_Curve!$B$19:$D$58,3,FALSE()) -> 0.94628885 | F89: =Par_Rates!$E$9 -> 0.035900471 | G89: =1/(1+F89*0.25) -> 0.99110472 | H89: =(Parameters!$C$5/Parameters!$C$4)*(1-EXP(-Parameters!$C$4*0.25))*SQRT((1-EXP(-2*Parameters!$C$4*B89))/(2*Parameters!$C$4)) -> 0.0020112979 | I89: =(1/H89)*LN(E89/(D89*G89))+H89/2 -> 0.02120091 | J89: =NORMSDIST(-I89+H89) -> 0.49234492 | K89: =NORMSDIST(-I89) -> 0.49154269 | L89: =(1+F89*0.25)*(G89*D89*J89-E89*K89) -> 0.00074685906 | M89: =L89*10000 -> 7.4685906 | O89: =IF(M89="","?",IF(ABS(M89-HW_Caplets!M89)<0.0000001,"OK","CHECK")) -> OK
B90: 1.5 | C90: 1.75 | D90: =VLOOKUP(B90,OIS_Curve!$B$19:$D$58,3,FALSE()) -> 0.94628885 | E90: =VLOOKUP(C90,OIS_Curve!$B$19:$D$58,3,FALSE()) -> 0.93802454 | F90: =Par_Rates!$E$9 -> 0.035900471 | G90: =1/(1+F90*0.25) -> 0.99110472 | H90: =(Parameters!$C$5/Parameters!$C$4)*(1-EXP(-Parameters!$C$4*0.25))*SQRT((1-EXP(-2*Parameters!$C$4*B90))/(2*Parameters!$C$4)) -> 0.0021622167 | I90: =(1/H90)*LN(E90/(D90*G90))+H90/2 -> 0.0766186 | J90: =NORMSDIST(-I90+H90) -> 0.47032362 | K90: =NORMSDIST(-I90) -> 0.46946348 | L90: =(1+F90*0.25)*(G90*D90*J90-E90*K90) -> 0.00074137856 | M90: =L90*10000 -> 7.4137856 | O90: =IF(M90="","?",IF(ABS(M90-HW_Caplets!M90)<0.0000001,"OK","CHECK")) -> OK
B91: 1.75 | C91: 2 | D91: =VLOOKUP(B91,OIS_Curve!$B$19:$D$58,3,FALSE()) -> 0.93802454 | E91: =VLOOKUP(C91,OIS_Curve!$B$19:$D$58,3,FALSE()) -> 0.92994651 | F91: =Par_Rates!$E$9 -> 0.035900471 | G91: =1/(1+F91*0.25) -> 0.99110472 | H91: =(Parameters!$C$5/Parameters!$C$4)*(1-EXP(-Parameters!$C$4*0.25))*SQRT((1-EXP(-2*Parameters!$C$4*B91))/(2*Parameters!$C$4)) -> 0.0022925715 | I91: =(1/H91)*LN(E91/(D91*G91))+H91/2 -> 0.12591368 | J91: =NORMSDIST(-I91+H91) -> 0.45080764 | K91: =NORMSDIST(-I91) -> 0.44990013 | L91: =(1+F91*0.25)*(G91*D91*J91-E91*K91) -> 0.00073053853 | M91: =L91*10000 -> 7.3053853 | O91: =IF(M91="","?",IF(ABS(M91-HW_Caplets!M91)<0.0000001,"OK","CHECK")) -> OK
B92: 2 | C92: 2.25 | D92: =VLOOKUP(B92,OIS_Curve!$B$19:$D$58,3,FALSE()) -> 0.92994651 | E92: =VLOOKUP(C92,OIS_Curve!$B$19:$D$58,3,FALSE()) -> 0.92179827 | F92: =Par_Rates!$E$9 -> 0.035900471 | G92: =1/(1+F92*0.25) -> 0.99110472 | H92: =(Parameters!$C$5/Parameters!$C$4)*(1-EXP(-Parameters!$C$4*0.25))*SQRT((1-EXP(-2*Parameters!$C$4*B92))/(2*Parameters!$C$4)) -> 0.0024065047 | I92: =(1/H92)*LN(E92/(D92*G92))+H92/2 -> 0.057057593 | J92: =NORMSDIST(-I92+H92) -> 0.47820822 | K92: =NORMSDIST(-I92) -> 0.47724966 | L92: =(1+F92*0.25)*(G92*D92*J92-E92*K92) -> 0.00083175034 | M92: =L92*10000 -> 8.3175034 | O92: =IF(M92="","?",IF(ABS(M92-HW_Caplets!M92)<0.0000001,"OK","CHECK")) -> OK
B93: 2.25 | C93: 2.5 | D93: =VLOOKUP(B93,OIS_Curve!$B$19:$D$58,3,FALSE()) -> 0.92179827 | E93: =VLOOKUP(C93,OIS_Curve!$B$19:$D$58,3,FALSE()) -> 0.91377784 | F93: =Par_Rates!$E$9 -> 0.035900471 | G93: =1/(1+F93*0.25) -> 0.99110472 | H93: =(Parameters!$C$5/Parameters!$C$4)*(1-EXP(-Parameters!$C$4*0.25))*SQRT((1-EXP(-2*Parameters!$C$4*B93))/(2*Parameters!$C$4)) -> 0.0025069625 | I93: =(1/H93)*LN(E93/(D93*G93))+H93/2 -> 0.079499695 | J93: =NORMSDIST(-I93+H93) -> 0.46931466 | K93: =NORMSDIST(-I93) -> 0.46831759 | L93: =(1+F93*0.25)*(G93*D93*J93-E93*K93) -> 0.00083441342 | M93: =L93*10000 -> 8.3441342 | O93: =IF(M93="","?",IF(ABS(M93-HW_Caplets!M93)<0.0000001,"OK","CHECK")) -> OK
B94: 2.5 | C94: 2.75 | D94: =VLOOKUP(B94,OIS_Curve!$B$19:$D$58,3,FALSE()) -> 0.91377784 | E94: =VLOOKUP(C94,OIS_Curve!$B$19:$D$58,3,FALSE()) -> 0.90588313 | F94: =Par_Rates!$E$9 -> 0.035900471 | G94: =1/(1+F94*0.25) -> 0.99110472 | H94: =(Parameters!$C$5/Parameters!$C$4)*(1-EXP(-Parameters!$C$4*0.25))*SQRT((1-EXP(-2*Parameters!$C$4*B94))/(2*Parameters!$C$4)) -> 0.0025961381 | I94: =(1/H94)*LN(E94/(D94*G94))+H94/2 -> 0.10064059 | J94: =NORMSDIST(-I94+H94) -> 0.4609485 | K94: =NORMSDIST(-I94) -> 0.45991789 | L94: =(1+F94*0.25)*(G94*D94*J94-E94*K94) -> 0.00083334674 | M94: =L94*10000 -> 8.3334674 | O94: =IF(M94="","?",IF(ABS(M94-HW_Caplets!M94)<0.0000001,"OK","CHECK")) -> OK
B95: 2.75 | C95: 3 | D95: =VLOOKUP(B95,OIS_Curve!$B$19:$D$58,3,FALSE()) -> 0.90588313 | E95: =VLOOKUP(C95,OIS_Curve!$B$19:$D$58,3,FALSE()) -> 0.89811208 | F95: =Par_Rates!$E$9 -> 0.035900471 | G95: =1/(1+F95*0.25) -> 0.99110472 | H95: =(Parameters!$C$5/Parameters!$C$4)*(1-EXP(-Parameters!$C$4*0.25))*SQRT((1-EXP(-2*Parameters!$C$4*B95))/(2*Parameters!$C$4)) -> 0.002675722 | I95: =(1/H95)*LN(E95/(D95*G95))+H95/2 -> 0.12080225 | J95: =NORMSDIST(-I95+H95) -> 0.4529837 | K95: =NORMSDIST(-I95) -> 0.45192383 | L95: =(1+F95*0.25)*(G95*D95*J95-E95*K95) -> 0.0008292328 | M95: =L95*10000 -> 8.292328 | O95: =IF(M95="","?",IF(ABS(M95-HW_Caplets!M95)<0.0000001,"OK","CHECK")) -> OK
B96: 3 | C96: 3.25 | D96: =VLOOKUP(B96,OIS_Curve!$B$19:$D$58,3,FALSE()) -> 0.89811208 | E96: =VLOOKUP(C96,OIS_Curve!$B$19:$D$58,3,FALSE()) -> 0.89004033 | F96: =Par_Rates!$E$9 -> 0.035900471 | G96: =1/(1+F96*0.25) -> 0.99110472 | H96: =(Parameters!$C$5/Parameters!$C$4)*(1-EXP(-Parameters!$C$4*0.25))*SQRT((1-EXP(-2*Parameters!$C$4*B96))/(2*Parameters!$C$4)) -> 0.0027470527 | I96: =(1/H96)*LN(E96/(D96*G96))+H96/2 -> -0.032489406 | J96: =NORMSDIST(-I96+H96) -> 0.5140544 | K96: =NORMSDIST(-I96) -> 0.51295912 | L96: =(1+F96*0.25)*(G96*D96*J96-E96*K96) -> 0.0010265438 | M96: =L96*10000 -> 10.265438 | O96: =IF(M96="","?",IF(ABS(M96-HW_Caplets!M96)<0.0000001,"OK","CHECK")) -> OK
... B123: 9.75 | C123: 10 | D123: =VLOOKUP(B123,OIS_Curve!$B$19:$D$58,3,FALSE()) -> 0.71141551 | E123: =VLOOKUP(C123,OIS_Curve!$B$19:$D$58,3,FALSE()) -> 0.7062794 | F123: =Par_Rates!$E$9 -> 0.035900471 | G123: =1/(1+F123*0.25) -> 0.99110472 | H123: =(Parameters!$C$5/Parameters!$C$4)*(1-EXP(-Parameters!$C$4*0.25))*SQRT((1-EXP(-2*Parameters!$C$4*B123))/(2*Parameters!$C$4)) -> 0.0034068003 | I123: =(1/H123)*LN(E123/(D123*G123))+H123/2 -> 0.49757478 | J123: =NORMSDIST(-I123+H123) -> 0.31059377 | K123: =NORMSDIST(-I123) -> 0.30939189 | L123: =(1+F123*0.25)*(G123*D123*J123-E123*K123) -> 0.00048289169 | M123: =L123*10000 -> 4.8289169 | O123: =IF(M123="","?",IF(ABS(M123-HW_Caplets!M123)<0.0000001,"OK","CHECK")) -> OK
B124: Cap 10Y Total (Model) | L124: =SUM(L85:L123) -> 0.033364325 | M124: =SUM(M85:M123) -> 333.64325

Sheet Cap_Prices
B1: Cap Prices · Model vs Market · SSE → Solver Target
B3: Cap Maturity | C3: Market Price (bps) | D3: Model Price (bps) | E3: Error (bps) | F3: Squared Error
B4: 2Y | C4: =Par_Rates!$F$5 -> 21.897316 | D4: =HW_Caplets!M12 -> 21.983824 | E4: =D4-C4 -> 0.086507835 | F4: =E4^2 -> 0.0074836054
B5: 3Y | C5: =Par_Rates!$F$6 -> 69.912719 | D5: =HW_Caplets!M27 -> 70.31273 | E5: =D5-C5 -> 0.4000108 | F5: =E5^2 -> 0.16000864
B6: 5Y | C6: =Par_Rates!$F$7 -> 143.36482 | D6: =HW_Caplets!M50 -> 142.46292 | E6: =D6-C6 -> -0.90189869 | F6: =E6^2 -> 0.81342124
B7: 7Y | C7: =Par_Rates!$F$8 -> 219.15872 | D7: =HW_Caplets!M81 -> 219.83469 | E7: =D7-C7 -> 0.67596745 | F7: =E7^2 -> 0.45693199
B8: 10Y | C8: =Par_Rates!$F$9 -> 333.79573 | D8: =HW_Caplets!M124 -> 333.64325 | E8: =D8-C8 -> -0.15247593 | F8: =E8^2 -> 0.023248908
B10: ◀ SSE — SOLVER MINIMISES THIS CELL | F10: =SUM(F4:F8) -> 1.4610944
B12: SOLVER SETUP
B13: Set Objective Cell → Cap_Prices!F10 → Minimize
B14: By Changing → Parameters!C4 (a) and Parameters!C5 (σ)
B15: Add Constraints → Parameters!C4 >= 0.001 | Parameters!C5 >= 0.0001
B16: Solving Method → GRG Nonlinear
B17: ★ True parameters embedded in market prices: a = 0.15, σ = 0.008 (+ small noise)

Sheet TRY_CapPrices
B1: PRACTICE: Cap Prices & Calibration · Yellow cells = YOUR TURN · Check col shows OK/CHECK
B3: Cap Maturity | C3: Market Price (bps) | D3: Model Price (bps) | E3: Error (bps) | F3: Squared Error | H3: Check vs Solution
B4: 2Y | C4: =Par_Rates!$F$5 -> 21.897316 | D4: =TRY_Caplets!M12 -> 21.983824 | E4: =D4-C4 -> 0.086507835 | F4: =E4^2 -> 0.0074836054 | H4: =IF(D4="","?",IF(ABS(D4-Cap_Prices!D4)<0.0001,"OK","CHECK")) -> OK
B5: 3Y | C5: =Par_Rates!$F$6 -> 69.912719 | D5: =TRY_Caplets!M27 -> 70.31273 | E5: =D5-C5 -> 0.4000108 | F5: =E5^2 -> 0.16000864 | H5: =IF(D5="","?",IF(ABS(D5-Cap_Prices!D5)<0.0001,"OK","CHECK")) -> OK
B6: 5Y | C6: =Par_Rates!$F$7 -> 143.36482 | D6: =TRY_Caplets!M50 -> 142.46292 | E6: =D6-C6 -> -0.90189869 | F6: =E6^2 -> 0.81342124 | H6: =IF(D6="","?",IF(ABS(D6-Cap_Prices!D6)<0.0001,"OK","CHECK")) -> OK
B7: 7Y | C7: =Par_Rates!$F$8 -> 219.15872 | D7: =TRY_Caplets!M81 -> 219.83469 | E7: =D7-C7 -> 0.67596745 | F7: =E7^2 -> 0.45693199 | H7: =IF(D7="","?",IF(ABS(D7-Cap_Prices!D7)<0.0001,"OK","CHECK")) -> OK
B8: 10Y | C8: =Par_Rates!$F$9 -> 333.79573 | D8: =TRY_Caplets!M124 -> 333.64325 | E8: =D8-C8 -> -0.15247593 | F8: =E8^2 -> 0.023248908 | H8: =IF(D8="","?",IF(ABS(D8-Cap_Prices!D8)<0.0001,"OK","CHECK")) -> OK
B10: ◀ SSE — SOLVER MINIMISES THIS CELL | F10: =SUM(F4:F8) -> 1.4610944
B12: SOLVER SETUP
B13: Set Objective Cell → Cap_Prices!F10 → Minimize
B14: By Changing → Parameters!C4 (a) and Parameters!C5 (σ)
B15: Add Constraints → Parameters!C4 >= 0.001 | Parameters!C5 >= 0.0001
B16: Solving Method → GRG Nonlinear
B17: ★ True parameters embedded in market prices: a = 0.15, σ = 0.008 (+ small noise)

Sheet Parameters
B1: HW1F Parameters · a and σ are Solver Variables
B3: Parameter | C3: Value | D3: Notes
B4: a (Mean Reversion Speed) | C4: 0.16252218 | D4: Solver variable · true=0.15 · must be > 0
B5: σ (Short Rate Volatility) | C5: 0.0081002192 | D5: Solver variable · true=0.008 · must be > 0
B6: r₀ (Initial Short Rate) | C6: 0.0104 | D6: ≈ overnight rate from OIS curve short end
B7: K (Cap Strike) | C7: per cap | D7: ATM par swap rate per maturity — see Par_Rates sheet
B8: δ (Caplet Tenor) | C8: 0.25 | D8: Quarterly (3M)
C10: =TRY_CapPrices!F10 -> 1.4610944
B12: SOLVER SETUP
B13: Set Objective Cell → Cap_Prices!F10 → Minimize
B14: By Changing → Parameters!C4 (a) and Parameters!C5 (σ)
B15: Add Constraints → Parameters!C4 >= 0.001 | Parameters!C5 >= 0.0001
B16: Solving Method → GRG Nonlinear
B17: ★ True parameters embedded in market prices: a = 0.15, σ = 0.008 (+ small noise)

Sheet TRY_OIS
B1: PRACTICE: OIS Curve Bootstrap · Yellow cells = YOUR TURN · Check col shows OK/CHECK
B3: SECTION 1 — SEQUENTIAL OIS BOOTSTRAP (liquid & interpolated tenors) | I3: Check vs Solution
B4: Tenor | C4: Type | D4: Instr Rate | E4: Discount Factor | F4: Zero Rate (cont) | G4: Formula / Note
B5: 0.25 | C5: MM | D5: =Instruments!$D$5 -> 0.0415 | E5: =1/(1+B5*D5) -> 0.98973154 | F5: =-LN(E5)/B5 -> 0.041286196 | G5: P = 1/(1+r·T) [simple interest, T=0.25] | I5: =IF(F5="","?",IF(ABS(F5-OIS_Curve!F5)<0.000001,"OK","CHECK")) -> OK | J5: =E5=OIS_Curve!E5 -> TRUE | K5: =F5=OIS_Curve!F5 -> TRUE
B6: 0.5 | C6: MM | D6: =Instruments!$D$6 -> 0.04 | E6: =1/(1+B6*D6) -> 0.98039216 | F6: =-LN(E6)/B6 -> 0.039605255 | G6: P = 1/(1+r·T) [simple interest, T=0.50] | I6: =IF(F6="","?",IF(ABS(F6-OIS_Curve!F6)<0.000001,"OK","CHECK")) -> OK | J6: =E6=OIS_Curve!E6 -> TRUE | K6: =F6=OIS_Curve!F6 -> TRUE
B7: 1 | C7: OIS Swap | D7: =Instruments!$D$9 -> 0.038 | E7: =1/(1+B7*D7) -> 0.96339114 | F7: =-LN(E7)/B7 -> 0.037295785 | G7: P = 1/(1+S) [1Y swap: single payment, P(1)=1/(1+S)] | I7: =IF(F7="","?",IF(ABS(F7-OIS_Curve!F7)<0.000001,"OK","CHECK")) -> OK | J7: =E7=OIS_Curve!E7 -> TRUE | K7: =F7=OIS_Curve!F7 -> TRUE
B8: 2 | C8: OIS Swap | D8: =Instruments!$D$10 -> 0.037 | E8: =(1-E7*D8)/(1+D8) -> 0.92994651 | F8: =-LN(E8)/B8 -> 0.036314107 | G8: P = (1-S·P1)/(1+S) [2Y bootstrap] | I8: =IF(F8="","?",IF(ABS(F8-OIS_Curve!F8)<0.000001,"OK","CHECK")) -> OK | J8: =E8=OIS_Curve!E8 -> TRUE | K8: =F8=OIS_Curve!F8 -> TRUE
B9: 3 | C9: OIS Swap | D9: =Instruments!$D$11 -> 0.0365 | E9: =(1-D9*E7-D9*E8)/(1+D9) -> 0.89811208 | F9: =-LN(E9)/B9 -> 0.035820134 | G9: P = (1-S·(P1+P2))/(1+S) [3Y bootstrap] | I9: =IF(F9="","?",IF(ABS(F9-OIS_Curve!F9)<0.000001,"OK","CHECK")) -> OK | J9: =E9=OIS_Curve!E9 -> TRUE | K9: =F9=OIS_Curve!F9 -> TRUE
B10: 4 | C10: Interp | D10: — | E10: =EXP(-F10*B10) -> 0.86619929 | F10: =F9+((D11-F9)/(B11-B9))*(B10-B9) -> 0.035910067 | G10: INTERP: z4 = z3 + (S5Y-z3)·(4-3)/(5-3) → P4 = EXP(-z4·4) [uses S5Y as proxy for z5] | I10: =IF(F10="","?",IF(ABS(F10-OIS_Curve!F10)<0.000001,"OK","CHECK")) -> OK | J10: =E10=OIS_Curve!E10 -> TRUE | K10: =F10=OIS_Curve!F10 -> TRUE
B11: 5 | C11: OIS Swap | D11: =Instruments!$D$12 -> 0.036 | E11: =(1-D11*SUM(E7:E10))/(1+D11) -> 0.83815119 | F11: =-LN(E11)/B11 -> 0.035311355 | G11: P = (1-S·(P1+P2+P3+P4))/(1+S) [5Y bootstrap using interpolated P4] | I11: =IF(F11="","?",IF(ABS(F11-OIS_Curve!F11)<0.000001,"OK","CHECK")) -> OK | J11: =E11=OIS_Curve!E11 -> TRUE | K11: =F11=OIS_Curve!F11 -> TRUE
B12: 6 | C12: Interp | D12: — | E12: =EXP(-F12*B12) -> 0.80788621 | F12: =F11+((D13-F11)/(B13-B11))*(B12-B11) -> 0.035555677 | G12: INTERP: z6 = z5 + (S7Y-z5)·(6-5)/(7-5) → P6 = EXP(-z6·6) | I12: =IF(F12="","?",IF(ABS(F12-OIS_Curve!F12)<0.000001,"OK","CHECK")) -> OK | J12: =E12=OIS_Curve!E12 -> TRUE | K12: =F12=OIS_Curve!F12 -> TRUE
B13: 7 | C13: OIS Swap | D13: =Instruments!$D$13 -> 0.0358 | E13: =(1-D13*SUM(E7:E12))/(1+D13) -> 0.78212785 | F13: =-LN(E13)/B13 -> 0.035105295 | G13: P = (1-S·(P1+...+P6))/(1+S) [7Y bootstrap] | I13: =IF(F13="","?",IF(ABS(F13-OIS_Curve!F13)<0.000001,"OK","CHECK")) -> OK | J13: =E13=OIS_Curve!E13 -> TRUE | K13: =F13=OIS_Curve!F13 -> TRUE
B14: 8 | C14: Interp | D14: — | E14: =EXP(-F14*B14) -> 0.75435296 | F14: =F13+((D16-F13)/(B16-B13))*(B14-B13) -> 0.035236863 | G14: INTERP: z8 = z7 + (S10Y-z7)·(8-7)/(10-7) → P8 = EXP(-z8·8) | I14: =IF(F14="","?",IF(ABS(F14-OIS_Curve!F14)<0.000001,"OK","CHECK")) -> OK | J14: =E14=OIS_Curve!E14 -> TRUE | K14: =F14=OIS_Curve!F14 -> TRUE
B15: 9 | C15: Interp | D15: — | E15: =EXP(-F15*B15) -> 0.72737299 | F15: =F13+((D16-F13)/(B16-B13))*(B15-B13) -> 0.035368432 | G15: INTERP: z9 = z7 + (S10Y-z7)·(9-7)/(10-7) → P9 = EXP(-z9·9) | I15: =IF(F15="","?",IF(ABS(F15-OIS_Curve!F15)<0.000001,"OK","CHECK")) -> OK | J15: =E15=OIS_Curve!E15 -> TRUE | K15: =F15=OIS_Curve!F15 -> TRUE
B16: 10 | C16: OIS Swap | D16: =Instruments!$D$14 -> 0.0355 | E16: =(1-D16*SUM(E7:E15))/(1+D16) -> 0.7062794 | F16: =-LN(E16)/B16 -> 0.034774436 | G16: P = (1-S·(P1+...+P9))/(1+S) [10Y bootstrap] | I16: =IF(F16="","?",IF(ABS(F16-OIS_Curve!F16)<0.000001,"OK","CHECK")) -> OK | J16: =E16=OIS_Curve!E16 -> TRUE | K16: =F16=OIS_Curve!F16 -> TRUE
B17: SECTION 2 — QUARTERLY OUTPUT GRID (piecewise linear interp on zero rates)
B18: Tenor | C18: Zero Rate (interp) | D18: Discount Factor | E18: Inst. Fwd Rate | F18: 3M OIS Fwd | G18: Formula Key
B19: 0.25 | C19: =F5 -> 0.041286196 | D19: =E5 -> 0.98973154 | E19: =C19 -> 0.041286196 | F19: =(D19/D20-1)/(B20-B19) -> 0.038104664 | G19: Z=MATCH+INDEX linear interp | DF=EXP(-Z·T) | IF=central diff | 3Mfwd=(DF/DF+1-1)/0.25 | I19: =IF(D19="","?",IF(ABS(D19-OIS_Curve!D19)<0.000001,"OK","CHECK")) -> OK | J19: =IF(ABS(C19-OIS_Curve!C19)<0.0001,TRUE(),FALSE()) -> TRUE | K19: =IF(ABS(D19-OIS_Curve!D19)<0.0001,TRUE(),FALSE()) -> TRUE | L19: =IF(ABS(E19-OIS_Curve!E19)<0.0001,TRUE(),FALSE()) -> TRUE | M19: =IF(ABS(F19-OIS_Curve!F19)<0.0001,TRUE(),FALSE()) -> TRUE
B20: 0.5 | C20: =F6 -> 0.039605255 | D20: =E6 -> 0.98039216 | E20: =-(LN(D21)-LN(D19))/(B21-B19) -> 0.037032681 | F20: =(D20/D21-1)/(B21-B20) -> 0.036304815 | G20: Z=MATCH+INDEX linear interp | DF=EXP(-Z·T) | IF=central diff | 3Mfwd=(DF/DF+1-1)/0.25 | I20: =IF(D20="","?",IF(ABS(D20-OIS_Curve!D20)<0.000001,"OK","CHECK")) -> OK | J20: =IF(ABS(C20-OIS_Curve!C20)<0.0001,TRUE(),FALSE()) -> TRUE | K20: =IF(ABS(D20-OIS_Curve!D20)<0.0001,TRUE(),FALSE()) -> TRUE | L20: =IF(ABS(E20-OIS_Curve!E20)<0.0001,TRUE(),FALSE()) -> TRUE | M20: =IF(ABS(F20-OIS_Curve!F20)<0.0001,TRUE(),FALSE()) -> TRUE
B21: 0.75 | C21: =AVERAGE(C20,C22) -> 0.03845052 | D21: =EXP(-B21*C21) -> 0.97157395 | E21: =-(LN(D22)-LN(D20))/(B22-B20) -> 0.034986315 | F21: =(D21/D22-1)/(B22-B21) -> 0.033975056 | G21: Z=MATCH+INDEX linear interp | DF=EXP(-Z·T) | IF=central diff | 3Mfwd=(DF/DF+1-1)/0.25 | I21: =IF(D21="","?",IF(ABS(D21-OIS_Curve!D21)<0.000001,"OK","CHECK")) -> OK | J21: =IF(ABS(C21-OIS_Curve!C21)<0.0001,TRUE(),FALSE()) -> TRUE | K21: =IF(ABS(D21-OIS_Curve!D21)<0.0001,TRUE(),FALSE()) -> TRUE | L21: =IF(ABS(E21-OIS_Curve!E21)<0.0001,TRUE(),FALSE()) -> TRUE | M21: =IF(ABS(F21-OIS_Curve!F21)<0.0001,TRUE(),FALSE()) -> TRUE
B22: 1 | C22: =VLOOKUP($B22,$B$4:$F$16,5,FALSE) -> 0.037295785 | D22: =VLOOKUP($B22,$B$4:$F$16,4,FALSE) -> 0.96339114 | E22: =-(LN(D23)-LN(D21))/(B23-B21) -> 0.034950134 | F22: =(D22/D23-1)/(B23-B22) -> 0.036231796 | I22: =IF(D22="","?",IF(ABS(D22-OIS_Curve!D22)<0.000001,"OK","CHECK")) -> OK | J22: =IF(ABS(C22-OIS_Curve!C22)<0.0001,TRUE(),FALSE()) -> TRUE | K22: =IF(ABS(D22-OIS_Curve!D22)<0.0001,TRUE(),FALSE()) -> TRUE | L22: =IF(ABS(E22-OIS_Curve!E22)<0.0001,TRUE(),FALSE()) -> TRUE | M22: =IF(ABS(F22-OIS_Curve!F22)<0.0001,TRUE(),FALSE()) -> TRUE
B23: 1.25 | C23: =$C$22+(($C$26-$C$22)/($B$26-$B$22))*(B23-$B$22) -> 0.037050365 | D23: =EXP(-B23*C23) -> 0.95474312 | E23: =-(LN(D24)-LN(D22))/(B24-B22) -> 0.035823268 | F23: =(D23/D24-1)/(B24-B23) -> 0.035736541 | I23: =IF(D23="","?",IF(ABS(D23-OIS_Curve!D23)<0.000001,"OK","CHECK")) -> OK | J23: =IF(ABS(C23-OIS_Curve!C23)<0.0001,TRUE(),FALSE()) -> TRUE | K23: =IF(ABS(D23-OIS_Curve!D23)<0.0001,TRUE(),FALSE()) -> TRUE | L23: =IF(ABS(E23-OIS_Curve!E23)<0.0001,TRUE(),FALSE()) -> TRUE | M23: =IF(ABS(F23-OIS_Curve!F23)<0.0001,TRUE(),FALSE()) -> TRUE
B24: 1.5 | C24: =$C$22+(($C$26-$C$22)/($B$26-$B$22))*(B24-$B$22) -> 0.036804946 | D24: =EXP(-B24*C24) -> 0.94628885 | E24: =-(LN(D25)-LN(D23))/(B25-B23) -> 0.035332429 | F24: =(D24/D25-1)/(B25-B24) -> 0.035241348 | I24: =IF(D24="","?",IF(ABS(D24-OIS_Curve!D24)<0.000001,"OK","CHECK")) -> OK | J24: =IF(ABS(C24-OIS_Curve!C24)<0.0001,TRUE(),FALSE()) -> TRUE | K24: =IF(ABS(D24-OIS_Curve!D24)<0.0001,TRUE(),FALSE()) -> TRUE | L24: =IF(ABS(E24-OIS_Curve!E24)<0.0001,TRUE(),FALSE()) -> TRUE | M24: =IF(ABS(F24-OIS_Curve!F24)<0.0001,TRUE(),FALSE()) -> TRUE
B25: 1.75 | C25: =$C$22+(($C$26-$C$22)/($B$26-$B$22))*(B25-$B$22) -> 0.036559526 | D25: =EXP(-B25*C25) -> 0.93802454 | E25: =-(LN(D26)-LN(D24))/(B26-B24) -> 0.03484159 | F25: =(D25/D26-1)/(B26-B25) -> 0.034746215 | I25: =IF(D25="","?",IF(ABS(D25-OIS_Curve!D25)<0.000001,"OK","CHECK")) -> OK | J25: =IF(ABS(C25-OIS_Curve!C25)<0.0001,TRUE(),FALSE()) -> TRUE | K25: =IF(ABS(D25-OIS_Curve!D25)<0.0001,TRUE(),FALSE()) -> TRUE | L25: =IF(ABS(E25-OIS_Curve!E25)<0.0001,TRUE(),FALSE()) -> TRUE | M25: =IF(ABS(F25-OIS_Curve!F25)<0.0001,TRUE(),FALSE()) -> TRUE
B26: 2 | C26: =VLOOKUP($B26,$B$4:$F$16,5,FALSE) -> 0.036314107 | D26: =VLOOKUP($B26,$B$4:$F$16,4,FALSE) -> 0.92994651 | E26: =-(LN(D27)-LN(D25))/(B27-B25) -> 0.034899419 | F26: =(D26/D27-1)/(B27-B26) -> 0.035358027 | I26: =IF(D26="","?",IF(ABS(D26-OIS_Curve!D26)<0.000001,"OK","CHECK")) -> OK | J26: =IF(ABS(C26-OIS_Curve!C26)<0.0001,TRUE(),FALSE()) -> TRUE | K26: =IF(ABS(D26-OIS_Curve!D26)<0.0001,TRUE(),FALSE()) -> TRUE | L26: =IF(ABS(E26-OIS_Curve!E26)<0.0001,TRUE(),FALSE()) -> TRUE | M26: =IF(ABS(F26-OIS_Curve!F26)<0.0001,TRUE(),FALSE()) -> TRUE
B27: 2.25 | C27: =$C$26+(($C$30-$C$26)/($B$30-$B$26))*(B27-$B$26) -> 0.036190614 | D27: =EXP(-B27*C27) -> 0.92179827 | E27: =-(LN(D28)-LN(D26))/(B28-B26) -> 0.035079175 | F27: =(D27/D28-1)/(B28-B27) -> 0.035108865 | I27: =IF(D27="","?",IF(ABS(D27-OIS_Curve!D27)<0.000001,"OK","CHECK")) -> OK | J27: =IF(ABS(C27-OIS_Curve!C27)<0.0001,TRUE(),FALSE()) -> TRUE | K27: =IF(ABS(D27-OIS_Curve!D27)<0.0001,TRUE(),FALSE()) -> TRUE | L27: =IF(ABS(E27-OIS_Curve!E27)<0.0001,TRUE(),FALSE()) -> TRUE | M27: =IF(ABS(F27-OIS_Curve!F27)<0.0001,TRUE(),FALSE()) -> TRUE
B28: 2.5 | C28: =$C$26+(($C$30-$C$26)/($B$30-$B$26))*(B28-$B$26) -> 0.03606712 | D28: =EXP(-B28*C28) -> 0.91377784 | E28: =-(LN(D29)-LN(D27))/(B29-B27) -> 0.034832189 | F28: =(D28/D29-1)/(B29-B28) -> 0.034859719 | I28: =IF(D28="","?",IF(ABS(D28-OIS_Curve!D28)<0.000001,"OK","CHECK")) -> OK | J28: =IF(ABS(C28-OIS_Curve!C28)<0.0001,TRUE(),FALSE()) -> TRUE | K28: =IF(ABS(D28-OIS_Curve!D28)<0.0001,TRUE(),FALSE()) -> TRUE | L28: =IF(ABS(E28-OIS_Curve!E28)<0.0001,TRUE(),FALSE()) -> TRUE | M28: =IF(ABS(F28-OIS_Curve!F28)<0.0001,TRUE(),FALSE()) -> TRUE
B29: 2.75 | C29: =$C$26+(($C$30-$C$26)/($B$30-$B$26))*(B29-$B$26) -> 0.035943627 | D29: =EXP(-B29*C29) -> 0.90588313 | E29: =-(LN(D30)-LN(D28))/(B30-B28) -> 0.034585202 | F29: =(D29/D30-1)/(B30-B29) -> 0.034610588 | I29: =IF(D29="","?",IF(ABS(D29-OIS_Curve!D29)<0.000001,"OK","CHECK")) -> OK | J29: =IF(ABS(C29-OIS_Curve!C29)<0.0001,TRUE(),FALSE()) -> TRUE | K29: =IF(ABS(D29-OIS_Curve!D29)<0.0001,TRUE(),FALSE()) -> TRUE | L29: =IF(ABS(E29-OIS_Curve!E29)<0.0001,TRUE(),FALSE()) -> TRUE | M29: =IF(ABS(F29-OIS_Curve!F29)<0.0001,TRUE(),FALSE()) -> TRUE
B30: 3 | C30: =VLOOKUP($B30,$B$4:$F$16,5,FALSE) -> 0.035820134 | D30: =VLOOKUP($B30,$B$4:$F$16,4,FALSE) -> 0.89811208 | E30: =-(LN(D31)-LN(D29))/(B31-B29) -> 0.035287063 | F30: =(D30/D31-1)/(B31-B30) -> 0.036275921 | I30: =IF(D30="","?",IF(ABS(D30-OIS_Curve!D30)<0.000001,"OK","CHECK")) -> OK | J30: =IF(ABS(C30-OIS_Curve!C30)<0.0001,TRUE(),FALSE()) -> TRUE | K30: =IF(ABS(D30-OIS_Curve!D30)<0.0001,TRUE(),FALSE()) -> TRUE | L30: =IF(ABS(E30-OIS_Curve!E30)<0.0001,TRUE(),FALSE()) -> TRUE | M30: =IF(ABS(F30-OIS_Curve!F30)<0.0001,TRUE(),FALSE()) -> TRUE
B31: 3.25 | C31: =C30+((C34-C30)/(B34-B30))*(B31-B30) -> 0.035842617 | D31: =EXP(-B31*C31) -> 0.89004033 | E31: =-(LN(D32)-LN(D30))/(B32-B30) -> 0.036134899 | F31: =(D31/D32-1)/(B32-B31) -> 0.036321296 | I31: =IF(D31="","?",IF(ABS(D31-OIS_Curve!D31)<0.000001,"OK","CHECK")) -> OK | J31: =IF(ABS(C31-OIS_Curve!C31)<0.0001,TRUE(),FALSE()) -> TRUE | K31: =IF(ABS(D31-OIS_Curve!D31)<0.0001,TRUE(),FALSE()) -> TRUE | L31: =IF(ABS(E31-OIS_Curve!E31)<0.0001,TRUE(),FALSE()) -> TRUE | M31: =IF(ABS(F31-OIS_Curve!F31)<0.0001,TRUE(),FALSE()) -> TRUE
B32: 3.5 | C32: =C30+((C34-C30)/(B34-B30))*(B32-B30) -> 0.035865101 | D32: =EXP(-B32*C32) -> 0.8820312 | E32: =-(LN(D33)-LN(D31))/(B33-B31) -> 0.036179866 | F32: =(D32/D33-1)/(B33-B32) -> 0.036366671 | I32: =IF(D32="","?",IF(ABS(D32-OIS_Curve!D32)<0.000001,"OK","CHECK")) -> OK | J32: =IF(ABS(C32-OIS_Curve!C32)<0.0001,TRUE(),FALSE()) -> TRUE | K32: =IF(ABS(D32-OIS_Curve!D32)<0.0001,TRUE(),FALSE()) -> TRUE | L32: =IF(ABS(E32-OIS_Curve!E32)<0.0001,TRUE(),FALSE()) -> TRUE | M32: =IF(ABS(F32-OIS_Curve!F32)<0.0001,TRUE(),FALSE()) -> TRUE
B33: 3.75 | C33: =C30+((C34-C30)/(B34-B30))*(B33-B30) -> 0.035887584 | D33: =EXP(-B33*C33) -> 0.87408431 | E33: =-(LN(D34)-LN(D32))/(B34-B32) -> 0.036224832 | F33: =(D33/D34-1)/(B34-B33) -> 0.036412046 | I33: =IF(D33="","?",IF(ABS(D33-OIS_Curve!D33)<0.000001,"OK","CHECK")) -> OK | J33: =IF(ABS(C33-OIS_Curve!C33)<0.0001,TRUE(),FALSE()) -> TRUE | K33: =IF(ABS(D33-OIS_Curve!D33)<0.0001,TRUE(),FALSE()) -> TRUE | L33: =IF(ABS(E33-OIS_Curve!E33)<0.0001,TRUE(),FALSE()) -> TRUE | M33: =IF(ABS(F33-OIS_Curve!F33)<0.0001,TRUE(),FALSE()) -> TRUE
B34: 4 | C34: =VLOOKUP($B34,$B$4:$F$16,5,FALSE) -> 0.035910067 | D34: =VLOOKUP($B34,$B$4:$F$16,4,FALSE) -> 0.86619929 | E34: =-(LN(D35)-LN(D33))/(B35-B33) -> 0.034806428 | F34: =(D34/D35-1)/(B35-B34) -> 0.033505085 | I34: =IF(D34="","?",IF(ABS(D34-OIS_Curve!D34)<0.000001,"OK","CHECK")) -> OK | J34: =IF(ABS(C34-OIS_Curve!C34)<0.0001,TRUE(),FALSE()) -> TRUE | K34: =IF(ABS(D34-OIS_Curve!D34)<0.0001,TRUE(),FALSE()) -> TRUE | L34: =IF(ABS(E34-OIS_Curve!E34)<0.0001,TRUE(),FALSE()) -> TRUE | M34: =IF(ABS(F34-OIS_Curve!F34)<0.0001,TRUE(),FALSE()) -> TRUE
B35: 4.25 | C35: =C34+((C38-C34)/(B38-B34))*(B35-B34) -> 0.035760389 | D35: =EXP(-B35*C35) -> 0.85900404 | E35: =-(LN(D36)-LN(D34))/(B36-B34) -> 0.033215862 | F35: =(D35/D36-1)/(B36-B35) -> 0.033203233 | I35: =IF(D35="","?",IF(ABS(D35-OIS_Curve!D35)<0.000001,"OK","CHECK")) -> OK | J35: =IF(ABS(C35-OIS_Curve!C35)<0.0001,TRUE(),FALSE()) -> TRUE | K35: =IF(ABS(D35-OIS_Curve!D35)<0.0001,TRUE(),FALSE()) -> TRUE | L35: =IF(ABS(E35-OIS_Curve!E35)<0.0001,TRUE(),FALSE()) -> TRUE | M35: =IF(ABS(F35-OIS_Curve!F35)<0.0001,TRUE(),FALSE()) -> TRUE
B36: 4.5 | C36: =C34+((C38-C34)/(B38-B34))*(B36-B34) -> 0.035610711 | D36: =EXP(-B36*C36) -> 0.85193231 | E36: =-(LN(D37)-LN(D35))/(B37-B35) -> 0.032916506 | F36: =(D36/D37-1)/(B37-B36) -> 0.032901403 | I36: =IF(D36="","?",IF(ABS(D36-OIS_Curve!D36)<0.000001,"OK","CHECK")) -> OK | J36: =IF(ABS(C36-OIS_Curve!C36)<0.0001,TRUE(),FALSE()) -> TRUE | K36: =IF(ABS(D36-OIS_Curve!D36)<0.0001,TRUE(),FALSE()) -> TRUE | L36: =IF(ABS(E36-OIS_Curve!E36)<0.0001,TRUE(),FALSE()) -> TRUE | M36: =IF(ABS(F36-OIS_Curve!F36)<0.0001,TRUE(),FALSE()) -> TRUE
B37: 4.75 | C37: =C34+((C38-C34)/(B38-B34))*(B37-B34) -> 0.035461033 | D37: =EXP(-B37*C37) -> 0.84498204 | E37: =-(LN(D38)-LN(D36))/(B38-B36) -> 0.03261715 | F37: =(D37/D38-1)/(B38-B37) -> 0.032599596 | I37: =IF(D37="","?",IF(ABS(D37-OIS_Curve!D37)<0.000001,"OK","CHECK")) -> OK | J37: =IF(ABS(C37-OIS_Curve!C37)<0.0001,TRUE(),FALSE()) -> TRUE | K37: =IF(ABS(D37-OIS_Curve!D37)<0.0001,TRUE(),FALSE()) -> TRUE | L37: =IF(ABS(E37-OIS_Curve!E37)<0.0001,TRUE(),FALSE()) -> TRUE | M37: =IF(ABS(F37-OIS_Curve!F37)<0.0001,TRUE(),FALSE()) -> TRUE
B38: 5 | C38: =VLOOKUP($B38,$B$4:$F$16,5,FALSE) -> 0.035311355 | D38: =VLOOKUP($B38,$B$4:$F$16,4,FALSE) -> 0.83815119 | E38: =-(LN(D39)-LN(D37))/(B39-B37) -> 0.03453076 | F38: =(D38/D39-1)/(B39-B38) -> 0.036761951 | I38: =IF(D38="","?",IF(ABS(D38-OIS_Curve!D38)<0.000001,"OK","CHECK")) -> OK | J38: =IF(ABS(C38-OIS_Curve!C38)<0.0001,TRUE(),FALSE()) -> TRUE | K38: =IF(ABS(D38-OIS_Curve!D38)<0.0001,TRUE(),FALSE()) -> TRUE | L38: =IF(ABS(E38-OIS_Curve!E38)<0.0001,TRUE(),FALSE()) -> TRUE | M38: =IF(ABS(F38-OIS_Curve!F38)<0.0001,TRUE(),FALSE()) -> TRUE
B39: 5.25 | C39: =C38+((C42-C38)/(B42-B38))*(B39-B38) -> 0.035372436 | D39: =EXP(-B39*C39) -> 0.83051832 | E39: =-(LN(D40)-LN(D38))/(B40-B38) -> 0.036655129 | F39: =(D39/D40-1)/(B40-B39) -> 0.036885236 | I39: =IF(D39="","?",IF(ABS(D39-OIS_Curve!D39)<0.000001,"OK","CHECK")) -> OK | J39: =IF(ABS(C39-OIS_Curve!C39)<0.0001,TRUE(),FALSE()) -> TRUE | K39: =IF(ABS(D39-OIS_Curve!D39)<0.0001,TRUE(),FALSE()) -> TRUE | L39: =IF(ABS(E39-OIS_Curve!E39)<0.0001,TRUE(),FALSE()) -> TRUE | M39: =IF(ABS(F39-OIS_Curve!F39)<0.0001,TRUE(),FALSE()) -> TRUE
B40: 5.5 | C40: =C38+((C42-C38)/(B42-B38))*(B40-B38) -> 0.035433516 | D40: =EXP(-B40*C40) -> 0.82292983 | E40: =-(LN(D41)-LN(D39))/(B41-B39) -> 0.03677729 | F40: =(D40/D41-1)/(B41-B40) -> 0.037008526 | I40: =IF(D40="","?",IF(ABS(D40-OIS_Curve!D40)<0.000001,"OK","CHECK")) -> OK | J40: =IF(ABS(C40-OIS_Curve!C40)<0.0001,TRUE(),FALSE()) -> TRUE | K40: =IF(ABS(D40-OIS_Curve!D40)<0.0001,TRUE(),FALSE()) -> TRUE | L40: =IF(ABS(E40-OIS_Curve!E40)<0.0001,TRUE(),FALSE()) -> TRUE | M40: =IF(ABS(F40-OIS_Curve!F40)<0.0001,TRUE(),FALSE()) -> TRUE
B41: 5.75 | C41: =C38+((C42-C38)/(B42-B38))*(B41-B38) -> 0.035494597 | D41: =EXP(-B41*C41) -> 0.81538578 | E41: =-(LN(D42)-LN(D40))/(B42-B40) -> 0.036899452 | F41: =(D41/D42-1)/(B42-B41) -> 0.037131819 | I41: =IF(D41="","?",IF(ABS(D41-OIS_Curve!D41)<0.000001,"OK","CHECK")) -> OK | J41: =IF(ABS(C41-OIS_Curve!C41)<0.0001,TRUE(),FALSE()) -> TRUE | K41: =IF(ABS(D41-OIS_Curve!D41)<0.0001,TRUE(),FALSE()) -> TRUE | L41: =IF(ABS(E41-OIS_Curve!E41)<0.0001,TRUE(),FALSE()) -> TRUE | M41: =IF(ABS(F41-OIS_Curve!F41)<0.0001,TRUE(),FALSE()) -> TRUE
B42: 6 | C42: =VLOOKUP($B42,$B$4:$F$16,5,FALSE) -> 0.035555677 | D42: =VLOOKUP($B42,$B$4:$F$16,4,FALSE) -> 0.80788621 | E42: =-(LN(D43)-LN(D41))/(B43-B41) -> 0.034850658 | F42: =(D42/D43-1)/(B43-B42) -> 0.032875146 | I42: =IF(D42="","?",IF(ABS(D42-OIS_Curve!D42)<0.000001,"OK","CHECK")) -> OK | J42: =IF(ABS(C42-OIS_Curve!C42)<0.0001,TRUE(),FALSE()) -> TRUE | K42: =IF(ABS(D42-OIS_Curve!D42)<0.0001,TRUE(),FALSE()) -> TRUE | L42: =IF(ABS(E42-OIS_Curve!E42)<0.0001,TRUE(),FALSE()) -> TRUE | M42: =IF(ABS(F42-OIS_Curve!F42)<0.0001,TRUE(),FALSE()) -> TRUE
B43: 6.25 | C43: =C42+((C46-C42)/(B46-B42))*(B43-B42) -> 0.035443082 | D43: =EXP(-B43*C43) -> 0.80130049 | E43: =-(LN(D44)-LN(D42))/(B44-B42) -> 0.032628189 | F43: =(D43/D44-1)/(B44-B43) -> 0.03264811 | I43: =IF(D43="","?",IF(ABS(D43-OIS_Curve!D43)<0.000001,"OK","CHECK")) -> OK | J43: =IF(ABS(C43-OIS_Curve!C43)<0.0001,TRUE(),FALSE()) -> TRUE | K43: =IF(ABS(D43-OIS_Curve!D43)<0.0001,TRUE(),FALSE()) -> TRUE | L43: =IF(ABS(E43-OIS_Curve!E43)<0.0001,TRUE(),FALSE()) -> TRUE | M43: =IF(ABS(F43-OIS_Curve!F43)<0.0001,TRUE(),FALSE()) -> TRUE
B44: 6.5 | C44: =C42+((C46-C42)/(B46-B42))*(B44-B42) -> 0.035330486 | D44: =EXP(-B44*C44) -> 0.7948132 | E44: =-(LN(D45)-LN(D43))/(B45-B43) -> 0.032402997 | F44: =(D44/D45-1)/(B45-B44) -> 0.032421087 | I44: =IF(D44="","?",IF(ABS(D44-OIS_Curve!D44)<0.000001,"OK","CHECK")) -> OK | J44: =IF(ABS(C44-OIS_Curve!C44)<0.0001,TRUE(),FALSE()) -> TRUE | K44: =IF(ABS(D44-OIS_Curve!D44)<0.0001,TRUE(),FALSE()) -> TRUE | L44: =IF(ABS(E44-OIS_Curve!E44)<0.0001,TRUE(),FALSE()) -> TRUE | M44: =IF(ABS(F44-OIS_Curve!F44)<0.0001,TRUE(),FALSE()) -> TRUE
B45: 6.75 | C45: =C42+((C46-C42)/(B46-B42))*(B45-B42) -> 0.03521789 | D45: =EXP(-B45*C45) -> 0.78842282 | E45: =-(LN(D46)-LN(D44))/(B46-B44) -> 0.032177806 | F45: =(D45/D46-1)/(B46-B45) -> 0.032194076 | I45: =IF(D45="","?",IF(ABS(D45-OIS_Curve!D45)<0.000001,"OK","CHECK")) -> OK | J45: =IF(ABS(C45-OIS_Curve!C45)<0.0001,TRUE(),FALSE()) -> TRUE | K45: =IF(ABS(D45-OIS_Curve!D45)<0.0001,TRUE(),FALSE()) -> TRUE | L45: =IF(ABS(E45-OIS_Curve!E45)<0.0001,TRUE(),FALSE()) -> TRUE | M45: =IF(ABS(F45-OIS_Curve!F45)<0.0001,TRUE(),FALSE()) -> TRUE
B46: 7 | C46: =VLOOKUP($B46,$B$4:$F$16,5,FALSE) -> 0.035105295 | D46: =VLOOKUP($B46,$B$4:$F$16,4,FALSE) -> 0.78212785 | E46: =-(LN(D47)-LN(D45))/(B47-B45) -> 0.034062188 | F46: =(D46/D47-1)/(B47-B46) -> 0.036222189 | I46: =IF(D46="","?",IF(ABS(D46-OIS_Curve!D46)<0.000001,"OK","CHECK")) -> OK | J46: =IF(ABS(C46-OIS_Curve!C46)<0.0001,TRUE(),FALSE()) -> TRUE | K46: =IF(ABS(D46-OIS_Curve!D46)<0.0001,TRUE(),FALSE()) -> TRUE | L46: =IF(ABS(E46-OIS_Curve!E46)<0.0001,TRUE(),FALSE()) -> TRUE | M46: =IF(ABS(F46-OIS_Curve!F46)<0.0001,TRUE(),FALSE()) -> TRUE
B47: 7.25 | C47: =C46+((C50-C46)/(B50-B46))*(B47-B46) -> 0.035138187 | D47: =EXP(-B47*C47) -> 0.77510881 | E47: =-(LN(D48)-LN(D46))/(B48-B46) -> 0.036092058 | F47: =(D47/D48-1)/(B48-B47) -> 0.036288569 | I47: =IF(D47="","?",IF(ABS(D47-OIS_Curve!D47)<0.000001,"OK","CHECK")) -> OK | J47: =IF(ABS(C47-OIS_Curve!C47)<0.0001,TRUE(),FALSE()) -> TRUE | K47: =IF(ABS(D47-OIS_Curve!D47)<0.0001,TRUE(),FALSE()) -> TRUE | L47: =IF(ABS(E47-OIS_Curve!E47)<0.0001,TRUE(),FALSE()) -> TRUE | M47: =IF(ABS(F47-OIS_Curve!F47)<0.0001,TRUE(),FALSE()) -> TRUE
B48: 7.5 | C48: =C46+((C50-C46)/(B50-B46))*(B48-B46) -> 0.035171079 | D48: =EXP(-B48*C48) -> 0.76814014 | E48: =-(LN(D49)-LN(D47))/(B49-B47) -> 0.036157842 | F48: =(D48/D49-1)/(B49-B48) -> 0.036354951 | I48: =IF(D48="","?",IF(ABS(D48-OIS_Curve!D48)<0.000001,"OK","CHECK")) -> OK | J48: =IF(ABS(C48-OIS_Curve!C48)<0.0001,TRUE(),FALSE()) -> TRUE | K48: =IF(ABS(D48-OIS_Curve!D48)<0.0001,TRUE(),FALSE()) -> TRUE | L48: =IF(ABS(E48-OIS_Curve!E48)<0.0001,TRUE(),FALSE()) -> TRUE | M48: =IF(ABS(F48-OIS_Curve!F48)<0.0001,TRUE(),FALSE()) -> TRUE
B49: 7.75 | C49: =C46+((C50-C46)/(B50-B46))*(B49-B46) -> 0.035203971 | D49: =EXP(-B49*C49) -> 0.76122159 | E49: =-(LN(D50)-LN(D48))/(B50-B48) -> 0.036223627 | F49: =(D49/D50-1)/(B50-B49) -> 0.036421333 | I49: =IF(D49="","?",IF(ABS(D49-OIS_Curve!D49)<0.000001,"OK","CHECK")) -> OK | J49: =IF(ABS(C49-OIS_Curve!C49)<0.0001,TRUE(),FALSE()) -> TRUE | K49: =IF(ABS(D49-OIS_Curve!D49)<0.0001,TRUE(),FALSE()) -> TRUE | L49: =IF(ABS(E49-OIS_Curve!E49)<0.0001,TRUE(),FALSE()) -> TRUE | M49: =IF(ABS(F49-OIS_Curve!F49)<0.0001,TRUE(),FALSE()) -> TRUE
B50: 8 | C50: =VLOOKUP($B50,$B$4:$F$16,5,FALSE) -> 0.035236863 | D50: =VLOOKUP($B50,$B$4:$F$16,4,FALSE) -> 0.75435296 | E50: =-(LN(D51)-LN(D49))/(B51-B49) -> 0.036289411 | F50: =(D50/D51-1)/(B51-B50) -> 0.036487717 | I50: =IF(D50="","?",IF(ABS(D50-OIS_Curve!D50)<0.000001,"OK","CHECK")) -> OK | J50: =IF(ABS(C50-OIS_Curve!C50)<0.0001,TRUE(),FALSE()) -> TRUE | K50: =IF(ABS(D50-OIS_Curve!D50)<0.0001,TRUE(),FALSE()) -> TRUE | L50: =IF(ABS(E50-OIS_Curve!E50)<0.0001,TRUE(),FALSE()) -> TRUE | M50: =IF(ABS(F50-OIS_Curve!F50)<0.0001,TRUE(),FALSE()) -> TRUE
B51: 8.25 | C51: =C50+((C54-C50)/(B54-B50))*(B51-B50) -> 0.035269755 | D51: =EXP(-B51*C51) -> 0.74753401 | E51: =-(LN(D52)-LN(D50))/(B52-B50) -> 0.036355195 | F51: =(D51/D52-1)/(B52-B51) -> 0.036554102 | I51: =IF(D51="","?",IF(ABS(D51-OIS_Curve!D51)<0.000001,"OK","CHECK")) -> OK | J51: =IF(ABS(C51-OIS_Curve!C51)<0.0001,TRUE(),FALSE()) -> TRUE | K51: =IF(ABS(D51-OIS_Curve!D51)<0.0001,TRUE(),FALSE()) -> TRUE | L51: =IF(ABS(E51-OIS_Curve!E51)<0.0001,TRUE(),FALSE()) -> TRUE | M51: =IF(ABS(F51-OIS_Curve!F51)<0.0001,TRUE(),FALSE()) -> TRUE
B52: 8.5 | C52: =C50+((C54-C50)/(B54-B50))*(B52-B50) -> 0.035302647 | D52: =EXP(-B52*C52) -> 0.74076451 | E52: =-(LN(D53)-LN(D51))/(B53-B51) -> 0.036420979 | F52: =(D52/D53-1)/(B53-B52) -> 0.036620488 | I52: =IF(D52="","?",IF(ABS(D52-OIS_Curve!D52)<0.000001,"OK","CHECK")) -> OK | J52: =IF(ABS(C52-OIS_Curve!C52)<0.0001,TRUE(),FALSE()) -> TRUE | K52: =IF(ABS(D52-OIS_Curve!D52)<0.0001,TRUE(),FALSE()) -> TRUE | L52: =IF(ABS(E52-OIS_Curve!E52)<0.0001,TRUE(),FALSE()) -> TRUE | M52: =IF(ABS(F52-OIS_Curve!F52)<0.0001,TRUE(),FALSE()) -> TRUE
B53: 8.75 | C53: =C50+((C54-C50)/(B54-B50))*(B53-B50) -> 0.035335539 | D53: =EXP(-B53*C53) -> 0.73404425 | E53: =-(LN(D54)-LN(D52))/(B54-B52) -> 0.036486764 | F53: =(D53/D54-1)/(B54-B53) -> 0.036686875 | I53: =IF(D53="","?",IF(ABS(D53-OIS_Curve!D53)<0.000001,"OK","CHECK")) -> OK | J53: =IF(ABS(C53-OIS_Curve!C53)<0.0001,TRUE(),FALSE()) -> TRUE | K53: =IF(ABS(D53-OIS_Curve!D53)<0.0001,TRUE(),FALSE()) -> TRUE | L53: =IF(ABS(E53-OIS_Curve!E53)<0.0001,TRUE(),FALSE()) -> TRUE | M53: =IF(ABS(F53-OIS_Curve!F53)<0.0001,TRUE(),FALSE()) -> TRUE
B54: 9 | C54: =VLOOKUP($B54,$B$4:$F$16,5,FALSE) -> 0.035368432 | D54: =VLOOKUP($B54,$B$4:$F$16,4,FALSE) -> 0.72737299 | E54: =-(LN(D55)-LN(D53))/(B55-B53) -> 0.033196816 | F54: =(D54/D55-1)/(B55-B54) -> 0.029985812 | I54: =IF(D54="","?",IF(ABS(D54-OIS_Curve!D54)<0.000001,"OK","CHECK")) -> OK | J54: =IF(ABS(C54-OIS_Curve!C54)<0.0001,TRUE(),FALSE()) -> TRUE | K54: =IF(ABS(D54-OIS_Curve!D54)<0.0001,TRUE(),FALSE()) -> TRUE | L54: =IF(ABS(E54-OIS_Curve!E54)<0.0001,TRUE(),FALSE()) -> TRUE | M54: =IF(ABS(F54-OIS_Curve!F54)<0.0001,TRUE(),FALSE()) -> TRUE
B55: 9.25 | C55: =C54+((C58-C54)/(B58-B54))*(B55-B54) -> 0.035219933 | D55: =EXP(-B55*C55) -> 0.72196084 | E55: =-(LN(D56)-LN(D54))/(B56-B54) -> 0.029725478 | F55: =(D55/D56-1)/(B56-B55) -> 0.029686599 | I55: =IF(D55="","?",IF(ABS(D55-OIS_Curve!D55)<0.000001,"OK","CHECK")) -> OK | J55: =IF(ABS(C55-OIS_Curve!C55)<0.0001,TRUE(),FALSE()) -> TRUE | K55: =IF(ABS(D55-OIS_Curve!D55)<0.0001,TRUE(),FALSE()) -> TRUE | L55: =IF(ABS(E55-OIS_Curve!E55)<0.0001,TRUE(),FALSE()) -> TRUE | M55: =IF(ABS(F55-OIS_Curve!F55)<0.0001,TRUE(),FALSE()) -> TRUE
B56: 9.5 | C56: =C54+((C58-C54)/(B58-B54))*(B56-B54) -> 0.035071434 | D56: =EXP(-B56*C56) -> 0.71664217 | E56: =-(LN(D57)-LN(D55))/(B57-B55) -> 0.02942848 | F56: =(D56/D57-1)/(B57-B56) -> 0.029387408 | I56: =IF(D56="","?",IF(ABS(D56-OIS_Curve!D56)<0.000001,"OK","CHECK")) -> OK | J56: =IF(ABS(C56-OIS_Curve!C56)<0.0001,TRUE(),FALSE()) -> TRUE | K56: =IF(ABS(D56-OIS_Curve!D56)<0.0001,TRUE(),FALSE()) -> TRUE | L56: =IF(ABS(E56-OIS_Curve!E56)<0.0001,TRUE(),FALSE()) -> TRUE | M56: =IF(ABS(F56-OIS_Curve!F56)<0.0001,TRUE(),FALSE()) -> TRUE
B57: 9.75 | C57: =C54+((C58-C54)/(B58-B54))*(B57-B54) -> 0.034922935 | D57: =EXP(-B57*C57) -> 0.71141551 | E57: =-(LN(D58)-LN(D56))/(B58-B56) -> 0.029131483 | F57: =(D57/D58-1)/(B58-B57) -> 0.02908824 | I57: =IF(D57="","?",IF(ABS(D57-OIS_Curve!D57)<0.000001,"OK","CHECK")) -> OK | J57: =IF(ABS(C57-OIS_Curve!C57)<0.0001,TRUE(),FALSE()) -> TRUE | K57: =IF(ABS(D57-OIS_Curve!D57)<0.0001,TRUE(),FALSE()) -> TRUE | L57: =IF(ABS(E57-OIS_Curve!E57)<0.0001,TRUE(),FALSE()) -> TRUE | M57: =IF(ABS(F57-OIS_Curve!F57)<0.0001,TRUE(),FALSE()) -> TRUE
B58: 10 | C58: =VLOOKUP($B58,$B$4:$F$16,5,FALSE) -> 0.034774436 | D58: =VLOOKUP($B58,$B$4:$F$16,4,FALSE) -> 0.7062794 | E58: =-(LN(D58)-LN(D57))/(B58-B57) -> 0.028982984 | I58: =IF(D58="","?",IF(ABS(D58-OIS_Curve!D58)<0.000001,"OK","CHECK")) -> OK | J58: =IF(ABS(C58-OIS_Curve!C58)<0.0001,TRUE(),FALSE()) -> TRUE | K58: =IF(ABS(D58-OIS_Curve!D58)<0.0001,TRUE(),FALSE()) -> TRUE | L58: =IF(ABS(E58-OIS_Curve!E58)<0.0001,TRUE(),FALSE()) -> TRUE

Sheet TRY_Proj
B1: PRACTICE: Projection Curve · Yellow cells = YOUR TURN · Check col shows OK/CHECK
B3: SECTION 1 — SOFR FUTURES (Implied 3M Forward Rate per Quarterly Period) | H3: Check vs Solution
B4: Contract | C4: T_start | D4: T_end | E4: Implied 3M Fwd | F4: Note | H4: DF
B5: Sep25 | C5: 0 | D5: 0.25 | E5: =Instruments!$E$19 -> 0.044 | F5: 3M SOFR forward for Sep25 — directly observed from futures market | H5: =VLOOKUP(D5,TRY_OIS!$B$18:$D$58,3,FALSE) -> 0.98973154 | I5: =E5*H5 -> 0.043548188
B6: Dec25 | C6: 0.25 | D6: 0.5 | E6: =Instruments!$E$20 -> 0.0425 | F6: 3M SOFR forward for Dec25 — directly observed from futures market | H6: =VLOOKUP(D6,TRY_OIS!$B$18:$D$58,3,FALSE) -> 0.98039216 | I6: =E6*H6 -> 0.041666667
B7: Mar26 | C7: 0.5 | D7: 0.75 | E7: =Instruments!$E$21 -> 0.0408 | F7: 3M SOFR forward for Mar26 — directly observed from futures market | H7: =VLOOKUP(D7,TRY_OIS!$B$18:$D$58,3,FALSE) -> 0.97157395 | I7: =E7*H7 -> 0.039640217
B8: Jun26 | C8: 0.75 | D8: 1 | E8: =Instruments!$E$22 -> 0.0392 | F8: 3M SOFR forward for Jun26 — directly observed from futures market | H8: =VLOOKUP(D8,TRY_OIS!$B$18:$D$58,3,FALSE) -> 0.96339114 | I8: =E8*H8 -> 0.037764933
B9: Sep26 | C9: 1 | D9: 1.25 | E9: =Instruments!$E$23 -> 0.0382 | F9: 3M SOFR forward for Sep26 — directly observed from futures market | H9: =VLOOKUP(D9,TRY_OIS!$B$18:$D$58,3,FALSE) -> 0.95474312 | I9: =E9*H9 -> 0.036471187
B10: Dec26 | C10: 1.25 | D10: 1.5 | E10: =Instruments!$E$24 -> 0.0376 | F10: 3M SOFR forward for Dec26 — directly observed from futures market | H10: =VLOOKUP(D10,TRY_OIS!$B$18:$D$58,3,FALSE) -> 0.94628885 | I10: =E10*H10 -> 0.035580461
B11: Mar27 | C11: 1.5 | D11: 1.75 | E11: =Instruments!$E$25 -> 0.0372 | F11: 3M SOFR forward for Mar27 — directly observed from futures market | H11: =VLOOKUP(D11,TRY_OIS!$B$18:$D$58,3,FALSE) -> 0.93802454 | I11: =E11*H11 -> 0.034894513
B12: Jun27 | C12: 1.75 | D12: 2 | E12: =Instruments!$E$26 -> 0.037 | F12: 3M SOFR forward for Jun27 — directly observed from futures market | H12: =VLOOKUP(D12,TRY_OIS!$B$18:$D$58,3,FALSE) -> 0.92994651 | I12: =E12*H12 -> 0.034408021 | J12: =SUM(I5:I12) -> 0.30397419
B14: SECTION 2 — IRS BOOTSTRAP (Flat Forward per Band, bootstrapped from 3M SOFR IRS)
B15: IRS Mat | C15: Par Rate | D15: Band | E15: Flat Fwd (bootstrapped) | F15: Bootstrap Formula
B16: 3 | C16: =Instruments!$D$30 -> 0.0367 | D16: 2Y-3Y | E16: 0.030563284 | F16: Flat Fwd = (K·Ann(3Y) - PV_Float(0-2Y)) / Ann(2Y-3Y) where Ann=δ·ΣP_OIS(Ti), PV_Float=δ·ΣF_i·P_OIS(Ti) | J16: =(C16*SUM(TRY_OIS!D19:D30)-J12)/(SUM(TRY_OIS!D27:D30)) -> 0.030563284 | K16: =E16=J16 -> TRUE
B17: 5 | C17: =Instruments!$D$31 -> 0.0364 | D17: 3Y-5Y | E17: 0.035908895 | F17: Flat Fwd = (K·Ann(5Y) - PV_Float(0-3Y)) / Ann(3Y-5Y) where Ann=δ·ΣP_OIS(Ti), PV_Float=δ·ΣF_i·P_OIS(Ti) | J17: =(C17*SUM(TRY_OIS!D19:D38)-J12-E16*SUM(TRY_OIS!D27:D30))/SUM(TRY_OIS!D31:D38) -> 0.035908559 | K17: =IF(ABS(E17-J17)<0.00001,TRUE(),FALSE()) -> TRUE
B18: 7 | C18: =Instruments!$D$32 -> 0.0362 | D18: 5Y-7Y | E18: 0.035634867 | F18: Flat Fwd = (K·Ann(7Y) - PV_Float(0-5Y)) / Ann(5Y-7Y) where Ann=δ·ΣP_OIS(Ti), PV_Float=δ·ΣF_i·P_OIS(Ti) | J18: =(C18*SUM(TRY_OIS!D19:D46)-J12-E16*SUM(TRY_OIS!D27:D30)-E17*SUM(TRY_OIS!D31:D38))/SUM(TRY_OIS!D39:D46) -> 0.035634096 | K18: =IF(ABS(E18-J18)<0.00001,TRUE(),FALSE()) -> TRUE
B19: 10 | C19: =Instruments!$D$33 -> 0.0359 | D19: 7Y-10Y | E19: 0.035066571 | F19: Flat Fwd = (K·Ann(10Y) - PV_Float(0-7Y)) / Ann(7Y-10Y) where Ann=δ·ΣP_OIS(Ti), PV_Float=δ·ΣF_i·P_OIS(Ti) | J19: =(C19*SUM(TRY_OIS!D19:D58)-J12-E16*SUM(TRY_OIS!D27:D30)-E17*SUM(TRY_OIS!D31:D38)-E18*SUM(TRY_OIS!D39:D46))/SUM(TRY_OIS!D47:D58) -> 0.035064789 | K19: =IF(ABS(E19-J19)<0.00001,TRUE(),FALSE()) -> TRUE
B21: SECTION 3 — QUARTERLY PROJECTION GRID (40 periods: T_start 0 to 9.75)
B22: T_start | C22: T_end | D22: 3M Forward Rate | E22: Proj DF at T_end | F22: Note
B23: 0 | C23: 0.25 | D23: =E5 -> 0.044 | E23: =1/(1+0.25*D23) -> 0.98911968 | F23: Proj DF(T_end)=Proj DF(T_start)/(1+Fwd·δ) where Proj DF(0)=1 | H23: =IF(E23="","?",IF(ABS(E23-Proj_Curve!E23)<0.000001,"OK","CHECK")) -> OK
B24: 0.25 | C24: 0.5 | D24: =E6 -> 0.0425 | E24: =E23/(1+D24*0.25) -> 0.97872078 | F24: Proj DF(T_end)=Proj DF(T_start)/(1+Fwd·δ) where Proj DF(0)=1 | H24: =IF(E24="","?",IF(ABS(E24-Proj_Curve!E24)<0.000001,"OK","CHECK")) -> OK
B25: 0.5 | C25: 0.75 | D25: =E7 -> 0.0408 | E25: =E24/(1+D25*0.25) -> 0.96883862 | H25: =IF(E25="","?",IF(ABS(E25-Proj_Curve!E25)<0.000001,"OK","CHECK")) -> OK
B26: 0.75 | C26: 1 | D26: =E8 -> 0.0392 | E26: =E25/(1+D26*0.25) -> 0.95943615 | H26: =IF(E26="","?",IF(ABS(E26-Proj_Curve!E26)<0.000001,"OK","CHECK")) -> OK
B27: 1 | C27: 1.25 | D27: =E9 -> 0.0382 | E27: =E26/(1+D27*0.25) -> 0.95036021 | H27: =IF(E27="","?",IF(ABS(E27-Proj_Curve!E27)<0.000001,"OK","CHECK")) -> OK
B28: 1.25 | C28: 1.5 | D28: =E10 -> 0.0376 | E28: =E27/(1+D28*0.25) -> 0.94151001 | H28: =IF(E28="","?",IF(ABS(E28-Proj_Curve!E28)<0.000001,"OK","CHECK")) -> OK
B29: 1.5 | C29: 1.75 | D29: =E11 -> 0.0372 | E29: =E28/(1+D29*0.25) -> 0.93283465 | H29: =IF(E29="","?",IF(ABS(E29-Proj_Curve!E29)<0.000001,"OK","CHECK")) -> OK
B30: 1.75 | C30: 2 | D30: =E12 -> 0.037 | E30: =E29/(1+D30*0.25) -> 0.92428501 | H30: =IF(E30="","?",IF(ABS(E30-Proj_Curve!E30)<0.000001,"OK","CHECK")) -> OK
B31: 2 | C31: 2.25 | D31: =E16 -> 0.030563284 | E31: =E30/(1+D31*0.25) -> 0.91727627 | H31: =IF(E31="","?",IF(ABS(E31-Proj_Curve!E31)<0.000001,"OK","CHECK")) -> OK
B32: 2.25 | C32: 2.5 | D32: =D31 -> 0.030563284 | E32: =E31/(1+D32*0.25) -> 0.91032067 | H32: =IF(E32="","?",IF(ABS(E32-Proj_Curve!E32)<0.000001,"OK","CHECK")) -> OK
B33: 2.5 | C33: 2.75 | D33: =D32 -> 0.030563284 | E33: =E32/(1+D33*0.25) -> 0.90341782 | H33: =IF(E33="","?",IF(ABS(E33-Proj_Curve!E33)<0.000001,"OK","CHECK")) -> OK
B34: 2.75 | C34: 3 | D34: =D33 -> 0.030563284 | E34: =E33/(1+D34*0.25) -> 0.89656731 | H34: =IF(E34="","?",IF(ABS(E34-Proj_Curve!E34)<0.000001,"OK","CHECK")) -> OK
B35: 3 | C35: 3.25 | D35: =E17 -> 0.035908895 | E35: =E34/(1+D35*0.25) -> 0.88859024 | H35: =IF(E35="","?",IF(ABS(E35-Proj_Curve!E35)<0.000001,"OK","CHECK")) -> OK
B36: 3.25 | C36: 3.5 | D36: =D35 -> 0.035908895 | E36: =E35/(1+D36*0.25) -> 0.88068414 | H36: =IF(E36="","?",IF(ABS(E36-Proj_Curve!E36)<0.000001,"OK","CHECK")) -> OK
B37: 3.5 | C37: 3.75 | D37: =D36 -> 0.035908895 | E37: =E36/(1+D37*0.25) -> 0.87284838 | H37: =IF(E37="","?",IF(ABS(E37-Proj_Curve!E37)<0.000001,"OK","CHECK")) -> OK
B38: 3.75 | C38: 4 | D38: =D37 -> 0.035908895 | E38: =E37/(1+D38*0.25) -> 0.86508234 | H38: =IF(E38="","?",IF(ABS(E38-Proj_Curve!E38)<0.000001,"OK","CHECK")) -> OK
B39: 4 | C39: 4.25 | D39: =D38 -> 0.035908895 | E39: =E38/(1+D39*0.25) -> 0.8573854 | H39: =IF(E39="","?",IF(ABS(E39-Proj_Curve!E39)<0.000001,"OK","CHECK")) -> OK
B40: 4.25 | C40: 4.5 | D40: =D39 -> 0.035908895 | E40: =E39/(1+D40*0.25) -> 0.84975695 | H40: =IF(E40="","?",IF(ABS(E40-Proj_Curve!E40)<0.000001,"OK","CHECK")) -> OK
B41: 4.5 | C41: 4.75 | D41: =D40 -> 0.035908895 | E41: =E40/(1+D41*0.25) -> 0.84219636 | H41: =IF(E41="","?",IF(ABS(E41-Proj_Curve!E41)<0.000001,"OK","CHECK")) -> OK
B42: 4.75 | C42: 5 | D42: =D41 -> 0.035908895 | E42: =E41/(1+D42*0.25) -> 0.83470304 | H42: =IF(E42="","?",IF(ABS(E42-Proj_Curve!E42)<0.000001,"OK","CHECK")) -> OK
B43: 5 | C43: 5.25 | D43: =E18 -> 0.035634867 | E43: =E42/(1+D43*0.25) -> 0.82733257 | H43: =IF(E43="","?",IF(ABS(E43-Proj_Curve!E43)<0.000001,"OK","CHECK")) -> OK
B44: 5.25 | C44: 5.5 | D44: =D43 -> 0.035634867 | E44: =E43/(1+D44*0.25) -> 0.82002718 | H44: =IF(E44="","?",IF(ABS(E44-Proj_Curve!E44)<0.000001,"OK","CHECK")) -> OK
B45: 5.5 | C45: 5.75 | D45: =D44 -> 0.035634867 | E45: =E44/(1+D45*0.25) -> 0.8127863 | H45: =IF(E45="","?",IF(ABS(E45-Proj_Curve!E45)<0.000001,"OK","CHECK")) -> OK
B46: 5.75 | C46: 6 | D46: =D45 -> 0.035634867 | E46: =E45/(1+D46*0.25) -> 0.80560935 | H46: =IF(E46="","?",IF(ABS(E46-Proj_Curve!E46)<0.000001,"OK","CHECK")) -> OK
B47: 6 | C47: 6.25 | D47: =D46 -> 0.035634867 | E47: =E46/(1+D47*0.25) -> 0.79849578 | H47: =IF(E47="","?",IF(ABS(E47-Proj_Curve!E47)<0.000001,"OK","CHECK")) -> OK
B48: 6.25 | C48: 6.5 | D48: =D47 -> 0.035634867 | E48: =E47/(1+D48*0.25) -> 0.79144502 | H48: =IF(E48="","?",IF(ABS(E48-Proj_Curve!E48)<0.000001,"OK","CHECK")) -> OK
B49: 6.5 | C49: 6.75 | D49: =D48 -> 0.035634867 | E49: =E48/(1+D49*0.25) -> 0.78445652 | H49: =IF(E49="","?",IF(ABS(E49-Proj_Curve!E49)<0.000001,"OK","CHECK")) -> OK
B50: 6.75 | C50: 7 | D50: =D49 -> 0.035634867 | E50: =E49/(1+D50*0.25) -> 0.77752973 | H50: =IF(E50="","?",IF(ABS(E50-Proj_Curve!E50)<0.000001,"OK","CHECK")) -> OK
B51: 7 | C51: 7.25 | D51: =E19 -> 0.035066571 | E51: =E50/(1+D51*0.25) -> 0.77077264 | H51: =IF(E51="","?",IF(ABS(E51-Proj_Curve!E51)<0.000001,"OK","CHECK")) -> OK
B52: 7.25 | C52: 7.5 | D52: =D51 -> 0.035066571 | E52: =E51/(1+D52*0.25) -> 0.76407427 | H52: =IF(E52="","?",IF(ABS(E52-Proj_Curve!E52)<0.000001,"OK","CHECK")) -> OK
B53: 7.5 | C53: 7.75 | D53: =D52 -> 0.035066571 | E53: =E52/(1+D53*0.25) -> 0.75743412 | H53: =IF(E53="","?",IF(ABS(E53-Proj_Curve!E53)<0.000001,"OK","CHECK")) -> OK
B54: 7.75 | C54: 8 | D54: =D53 -> 0.035066571 | E54: =E53/(1+D54*0.25) -> 0.75085167 | H54: =IF(E54="","?",IF(ABS(E54-Proj_Curve!E54)<0.000001,"OK","CHECK")) -> OK
B55: 8 | C55: 8.25 | D55: =D54 -> 0.035066571 | E55: =E54/(1+D55*0.25) -> 0.74432643 | H55: =IF(E55="","?",IF(ABS(E55-Proj_Curve!E55)<0.000001,"OK","CHECK")) -> OK
B56: 8.25 | C56: 8.5 | D56: =D55 -> 0.035066571 | E56: =E55/(1+D56*0.25) -> 0.73785789 | H56: =IF(E56="","?",IF(ABS(E56-Proj_Curve!E56)<0.000001,"OK","CHECK")) -> OK
B57: 8.5 | C57: 8.75 | D57: =D56 -> 0.035066571 | E57: =E56/(1+D57*0.25) -> 0.73144557 | H57: =IF(E57="","?",IF(ABS(E57-Proj_Curve!E57)<0.000001,"OK","CHECK")) -> OK
B58: 8.75 | C58: 9 | D58: =D57 -> 0.035066571 | E58: =E57/(1+D58*0.25) -> 0.72508897 | H58: =IF(E58="","?",IF(ABS(E58-Proj_Curve!E58)<0.000001,"OK","CHECK")) -> OK
B59: 9 | C59: 9.25 | D59: =D58 -> 0.035066571 | E59: =E58/(1+D59*0.25) -> 0.71878762 | H59: =IF(E59="","?",IF(ABS(E59-Proj_Curve!E59)<0.000001,"OK","CHECK")) -> OK
B60: 9.25 | C60: 9.5 | D60: =D59 -> 0.035066571 | E60: =E59/(1+D60*0.25) -> 0.71254103 | H60: =IF(E60="","?",IF(ABS(E60-Proj_Curve!E60)<0.000001,"OK","CHECK")) -> OK
B61: 9.5 | C61: 9.75 | D61: =D60 -> 0.035066571 | E61: =E60/(1+D61*0.25) -> 0.70634872 | H61: =IF(E61="","?",IF(ABS(E61-Proj_Curve!E61)<0.000001,"OK","CHECK")) -> OK
B62: 9.75 | C62: 10 | D62: =D61 -> 0.035066571 | E62: =E61/(1+D62*0.25) -> 0.70021023 | H62: =IF(E62="","?",IF(ABS(E62-Proj_Curve!E62)<0.000001,"OK","CHECK")) -> OK

Sheet TRY_Par
B1: PRACTICE: Par Swap Rates (ATM Strikes) · Yellow cells = YOUR TURN · Check col shows OK/CHECK
B2: Par Rate = PV(Float) / Annuity | PV(Float) = δ·Σ F_i·P_OIS(T_i) | Annuity = δ·Σ P_OIS(T_i)
H3: Check vs Solution
B4: Cap Maturity | C4: Annuity | D4: PV(Floating) | E4: Par Rate K | F4: Market Cap (bps)
B5: 2Y | C5: =0.25*SUM(TRY_OIS!$D$19:D26) -> 1.9185229 | D5: {=0.25*SUMPRODUCT(TRY_Proj!$D$23:D30,TRY_OIS!$D$19:D26)} -> 0.075993546 | E5: =D5/C5 -> 0.039610444 | F5: 21.897316 | H5: =IF(E5="","?",IF(ABS(E5-Par_Rates!E5)<0.000001,"OK","CHECK")) -> OK
B6: 3Y | C6: =0.25*SUM(TRY_OIS!$D$19:D30) -> 2.8284158 | D6: {=0.25*SUMPRODUCT(TRY_Proj!$D$23:D34,TRY_OIS!$D$19:D30)} -> 0.10380286 | E6: =D6/C6 -> 0.0367 | F6: 69.912719 | H6: =IF(E6="","?",IF(ABS(E6-Par_Rates!E6)<0.000001,"OK","CHECK")) -> OK
B7: 5Y | C7: =0.25*SUM(TRY_OIS!$D$19:D38) -> 4.555022 | D7: {=0.25*SUMPRODUCT(TRY_Proj!$D$23:D42,TRY_OIS!$D$19:D38)} -> 0.16580338 | E7: =D7/C7 -> 0.036400127 | F7: 143.36482 | H7: =IF(E7="","?",IF(ABS(E7-Par_Rates!E7)<0.000001,"OK","CHECK")) -> OK
B8: 7Y | C8: =0.25*SUM(TRY_OIS!$D$19:D46) -> 6.1658681 | D8: {=0.25*SUMPRODUCT(TRY_Proj!$D$23:D50,TRY_OIS!$D$19:D46)} -> 0.22320567 | E8: =D8/C8 -> 0.036200201 | F8: 219.15872 | H8: =IF(E8="","?",IF(ABS(E8-Par_Rates!E8)<0.000001,"OK","CHECK")) -> OK
B9: 10Y | C9: =0.25*SUM(TRY_OIS!$D$19:D58) -> 8.3820774 | D9: {=0.25*SUMPRODUCT(TRY_Proj!$D$23:D62,TRY_OIS!$D$19:D58)} -> 0.30092053 | E9: =D9/C9 -> 0.035900471 | F9: 333.79573 | H9: =IF(E9="","?",IF(ABS(E9-Par_Rates!E9)<0.000001,"OK","CHECK")) -> OK
